Workbook

Sheet 00_执行总览
A1: LAMDA 云控｜一期智能体执行计划
A2: 2026-09-10 智能体执行版｜当前验收=现有 OnePlus 9R b0644fb5 单机分阶段。Note9/10台/100模拟为后期扩展（非已通过、非删除）。网页高级模型定方案，本地模型实施，达到触发条件才升级诊断。原功能与安全门禁在当前机上仍须满足，不预估人力工期。
A5: 原任务映射 | D5: 新包总数 / 仍需推进 | G5: 已记录执行轮次 | J5: 开工图最长 · 层
A6: =COUNTA('04_旧任务对照'!A6:A125)&" / 120" | D6: =COUNTA('01_闭环计划'!A6:A55)&" / "&(COUNTA('01_闭环计划'!A6:A55)-COUNTIF('01_闭环计划'!D6:D55,"沿用完成")-COUNTIF('01_闭环计划'!D6:D55,"验收通过")) | G6: =SUM('01_闭环计划'!J6:J55) | J6: =MAX('01_闭环计划'!P6:P55)
A9: 边界：50包含P00已完成成果归档，P14另已单机验收，48包仍需推进。6层=5条开工依赖边；原图20条边包含验收前置，两种口径不等于交付工期对比。新包状态不会因合并自动变完成。
A12: 当前执行模式：Root + 最多3个隔离写入子智能体；P14 WEB/CONTROL/ANDROID已合并并完成OnePlus单机版本生命周期验收。当前继续按READY规则安排P09/G3检查及P15等独立模块，设备/部署仍单队列。 2026-09-15回填：integration/p14-20260909@50b4fda。闲鱼维护三件套（擦亮/下架/删除）经受控账本GATED全部真机闭环；IM聚合（范围变更，原二期提前）真机验收通过；投屏/远控第一片集成待Q04真机；DY预提交验证过、真实发布未执行（用户指示）。09表追加5行回填，01表P09/P10/P11/P28/P29/P30按真机证据更新。权威活动计划：lamda_yun_一期计划_多智能体版.xlsx（任务状态以新表01为准）。
A13: 2026-09-10：集成分支 integration/p14-20260909，P14运行修复80a5de9/1ca0c1a，设备故障测试033e5ac/5eaa2f1。已建立独立worktree；不再重复WAIT_BASELINE。P14已解锁P15，但P15及G3尚未验收。
A14: 2026-09-15：订单同步slice1全链闭环（集成c113f0e已推送；首尔orders-7adc827；真机双方向验收6单入库；后端626/1·Android339·Web178）。现在先做：维护新路径W4增量实现（标题定位→详情→管理菜单，锚点契约已冻结，GATED删除/下架复验须用户逐件授权）→ 订单slice2（详情页订单号/断点续传） | B14: 修复companion暂停任务生命周期(服务器取消不下发→本地PAUSED行永久卡队列，Q02-B真机场景的前置)；顺带runbook化无障碍重启用设置搜索路径
A15: 2026-09-16：P09 claim断开安全释放协议完成实现+两轮对抗审阅闭环（仅CLAIMED/PREFLIGHT可释放；B1卡死/B2churn已修；Android 409、后端44测试通过）。旧UNKNOWN任务保持KEEP_WAITING严禁重试。现在先做：等待用户裁决UNKNOWN（人工核验“如果历史是一群喵4”是否仍存在）；部署/真机联调需用户逐项授权。 | B15: 修复companion暂停任务生命周期(服务器取消不下发→本地PAUSED行永久卡队列，Q02-B真机场景的前置)；顺带runbook化无障碍重启用设置搜索路径
A18: 执行实测｜累计分钟不等于日历工期 | H18: 上传快照｜原进度
A19: 执行分组 | B19: 包数 | C19: 验收通过 | D19: 执行轮次 | E19: 主动分钟* | F19: 已知成本¥* | H19: 原任务状态 | L19: 项数
A20: 继承 | B20: =COUNTIF('01_闭环计划'!B6:B55,A20) | C20: 1 | D20: 1 | E20: =IF(SUMPRODUCT(--ISNUMBER('01_闭环计划'!K6:K55),--('01_闭环计划'!B6:B55=A20))=0,"",SUMIF('01_闭环计划'!B6:B55,A20,'01_闭环计划'!K6:K55)) | F20: =IF(SUMPRODUCT(--ISNUMBER('01_闭环计划'!L6:L55),--('01_闭环计划'!B6:B55=A20))=0,"",SUMIF('01_闭环计划'!B6:B55,A20,'01_闭环计划'!L6:L55)) | H20: 已完成 | L20: =COUNTIF('04_旧任务对照'!C6:C125,H20)
A21: 主链路 | B21: =COUNTIF('01_闭环计划'!B6:B55,A21) | C21: 2 | D21: =SUMIF('01_闭环计划'!B6:B55,A21,'01_闭环计划'!J6:J55) | E21: =IF(SUMPRODUCT(--ISNUMBER('01_闭环计划'!K6:K55),--('01_闭环计划'!B6:B55=A21))=0,"",SUMIF('01_闭环计划'!B6:B55,A21,'01_闭环计划'!K6:K55)) | F21: =IF(SUMPRODUCT(--ISNUMBER('01_闭环计划'!L6:L55),--('01_闭环计划'!B6:B55=A21))=0,"",SUMIF('01_闭环计划'!B6:B55,A21,'01_闭环计划'!L6:L55)) | H21: 进行中 | L21: =COUNTIF('04_旧任务对照'!C6:C125,H21)
A22: 设备与底座 | B22: =COUNTIF('01_闭环计划'!B6:B55,A22) | C22: =COUNTIFS('01_闭环计划'!B6:B55,A22,'01_闭环计划'!D6:D55,"验收通过") | D22: =SUMIF('01_闭环计划'!B6:B55,A22,'01_闭环计划'!J6:J55) | E22: =IF(SUMPRODUCT(--ISNUMBER('01_闭环计划'!K6:K55),--('01_闭环计划'!B6:B55=A22))=0,"",SUMIF('01_闭环计划'!B6:B55,A22,'01_闭环计划'!K6:K55)) | F22: =IF(SUMPRODUCT(--ISNUMBER('01_闭环计划'!L6:L55),--('01_闭环计划'!B6:B55=A22))=0,"",SUMIF('01_闭环计划'!B6:B55,A22,'01_闭环计划'!L6:L55)) | H22: 待联调 | L22: =COUNTIF('04_旧任务对照'!C6:C125,H22)
A23: 双平台发布 | B23: =COUNTIF('01_闭环计划'!B6:B55,A23) | C23: =COUNTIFS('01_闭环计划'!B6:B55,A23,'01_闭环计划'!D6:D55,"验收通过") | D23: =SUMIF('01_闭环计划'!B6:B55,A23,'01_闭环计划'!J6:J55) | E23: =IF(SUMPRODUCT(--ISNUMBER('01_闭环计划'!K6:K55),--('01_闭环计划'!B6:B55=A23))=0,"",SUMIF('01_闭环计划'!B6:B55,A23,'01_闭环计划'!K6:K55)) | F23: =IF(SUMPRODUCT(--ISNUMBER('01_闭环计划'!L6:L55),--('01_闭环计划'!B6:B55=A23))=0,"",SUMIF('01_闭环计划'!B6:B55,A23,'01_闭环计划'!L6:L55)) | H23: 未开始 | L23: =COUNTIF('04_旧任务对照'!C6:C125,H23)
A24: 闲鱼与采集 | B24: =COUNTIF('01_闭环计划'!B6:B55,A24) | C24: =COUNTIFS('01_闭环计划'!B6:B55,A24,'01_闭环计划'!D6:D55,"验收通过") | D24: =SUMIF('01_闭环计划'!B6:B55,A24,'01_闭环计划'!J6:J55) | E24: =IF(SUMPRODUCT(--ISNUMBER('01_闭环计划'!K6:K55),--('01_闭环计划'!B6:B55=A24))=0,"",SUMIF('01_闭环计划'!B6:B55,A24,'01_闭环计划'!K6:K55)) | F24: =IF(SUMPRODUCT(--ISNUMBER('01_闭环计划'!L6:L55),--('01_闭环计划'!B6:B55=A24))=0,"",SUMIF('01_闭环计划'!B6:B55,A24,'01_闭环计划'!L6:L55)) | H24: 原审阅“代码已修/待联调” | L24: =COUNTIF('07_原审阅索引'!D6:D68,"代码已修/待联调")
A25: 交付收口 | B25: =COUNTIF('01_闭环计划'!B6:B55,A25) | C25: =COUNTIFS('01_闭环计划'!B6:B55,A25,'01_闭环计划'!D6:D55,"验收通过") | D25: =SUMIF('01_闭环计划'!B6:B55,A25,'01_闭环计划'!J6:J55) | E25: =IF(SUMPRODUCT(--ISNUMBER('01_闭环计划'!K6:K55),--('01_闭环计划'!B6:B55=A25))=0,"",SUMIF('01_闭环计划'!B6:B55,A25,'01_闭环计划'!K6:K55)) | F25: =IF(SUMPRODUCT(--ISNUMBER('01_闭环计划'!L6:L55),--('01_闭环计划'!B6:B55=A25))=0,"",SUMIF('01_闭环计划'!B6:B55,A25,'01_闭环计划'!L6:L55)) | H25: *分钟/成本为已填写项之和，缺失不当免费或零耗时；完整度见06。旧状态冲突保留，待当前代码证据核实。
A26: 合计 | B26: =SUM(B20:B25) | C26: =SUM(C20:C25) | D26: =SUM(D20:D25) | E26: =IF(COUNT(E20:E25)=0,"",SUM(E20:E25)) | F26: =IF(COUNT(F20:F25)=0,"",SUM(F20:F25))
A28: 不是删范围提速：核心通过 ≠ 一期验收通过
A29: 当前验收改为 OnePlus 9R b0644fb5 单机分阶段。原范围功能（实时视频、同任务恢复、Recipe手动发布、完整产品/帖子/资源池、双平台发布、闲鱼31目录、订单与指标历史、长期保存）在当前机上仍须满足。Note9 认证与至少10台真机（及配套100模拟容量）改为后期扩展，不得标已通过，也不得永久删除。 真实副作用前的权限、单writer、提交防重和版本安全不能后补。平台入口不存在只记阻塞。单机通过 ≠ 原多机/Note9 一期完成。
A33: 怎么用这份表
A34: 01_闭环计划 | D34: 维护D/Q状态、阻塞、下一检查点与证据；J/K/L由09执行记录自动汇总。
A35: 02_验收卡 | D35: 只读取当前P卡；主路径和必要错误验证通过即结束当前检查点。
A36: 03_启动与门禁 | D36: 启动五阶段不是五天；门禁只阻止受影响操作，独立工作继续。
A37: 04_旧任务对照 | D37: 120项旧T完整映射；保留原状态、证据、契约和验收，不重复执行旧手册。
A38: 05_范围追溯 | D38: 20需求 + 12原范围 + 31闲鱼目录；逐项验收，不静默删减。
A39: 06_执行实测 | D39: 记录轮次、主动耗时、等待与成本完整度；无实测时不推算总工期。
A40: 07索引 / 08–11执行辅助 | D40: 07只追溯；08模型/子智能体分工；09逐轮日志；10当前包交接；11多智能体并行控制台与P14工作队列。
A42: 本次修改与证据边界
A43: 基于用户提供的闭环执行版于2026-09-08调整。原50包、120项映射、需求、验收和安全门禁保留；删除原38–76人日与人数换算，不把旧估算改名为AI小时。60分钟无进展检查、同错两轮升级均为建议起始策略。调用账单未提供，费用留空。原文件保留。 2026-09-08 补记本轮执行：09表写入P08/P09/P07/P01四轮；01表Q列模块通过，D列仍非验收通过。当前仓库已检查；OnePlus 9R探针已跑通。原口径「验收通过才算整包」保留。 2026-09-08 用户已确认：当前验收改为现有 OnePlus 9R b0644fb5 单机分阶段验收。红米 Note9 认证、至少10台真机及配套100模拟容量验证推迟到单机主链路通过之后，作为后期扩展：不得标成已通过，也不得从原范围永久删除。当前机上的功能与安全门禁仍须满足；单机通过 ≠ 原多机/Note9 一期完成。权威活动计划：lamda_yun_一期计划_智能体执行版.xlsx。本轮不启动 P15、不做新真机试验。 09表追加 R20260908-06。P01/P07 去掉过期「生产claim仍发旧steps」。P14 不以 worker CLOSED 为整包通过。 2026-09-09 对照当前任务更新：P14 焦点竞争硬验收通过；新增任务 0d36fe3f… 在闲鱼前台起始时成功等待 Companion 成为活动窗口，并留下 expected/actual 日志。历史失败 7f292679 未改写，签名校验未关闭。本次复跑后端 6 项测试通过、Android Recipe 定向测试构建成功。由于该 probe 仍使用内置 Recipe，且 T041 网页入口、签名 Recipe claim 固定、暂停/运行版本固定、下载中断旧版可用、回退审计尚未闭环，P14 保持进行中/开发中。09 表追加 R20260909-01；10 表切换到版本生命周期余项。 2026-09-09 多智能体方案：新增 11_多智能体并行；采用 Root Worker + 3 子智能体。编码智能体编排位于外部开发执行层，不改造成生产 Temporal Worker。READY 由合同、写集、资源锁和验证定义决定；三个子智能体必须批量创建后统一等待。当前脏工作区先做可恢复基线冻结；子智能体使用独立 worktree/branch。P14 拆为 WEB、CONTROL、ANDROID 三路并行，Root 串行合并与真机验收。09 表追加 R20260909-02。 2026-09-15回填：按W0里程碑统一回写旧表规则，09表追加R20260913-P09-02/R20260914-SCOPE-01/R20260914-P10-01/R20260915-P29-01/R20260915-P30-01五行（明细取自新表11_执行记录；时间Asia/Shanghai；Token/费用未知留空）。01表仅改D/N/Q/R/S，J/K/L仍由公式从09汇总，未手填。

Sheet 01_闭环计划
A1: 01 / 智能体功能包执行台
A2: I列为连续主动排查无新增证据的检查阈值，不是包工期。J/L/K由09记录汇总；缺失数据不当0。Q模块自测通过可结束开发，D保留真实功能验收状态；F/G不得解释为等待前置整包完成。接口解锁见08，当前施工交接见10。
A5: 新编号 | B5: 执行分组 | C5: 功能闭环 | D5: 当前状态 | E5: 执行模型 / 责任人 | F5: 所需接口来源 MUST | G5: 接通验证相关包 非整包完成前置 | H5: 必过门禁 | I5: 无进展检查 分钟（可调） | J5: 已记录轮次 | K5: 已记录主动 分钟（可缺项） | L5: 已知调用成本 人民币（可缺项） | M5: 接口可用性 非整包状态 | N5: 证据 / 当前阻塞 | O5: 原任务归属 | P5: 开工依赖 层数 | Q5: 模块开发状态 | R5: 当前阻塞类型 | S5: 下一可见交付 / 解锁边界
A6: P00 | B6: 继承 | C6: 继承基线、审阅和架构成果 | D6: 沿用完成 | E6: 待认领 | F6: 无新增包前置 | G6: 无 | H6: G0 | I6: 0 | J6: =COUNTIFS('09_执行记录'!$B$6:$B$2022,A6,'09_执行记录'!$A$6:$A$2022,"<>") | K6: =IF(COUNTIFS('09_执行记录'!$B$6:$B$2022,A6,'09_执行记录'!$A$6:$A$2022,"<>",'09_执行记录'!$H$6:$H$2022,"<>")=0,"",SUMIFS('09_执行记录'!$H$6:$H$2022,'09_执行记录'!$B$6:$B$2022,A6,'09_执行记录'!$A$6:$A$2022,"<>")) | L6: =IF(COUNTIFS('09_执行记录'!$B$6:$B$2022,A6,'09_执行记录'!$A$6:$A$2022,"<>",'09_执行记录'!$M$6:$M$2022,"<>")=0,"",SUMIFS('09_执行记录'!$M$6:$M$2022,'09_执行记录'!$B$6:$B$2022,A6,'09_执行记录'!$A$6:$A$2022,"<>")) | M6: 可用 | N6: 沿用原表T001–T003已完成；N列未附证据链接，本次未复核，不重做全仓。 | O6: T001、T002、T003 | P6: =1 | Q6: 沿用完成 | R6: 待核实 | S6: 仅登记当前分支与已有产物位置；没有代码变化不重做T001–T003。
A7: P01 | B7: 主链路 | C7: 字段映射与双平台命令工厂 | D7: 已有实现待联调 | E7: ZCode | F7: 无新增包前置 | G7: P03；P05；P07 | H7: G1 | I7: 60 | J7: =COUNTIFS('09_执行记录'!$B$6:$B$2022,A7,'09_执行记录'!$A$6:$A$2022,"<>") | K7: =IF(COUNTIFS('09_执行记录'!$B$6:$B$2022,A7,'09_执行记录'!$A$6:$A$2022,"<>",'09_执行记录'!$H$6:$H$2022,"<>")=0,"",SUMIFS('09_执行记录'!$H$6:$H$2022,'09_执行记录'!$B$6:$B$2022,A7,'09_执行记录'!$A$6:$A$2022,"<>")) | L7: =IF(COUNTIFS('09_执行记录'!$B$6:$B$2022,A7,'09_执行记录'!$A$6:$A$2022,"<>",'09_执行记录'!$M$6:$M$2022,"<>")=0,"",SUMIFS('09_执行记录'!$M$6:$M$2022,'09_执行记录'!$B$6:$B$2022,A7,'09_执行记录'!$A$6:$A$2022,"<>")) | M7: 部分可用 | N7: 模块通过：T077工厂已接；31项目录唯一归属。生产 claim 已走 CommandV1（protocolVersion=cloudctl.command/v1）。现场 device-probe ca985a89 SUCCEEDED controlEpoch=94。OPEN_ONLY 不记发布成功。不重做 field-map。 | O7: T004、T012、T077 | P7: =1 | Q7: 模块通过 | R7: 待核实 | S7: 不重做 field-map。下一可见：与 P03/P05 联调 operationId；P14 转入版本生命周期余项。
A8: P02 | B8: 主链路 | C8: 真实登录态、API与统一权限 | D8: 模块通过 | E8: 待认领 | F8: 无新增包前置 | G8: 无 | H8: G1 | I8: 60 | J8: =COUNTIFS('09_执行记录'!$B$6:$B$2022,A8,'09_执行记录'!$A$6:$A$2022,"<>") | K8: =IF(COUNTIFS('09_执行记录'!$B$6:$B$2022,A8,'09_执行记录'!$A$6:$A$2022,"<>",'09_执行记录'!$H$6:$H$2022,"<>")=0,"",SUMIFS('09_执行记录'!$H$6:$H$2022,'09_执行记录'!$B$6:$B$2022,A8,'09_执行记录'!$A$6:$A$2022,"<>")) | L8: =IF(COUNTIFS('09_执行记录'!$B$6:$B$2022,A8,'09_执行记录'!$A$6:$A$2022,"<>",'09_执行记录'!$M$6:$M$2022,"<>")=0,"",SUMIFS('09_执行记录'!$M$6:$M$2022,'09_执行记录'!$B$6:$B$2022,A8,'09_执行记录'!$A$6:$A$2022,"<>")) | M8: 部分可用 | N8: 404/501 fail-closed + 权限单测通过；真实身份联调待补 | O8: T005、T006 | P8: =1 | Q8: 继承待核实 | R8: 待核实 | S8: 按原表已记录的/session实际实现核对路由，联调现有测试；不另造/me第二套身份。
A9: P03 | B9: 主链路 | C9: 设备及双平台账号绑定、换绑隔离 | D9: 已有实现待联调 | E9: 待认领 | F9: P01；P02 | G9: P04；P06；P08 | H9: G1/G2 | I9: 60 | J9: =COUNTIFS('09_执行记录'!$B$6:$B$2022,A9,'09_执行记录'!$A$6:$A$2022,"<>") | K9: =IF(COUNTIFS('09_执行记录'!$B$6:$B$2022,A9,'09_执行记录'!$A$6:$A$2022,"<>",'09_执行记录'!$H$6:$H$2022,"<>")=0,"",SUMIFS('09_执行记录'!$H$6:$H$2022,'09_执行记录'!$B$6:$B$2022,A9,'09_执行记录'!$A$6:$A$2022,"<>")) | L9: =IF(COUNTIFS('09_执行记录'!$B$6:$B$2022,A9,'09_执行记录'!$A$6:$A$2022,"<>",'09_执行记录'!$M$6:$M$2022,"<>")=0,"",SUMIFS('09_执行记录'!$M$6:$M$2022,'09_执行记录'!$B$6:$B$2022,A9,'09_执行记录'!$A$6:$A$2022,"<>")) | M9: 部分可用 | N9: 002/003 SQL + ACCOUNT_CHANGED逻辑已有；迁移未上生产 | O9: T007、T010、T011、T086 | P9: =MAX(P7,P8)+1 | Q9: 继承待核实 | R9: 待核实 | S9: 复用002/003迁移与现有绑定接口，先在可回滚环境应用并验证；核对T011把暂停计划记为CANCELED的语义。
A10: P04 | B10: 主链路 | C10: 设备、平台能力探测与兼容底稿 | D10: 已有实现待联调 | E10: 待认领 | F10: 无新增包前置 | G10: P03；P07 | H10: G1/G7 | I10: 60 | J10: =COUNTIFS('09_执行记录'!$B$6:$B$2022,A10,'09_执行记录'!$A$6:$A$2022,"<>") | K10: =IF(COUNTIFS('09_执行记录'!$B$6:$B$2022,A10,'09_执行记录'!$A$6:$A$2022,"<>",'09_执行记录'!$H$6:$H$2022,"<>")=0,"",SUMIFS('09_执行记录'!$H$6:$H$2022,'09_执行记录'!$B$6:$B$2022,A10,'09_执行记录'!$A$6:$A$2022,"<>")) | L10: =IF(COUNTIFS('09_执行记录'!$B$6:$B$2022,A10,'09_执行记录'!$A$6:$A$2022,"<>",'09_执行记录'!$M$6:$M$2022,"<>")=0,"",SUMIFS('09_执行记录'!$M$6:$M$2022,'09_执行记录'!$B$6:$B$2022,A10,'09_执行记录'!$A$6:$A$2022,"<>")) | M10: 部分可用 | N10: heartbeat扩展字段已有。当前验收机为 OnePlus 9R b0644fb5，单机证据保留。Note9 认证与10台容量改为后期扩展，不作为当前阻塞，也不得标已通过。 | O10: T008、T009 | P10: =1 | Q10: 继承待核实 | R10: 待核实 | S10: 复用现有 OnePlus 9R 报告做当前机能力探测。Note9/多机认证推迟，不在本阶段把其资源缺口当当前阻塞。
A11: P05 | B11: 主链路 | C11: 统一任务事实、事件与任务工作台 | D11: 已有实现待联调 | E11: 待认领 | F11: P01；P02 | G11: P06；P08；P12 | H11: G1/G2 | I11: 60 | J11: =COUNTIFS('09_执行记录'!$B$6:$B$2022,A11,'09_执行记录'!$A$6:$A$2022,"<>") | K11: =IF(COUNTIFS('09_执行记录'!$B$6:$B$2022,A11,'09_执行记录'!$A$6:$A$2022,"<>",'09_执行记录'!$H$6:$H$2022,"<>")=0,"",SUMIFS('09_执行记录'!$H$6:$H$2022,'09_执行记录'!$B$6:$B$2022,A11,'09_执行记录'!$A$6:$A$2022,"<>")) | L11: =IF(COUNTIFS('09_执行记录'!$B$6:$B$2022,A11,'09_执行记录'!$A$6:$A$2022,"<>",'09_执行记录'!$M$6:$M$2022,"<>")=0,"",SUMIFS('09_执行记录'!$M$6:$M$2022,'09_执行记录'!$B$6:$B$2022,A11,'09_执行记录'!$A$6:$A$2022,"<>")) | M11: 部分可用 | N11: platform_tasks.py + 004 SQL已有；迁移未上生产 | O11: T013、T014、T028 | P11: =MAX(P7,P8)+1 | Q11: 继承待核实 | R11: 待核实 | S11: 应用并验证004迁移；沿用现有API和事件schema，先让一个真实taskId在网页完整可见。
A12: P06 | B12: 主链路 | C12: 快照冻结与立即、预约、周期调度 | D12: 已有实现待联调 | E12: 待认领 | F12: P01；P05 | G12: P03；P17；P19；P20 | H12: G1/G3 | I12: 60 | J12: =COUNTIFS('09_执行记录'!$B$6:$B$2022,A12,'09_执行记录'!$A$6:$A$2022,"<>") | K12: =IF(COUNTIFS('09_执行记录'!$B$6:$B$2022,A12,'09_执行记录'!$A$6:$A$2022,"<>",'09_执行记录'!$H$6:$H$2022,"<>")=0,"",SUMIFS('09_执行记录'!$H$6:$H$2022,'09_执行记录'!$B$6:$B$2022,A12,'09_执行记录'!$A$6:$A$2022,"<>")) | L12: =IF(COUNTIFS('09_执行记录'!$B$6:$B$2022,A12,'09_执行记录'!$A$6:$A$2022,"<>",'09_执行记录'!$M$6:$M$2022,"<>")=0,"",SUMIFS('09_执行记录'!$M$6:$M$2022,'09_执行记录'!$B$6:$B$2022,A12,'09_执行记录'!$A$6:$A$2022,"<>")) | M12: 部分可用 | N12: schedules.py + ScheduleEditor + 006 SQL已有；Temporal未接线 | O12: T015、T017、T018 | P12: =MAX(P7,P11)+1 | Q12: 继承待核实 | R12: 待核实 | S12: 先补T017的Temporal接线与006迁移，再验证一次定时触发；资源解析按P19/P20接口联调。
A13: P07 | B13: 主链路 | C13: 本地Recipe生产接线与执行生命周期 | D13: 已有实现待联调 | E13: ZCode | F13: P01；P04 | G13: P03；P05；P08；P14；P17 | H13: G1/G2/G4 | I13: 60 | J13: =COUNTIFS('09_执行记录'!$B$6:$B$2022,A13,'09_执行记录'!$A$6:$A$2022,"<>") | K13: =IF(COUNTIFS('09_执行记录'!$B$6:$B$2022,A13,'09_执行记录'!$A$6:$A$2022,"<>",'09_执行记录'!$H$6:$H$2022,"<>")=0,"",SUMIFS('09_执行记录'!$H$6:$H$2022,'09_执行记录'!$B$6:$B$2022,A13,'09_执行记录'!$A$6:$A$2022,"<>")) | L13: =IF(COUNTIFS('09_执行记录'!$B$6:$B$2022,A13,'09_执行记录'!$A$6:$A$2022,"<>",'09_执行记录'!$M$6:$M$2022,"<>")=0,"",SUMIFS('09_执行记录'!$M$6:$M$2022,'09_执行记录'!$B$6:$B$2022,A13,'09_执行记录'!$A$6:$A$2022,"<>")) | M13: 部分可用 | N13: 模块通过：生产 claim 已走 CommandV1 并接 RecipeEngine；无 legacy steps。OnePlus 探针 67d95d4a SUCCEEDED controlEpoch=93。内置 Recipe 不是 P14 已发布目录。OPEN_ONLY 不记发布成功。 | O13: T019、T020、T021、T022 | P13: =MAX(P7,P10)+1 | Q13: 模块通过 | R13: 待核实 | S13: P14 焦点硬验收已于 2026-09-09 通过；P07 不重开 CommandV1/焦点诊断。继续由 P14 验证已发布签名 Recipe 的版本固定、回退与审计。
A14: P08 | B14: 主链路 | C14: 单写锁与暂停→人工→同task恢复 | D14: 核心通过 | E14: ZCode | F14: 现有T026/T023/T016接口可先用 | G14: P03；P05；P07；P09 | H14: G2；真实副作用另须G3 | I14: 60 | J14: =COUNTIFS('09_执行记录'!$B$6:$B$2022,A14,'09_执行记录'!$A$6:$A$2022,"<>") | K14: =IF(COUNTIFS('09_执行记录'!$B$6:$B$2022,A14,'09_执行记录'!$A$6:$A$2022,"<>",'09_执行记录'!$H$6:$H$2022,"<>")=0,"",SUMIFS('09_执行记录'!$H$6:$H$2022,'09_执行记录'!$B$6:$B$2022,A14,'09_执行记录'!$A$6:$A$2022,"<>")) | L14: =IF(COUNTIFS('09_执行记录'!$B$6:$B$2022,A14,'09_执行记录'!$A$6:$A$2022,"<>",'09_执行记录'!$M$6:$M$2022,"<>")=0,"",SUMIFS('09_执行记录'!$M$6:$M$2022,'09_执行记录'!$B$6:$B$2022,A14,'09_执行记录'!$A$6:$A$2022,"<>")) | M14: 部分可用 | N14: 2026-09-10：caa22da3 CommandV1签名任务，PAUSED_WAITING_USER后保留数据安装APK，原taskId恢复RUNNING，resumeCount=2，保持1.0.3并从hold继续，started未重放；pageVerified=false拒绝409。取证后主动取消。其他G2故障不据此自动通过。见 cloudctl-source/artifacts/tasks/P14-multi-agent/P14-INTEGRATION-ACCEPTANCE/summary.md | O14: T016、T023、T026、T027 | P14: =1 | Q14: 模块通过 | R14: 待核实 | S14: 同taskId续跑不再重复开发；后续补失租立停等G2故障，P09/G3真实副作用门禁仍未过。
A15: P09 | B15: 主链路 | C15: 共享提交门禁与不确定结果核对 | D15: 进行中 | E15: ZCode | F15: P01；P08 | G15: P03；P14；P26；P28；P30；P32；P37 | H15: G3（不可后置） | I15: 60 | J15: =COUNTIFS('09_执行记录'!$B$6:$B$2022,A15,'09_执行记录'!$A$6:$A$2022,"<>") | K15: =IF(COUNTIFS('09_执行记录'!$B$6:$B$2022,A15,'09_执行记录'!$A$6:$A$2022,"<>",'09_执行记录'!$H$6:$H$2022,"<>")=0,"",SUMIFS('09_执行记录'!$H$6:$H$2022,'09_执行记录'!$B$6:$B$2022,A15,'09_执行记录'!$A$6:$A$2022,"<>")) | L15: =IF(COUNTIFS('09_执行记录'!$B$6:$B$2022,A15,'09_执行记录'!$A$6:$A$2022,"<>",'09_执行记录'!$M$6:$M$2022,"<>")=0,"",SUMIFS('09_执行记录'!$M$6:$M$2022,'09_执行记录'!$B$6:$B$2022,A15,'09_执行记录'!$A$6:$A$2022,"<>")) | M15: 部分可用 | N15: 2026-09-16：claim断开安全释放协议已实现并通过两轮对抗审阅：仅CLAIMED/PREFLIGHT可释放，首次heartbeat为执行边界，GATED/RECONCILING全阻断；B1卡死与B2 churn已修复确认。Android 409/后端44测试通过；未部署未连设备；旧UNKNOWN未触碰。 | O15: T024、T025 | P15: =MAX(P7,P14)+1 | Q15: 模块通过 | R15: 等待用户对UNKNOWN任务a25549e5的裁决（继续KEEP_WAITING或人工核验商品状态）；工程侧后续为部署release端点到首尔并构建安装新APK做真机联调，均需用户明确授权 | S15: cloudctl-source/artifacts/tasks/P09-unknown/xianyu-maintenance-20260916/release-protocol-evidence.md
A16: P10 | B16: 设备与底座 | C16: WebRTC会话、采集与实时播放器 | D16: 进行中 | E16: 待认领 | F16: P02；P04 | G16: P48 | H16: G1/G5 | I16: 60 | J16: =COUNTIFS('09_执行记录'!$B$6:$B$2022,A16,'09_执行记录'!$A$6:$A$2022,"<>") | K16: =IF(COUNTIFS('09_执行记录'!$B$6:$B$2022,A16,'09_执行记录'!$A$6:$A$2022,"<>",'09_执行记录'!$H$6:$H$2022,"<>")=0,"",SUMIFS('09_执行记录'!$H$6:$H$2022,'09_执行记录'!$B$6:$B$2022,A16,'09_执行记录'!$A$6:$A$2022,"<>")) | L16: =IF(COUNTIFS('09_执行记录'!$B$6:$B$2022,A16,'09_执行记录'!$A$6:$A$2022,"<>",'09_执行记录'!$M$6:$M$2022,"<>")=0,"",SUMIFS('09_执行记录'!$M$6:$M$2022,'09_执行记录'!$B$6:$B$2022,A16,'09_执行记录'!$A$6:$A$2022,"<>")) | M16: 未核实 | N16: 2026-09-14回填：投屏/远控第一片（JPEG帧流，WebRTC后置）已集成02a10fd：后端51过1跳；Android 197/0；web typecheck+build过。契约p10-live/20260913.1冻结。真机SIM观看/远控验收（Q04）待Root持锁。 | O16: T029、T030、T031、T032 | P16: =MAX(P8,P10)+1 | Q16: 模块通过 | R16: 待真机验收 | S16: 先做单机Q04真机验收（观看→远控交还）；WebRTC升级与长时观看重连（P12）后置；最小成功≠整包验收。
A17: P11 | B17: 设备与底座 | C17: 远控面板、手势输入与交还自动化 | D17: 进行中 | E17: 待认领 | F17: P08；P10；P07 | G17: P03；P12 | H17: G2/G5 | I17: 60 | J17: =COUNTIFS('09_执行记录'!$B$6:$B$2022,A17,'09_执行记录'!$A$6:$A$2022,"<>") | K17: =IF(COUNTIFS('09_执行记录'!$B$6:$B$2022,A17,'09_执行记录'!$A$6:$A$2022,"<>",'09_执行记录'!$H$6:$H$2022,"<>")=0,"",SUMIFS('09_执行记录'!$H$6:$H$2022,'09_执行记录'!$B$6:$B$2022,A17,'09_执行记录'!$A$6:$A$2022,"<>")) | L17: =IF(COUNTIFS('09_执行记录'!$B$6:$B$2022,A17,'09_执行记录'!$A$6:$A$2022,"<>",'09_执行记录'!$M$6:$M$2022,"<>")=0,"",SUMIFS('09_执行记录'!$M$6:$M$2022,'09_执行记录'!$B$6:$B$2022,A17,'09_执行记录'!$A$6:$A$2022,"<>")) | M17: 未核实 | N17: 2026-09-14回填：远控动作交接随实时会话第一片交付（集成02a10fd，Android 197/0）；输入通道经IM聚合自有IME闭环（焦点门禁/快照契约/会话抖动三层修复，终验6步SUCCEEDED）。完整接管→点击→交还路径待Q04真机。 | O17: T034、T035、T036、T037 | P17: =MAX(P14,P16,P13)+1 | Q17: 模块通过（第一片） | R17: 待真机验收 | S17: Q04真机验收接管→点击→交还完整路径；手势输入边界后补。
A18: P12 | B18: 设备与底座 | C18: 长时观看、重连与设备工作台 | D18: 未开始 | E18: 待认领 | F18: P10；P05 | G18: P04；P11 | H18: G5 | I18: 60 | J18: =COUNTIFS('09_执行记录'!$B$6:$B$2022,A18,'09_执行记录'!$A$6:$A$2022,"<>") | K18: =IF(COUNTIFS('09_执行记录'!$B$6:$B$2022,A18,'09_执行记录'!$A$6:$A$2022,"<>",'09_执行记录'!$H$6:$H$2022,"<>")=0,"",SUMIFS('09_执行记录'!$H$6:$H$2022,'09_执行记录'!$B$6:$B$2022,A18,'09_执行记录'!$A$6:$A$2022,"<>")) | L18: =IF(COUNTIFS('09_执行记录'!$B$6:$B$2022,A18,'09_执行记录'!$A$6:$A$2022,"<>",'09_执行记录'!$M$6:$M$2022,"<>")=0,"",SUMIFS('09_执行记录'!$M$6:$M$2022,'09_执行记录'!$B$6:$B$2022,A18,'09_执行记录'!$A$6:$A$2022,"<>")) | M18: 未核实 | N18: 原任务未开始；状态继承原上传快照；当前仓库与运行结果待核实。 | O18: T033、T038 | P18: =MAX(P16,P11)+1 | Q18: 继承待核实 | R18: 待核实 | S18: 让同一个DeviceLiveScreen进入设备详情；复用P10首帧证据，集中做30分钟与网络切换。
A19: P13 | B19: 设备与底座 | C19: 页面定位器采样与版本回归 | D19: 未开始 | E19: 待认领 | F19: P04；P07 | G19: P08；P14 | H19: G2/G4 | I19: 60 | J19: =COUNTIFS('09_执行记录'!$B$6:$B$2022,A19,'09_执行记录'!$A$6:$A$2022,"<>") | K19: =IF(COUNTIFS('09_执行记录'!$B$6:$B$2022,A19,'09_执行记录'!$A$6:$A$2022,"<>",'09_执行记录'!$H$6:$H$2022,"<>")=0,"",SUMIFS('09_执行记录'!$H$6:$H$2022,'09_执行记录'!$B$6:$B$2022,A19,'09_执行记录'!$A$6:$A$2022,"<>")) | L19: =IF(COUNTIFS('09_执行记录'!$B$6:$B$2022,A19,'09_执行记录'!$A$6:$A$2022,"<>",'09_执行记录'!$M$6:$M$2022,"<>")=0,"",SUMIFS('09_执行记录'!$M$6:$M$2022,'09_执行记录'!$B$6:$B$2022,A19,'09_执行记录'!$A$6:$A$2022,"<>")) | M19: 未核实 | N19: 原任务未开始；状态继承原上传快照；当前仓库与运行结果待核实。 | O19: T039 | P19: =MAX(P10,P13)+1 | Q19: 继承待核实 | R19: 待核实 | S19: 先采登录/首页/发布/列表等首条闭环所需页面；后续页面随相应业务包补齐。
A20: P14 | B20: 设备与底座 | C20: Recipe手动发布、签名校验与回退 | D20: 验收通过 | E20: Root Worker + 子智能体×3 | F20: P01；P02 | G20: P07；P08；P13 | H20: G4 | I20: 60 | J20: =COUNTIFS('09_执行记录'!$B$6:$B$2022,A20,'09_执行记录'!$A$6:$A$2022,"<>") | K20: =IF(COUNTIFS('09_执行记录'!$B$6:$B$2022,A20,'09_执行记录'!$A$6:$A$2022,"<>",'09_执行记录'!$H$6:$H$2022,"<>")=0,"",SUMIFS('09_执行记录'!$H$6:$H$2022,'09_执行记录'!$B$6:$B$2022,A20,'09_执行记录'!$A$6:$A$2022,"<>")) | L20: =IF(COUNTIFS('09_执行记录'!$B$6:$B$2022,A20,'09_执行记录'!$A$6:$A$2022,"<>",'09_执行记录'!$M$6:$M$2022,"<>")=0,"",SUMIFS('09_执行记录'!$M$6:$M$2022,'09_执行记录'!$B$6:$B$2022,A20,'09_执行记录'!$A$6:$A$2022,"<>")) | M20: 可用 | N20: 2026-09-10 OnePlus单机验收通过：网页人工登记/发布/回退；签名版本真实领取执行；caa22da3同任务运行中发布新版、暂停、APK重启、恢复均固定1.0.3且不重放已完成步；真实HTTPS 685→32字节截断时保留1.0.1，恢复后自动验签激活1.0.4；最后回退1.0.1并由c8ec815c探针成功。62 Android单测、3真机存储故障测试通过。见 cloudctl-source/artifacts/tasks/P14-multi-agent/P14-INTEGRATION-ACCEPTANCE/summary.md | O20: T040、T041、T042 | P20: =MAX(P7,P8)+1 | Q20: 模块通过 | R20: 无 | S20: P14依赖已解锁；允许按READY规则安排P15。P08同任务恢复已补证，其他G2故障及P09/G3仍需独立验收。公网Basic Auth登录未计入本次通过范围。
A21: P15 | B21: 设备与底座 | C21: APK整包升级与系统确认 | D21: 未开始 | E21: 待认领 | F21: P04；P14 | G21: P08；P09 | H21: G2/G4 | I21: 60 | J21: =COUNTIFS('09_执行记录'!$B$6:$B$2022,A21,'09_执行记录'!$A$6:$A$2022,"<>") | K21: =IF(COUNTIFS('09_执行记录'!$B$6:$B$2022,A21,'09_执行记录'!$A$6:$A$2022,"<>",'09_执行记录'!$H$6:$H$2022,"<>")=0,"",SUMIFS('09_执行记录'!$H$6:$H$2022,'09_执行记录'!$B$6:$B$2022,A21,'09_执行记录'!$A$6:$A$2022,"<>")) | L21: =IF(COUNTIFS('09_执行记录'!$B$6:$B$2022,A21,'09_执行记录'!$A$6:$A$2022,"<>",'09_执行记录'!$M$6:$M$2022,"<>")=0,"",SUMIFS('09_执行记录'!$M$6:$M$2022,'09_执行记录'!$B$6:$B$2022,A21,'09_执行记录'!$A$6:$A$2022,"<>")) | M21: 未核实 | N21: 原任务未开始；状态继承原上传快照；当前仓库与运行结果待核实。 | O21: T043 | P21: =MAX(P10,P20)+1 | Q21: 继承待核实 | R21: 待核实 | S21: 在现有Companion上做一次保留数据升级；不引入Root/Device Owner或静默安装前提。
A22: P16 | B22: 设备与底座 | C22: 媒体上传、持久资产与权限 | D22: 未开始 | E22: 待认领 | F22: P02 | G22: 无 | H22: G1/G6 | I22: 60 | J22: =COUNTIFS('09_执行记录'!$B$6:$B$2022,A22,'09_执行记录'!$A$6:$A$2022,"<>") | K22: =IF(COUNTIFS('09_执行记录'!$B$6:$B$2022,A22,'09_执行记录'!$A$6:$A$2022,"<>",'09_执行记录'!$H$6:$H$2022,"<>")=0,"",SUMIFS('09_执行记录'!$H$6:$H$2022,'09_执行记录'!$B$6:$B$2022,A22,'09_执行记录'!$A$6:$A$2022,"<>")) | L22: =IF(COUNTIFS('09_执行记录'!$B$6:$B$2022,A22,'09_执行记录'!$A$6:$A$2022,"<>",'09_执行记录'!$M$6:$M$2022,"<>")=0,"",SUMIFS('09_执行记录'!$M$6:$M$2022,'09_执行记录'!$B$6:$B$2022,A22,'09_执行记录'!$A$6:$A$2022,"<>")) | M22: 未核实 | N22: 原任务未开始，本次未重跑代码。 审阅B007/B015标已修，但关联任务仍未开始；先核实复用改动。 | O22: T044、T045 | P22: =MAX(P8)+1 | Q22: 继承待核实 | R22: 待核实 | S22: 先把MediaAsset接口/fixture提供给编辑器和下载模块；后端与上传UI同一包完成。
A23: P17 | B23: 设备与底座 | C23: 素材下发、流式下载与确定选取 | D23: 未开始 | E23: 待认领 | F23: P16；P06；P07 | G23: P03；P13；P14 | H23: G1/G2/G3 | I23: 60 | J23: =COUNTIFS('09_执行记录'!$B$6:$B$2022,A23,'09_执行记录'!$A$6:$A$2022,"<>") | K23: =IF(COUNTIFS('09_执行记录'!$B$6:$B$2022,A23,'09_执行记录'!$A$6:$A$2022,"<>",'09_执行记录'!$H$6:$H$2022,"<>")=0,"",SUMIFS('09_执行记录'!$H$6:$H$2022,'09_执行记录'!$B$6:$B$2022,A23,'09_执行记录'!$A$6:$A$2022,"<>")) | L23: =IF(COUNTIFS('09_执行记录'!$B$6:$B$2022,A23,'09_执行记录'!$A$6:$A$2022,"<>",'09_执行记录'!$M$6:$M$2022,"<>")=0,"",SUMIFS('09_执行记录'!$M$6:$M$2022,'09_执行记录'!$B$6:$B$2022,A23,'09_执行记录'!$A$6:$A$2022,"<>")) | M23: 未核实 | N23: 原任务未开始，本次未重跑代码。 审阅B025标已修，但关联任务仍未开始；先核实复用改动。 | O23: T046、T047、T048 | P23: =MAX(P22,P12,P13)+1 | Q23: 继承待核实 | R23: 待核实 | S23: 先下发一图一视频验证manifest；再在真实图库验证选取，不等完整发布页面全部完成。
A24: P18 | B24: 设备与底座 | C24: 文件推送与截图证据闭环 | D24: 未开始 | E24: 待认领 | F24: P16；P17 | G24: P05；P11 | H24: G1/G6 | I24: 60 | J24: =COUNTIFS('09_执行记录'!$B$6:$B$2022,A24,'09_执行记录'!$A$6:$A$2022,"<>") | K24: =IF(COUNTIFS('09_执行记录'!$B$6:$B$2022,A24,'09_执行记录'!$A$6:$A$2022,"<>",'09_执行记录'!$H$6:$H$2022,"<>")=0,"",SUMIFS('09_执行记录'!$H$6:$H$2022,'09_执行记录'!$B$6:$B$2022,A24,'09_执行记录'!$A$6:$A$2022,"<>")) | L24: =IF(COUNTIFS('09_执行记录'!$B$6:$B$2022,A24,'09_执行记录'!$A$6:$A$2022,"<>",'09_执行记录'!$M$6:$M$2022,"<>")=0,"",SUMIFS('09_执行记录'!$M$6:$M$2022,'09_执行记录'!$B$6:$B$2022,A24,'09_执行记录'!$A$6:$A$2022,"<>")) | M24: 未核实 | N24: 原任务未开始，本次未重跑代码。 审阅B028标已修，但关联任务仍未开始；先核实复用改动。 | O24: T049、T050 | P24: =MAX(P22,P23)+1 | Q24: 继承待核实 | R24: 待核实 | S24: 复用MediaDelivery与资产上传，不新建独立文件服务；先做一次推送和一次失败截图。
A25: P19 | B25: 设备与底座 | C25: 水印配置、派生素材与真实预览 | D25: 未开始 | E25: 待认领 | F25: P16 | G25: P06；P21；P28 | H25: G3/G6 | I25: 60 | J25: =COUNTIFS('09_执行记录'!$B$6:$B$2022,A25,'09_执行记录'!$A$6:$A$2022,"<>") | K25: =IF(COUNTIFS('09_执行记录'!$B$6:$B$2022,A25,'09_执行记录'!$A$6:$A$2022,"<>",'09_执行记录'!$H$6:$H$2022,"<>")=0,"",SUMIFS('09_执行记录'!$H$6:$H$2022,'09_执行记录'!$B$6:$B$2022,A25,'09_执行记录'!$A$6:$A$2022,"<>")) | L25: =IF(COUNTIFS('09_执行记录'!$B$6:$B$2022,A25,'09_执行记录'!$A$6:$A$2022,"<>",'09_执行记录'!$M$6:$M$2022,"<>")=0,"",SUMIFS('09_执行记录'!$M$6:$M$2022,'09_执行记录'!$B$6:$B$2022,A25,'09_执行记录'!$A$6:$A$2022,"<>")) | M25: 未核实 | N25: 原任务未开始；状态继承原上传快照；当前仓库与运行结果待核实。 | O25: T051、T052、T053 | P25: =MAX(P22)+1 | Q25: 继承待核实 | R25: 待核实 | S25: 复用现有派生工作流；一个模板贯通配置→预览→输出asset，随后补全field-map有效字段。
A26: P20 | B26: 设备与底座 | C26: 地址、描述和标签共享资源池 | D26: 未开始 | E26: 待认领 | F26: P02；P03 | G26: P06；P21；P28 | H26: G1/G3 | I26: 60 | J26: =COUNTIFS('09_执行记录'!$B$6:$B$2022,A26,'09_执行记录'!$A$6:$A$2022,"<>") | K26: =IF(COUNTIFS('09_执行记录'!$B$6:$B$2022,A26,'09_执行记录'!$A$6:$A$2022,"<>",'09_执行记录'!$H$6:$H$2022,"<>")=0,"",SUMIFS('09_执行记录'!$H$6:$H$2022,'09_执行记录'!$B$6:$B$2022,A26,'09_执行记录'!$A$6:$A$2022,"<>")) | L26: =IF(COUNTIFS('09_执行记录'!$B$6:$B$2022,A26,'09_执行记录'!$A$6:$A$2022,"<>",'09_执行记录'!$M$6:$M$2022,"<>")=0,"",SUMIFS('09_执行记录'!$M$6:$M$2022,'09_执行记录'!$B$6:$B$2022,A26,'09_执行记录'!$A$6:$A$2022,"<>")) | M26: 未核实 | N26: 原任务未开始；状态继承原上传快照；当前仓库与运行结果待核实。 | O26: T054、T055、T056、T057 | P26: =MAX(P8,P9)+1 | Q26: 继承待核实 | R26: 待核实 | S26: 先交共享PoolSelectionSnapshot与CRUD，再接三个薄页面；不为每类池重复建库存储。
A27: P21 | B27: 设备与底座 | C27: 商品模型、编辑、分组与列表 | D27: 未开始 | E27: 待认领 | F27: P02；P16 | G27: P19；P20 | H27: G1/G6 | I27: 60 | J27: =COUNTIFS('09_执行记录'!$B$6:$B$2022,A27,'09_执行记录'!$A$6:$A$2022,"<>") | K27: =IF(COUNTIFS('09_执行记录'!$B$6:$B$2022,A27,'09_执行记录'!$A$6:$A$2022,"<>",'09_执行记录'!$H$6:$H$2022,"<>")=0,"",SUMIFS('09_执行记录'!$H$6:$H$2022,'09_执行记录'!$B$6:$B$2022,A27,'09_执行记录'!$A$6:$A$2022,"<>")) | L27: =IF(COUNTIFS('09_执行记录'!$B$6:$B$2022,A27,'09_执行记录'!$A$6:$A$2022,"<>",'09_执行记录'!$M$6:$M$2022,"<>")=0,"",SUMIFS('09_执行记录'!$M$6:$M$2022,'09_执行记录'!$B$6:$B$2022,A27,'09_执行记录'!$A$6:$A$2022,"<>")) | M27: 未核实 | N27: 原任务T058–T062未开始；但B001标代码已修/待联调，先核实可复用变更，勿重复修复。 审阅B001/B007/B005/B006标已修，但关联任务仍未开始；先核实复用改动。 | O27: T058、T059、T060、T061、T062 | P27: =MAX(P8,P22)+1 | Q27: 继承待核实 | R27: 待核实 | S27: 先做价格/外键迁移与一条商品编辑闭环，再接列表分组；水印/池字段允许先接契约，但整包验收不能漏联调。
A28: P22 | B28: 设备与底座 | C28: 商品导入与安全导出 | D28: 未开始 | E28: 待认领 | F28: P21；P16 | G28: P24；P41 | H28: G1/G6 | I28: 60 | J28: =COUNTIFS('09_执行记录'!$B$6:$B$2022,A28,'09_执行记录'!$A$6:$A$2022,"<>") | K28: =IF(COUNTIFS('09_执行记录'!$B$6:$B$2022,A28,'09_执行记录'!$A$6:$A$2022,"<>",'09_执行记录'!$H$6:$H$2022,"<>")=0,"",SUMIFS('09_执行记录'!$H$6:$H$2022,'09_执行记录'!$B$6:$B$2022,A28,'09_执行记录'!$A$6:$A$2022,"<>")) | L28: =IF(COUNTIFS('09_执行记录'!$B$6:$B$2022,A28,'09_执行记录'!$A$6:$A$2022,"<>",'09_执行记录'!$M$6:$M$2022,"<>")=0,"",SUMIFS('09_执行记录'!$M$6:$M$2022,'09_执行记录'!$B$6:$B$2022,A28,'09_执行记录'!$A$6:$A$2022,"<>")) | M28: 未核实 | N28: 原任务未开始；状态继承原上传快照；当前仓库与运行结果待核实。 | O28: T063、T064、T065、T070 | P28: =MAX(P27,P22)+1 | Q28: 继承待核实 | R28: 待核实 | S28: 固定小样本：正常、错误行、重复批次、缺媒体；先跑后端批次，再接预览/提交页面。
A29: P23 | B29: 设备与底座 | C29: 一次性旧浏览器数据迁移 | D29: 未开始 | E29: 待认领 | F29: P21；P20；P19 | G29: P24 | H29: G6 | I29: 60 | J29: =COUNTIFS('09_执行记录'!$B$6:$B$2022,A29,'09_执行记录'!$A$6:$A$2022,"<>") | K29: =IF(COUNTIFS('09_执行记录'!$B$6:$B$2022,A29,'09_执行记录'!$A$6:$A$2022,"<>",'09_执行记录'!$H$6:$H$2022,"<>")=0,"",SUMIFS('09_执行记录'!$H$6:$H$2022,'09_执行记录'!$B$6:$B$2022,A29,'09_执行记录'!$A$6:$A$2022,"<>")) | L29: =IF(COUNTIFS('09_执行记录'!$B$6:$B$2022,A29,'09_执行记录'!$A$6:$A$2022,"<>",'09_执行记录'!$M$6:$M$2022,"<>")=0,"",SUMIFS('09_执行记录'!$M$6:$M$2022,'09_执行记录'!$B$6:$B$2022,A29,'09_执行记录'!$A$6:$A$2022,"<>")) | M29: 未核实 | N29: 原任务未开始；状态继承原上传快照；当前仓库与运行结果待核实。 | O29: T066 | P29: =MAX(P27,P26,P25)+1 | Q29: 继承待核实 | R29: 待核实 | S29: 先备份一份旧localStorage样本；与P22复用预检能力，只迁移真实数据。
A30: P24 | B30: 设备与底座 | C30: 帖子编辑、分组、修订与归档 | D30: 未开始 | E30: 待认领 | F30: P02；P16 | G30: 无 | H30: G1/G6 | I30: 60 | J30: =COUNTIFS('09_执行记录'!$B$6:$B$2022,A30,'09_执行记录'!$A$6:$A$2022,"<>") | K30: =IF(COUNTIFS('09_执行记录'!$B$6:$B$2022,A30,'09_执行记录'!$A$6:$A$2022,"<>",'09_执行记录'!$H$6:$H$2022,"<>")=0,"",SUMIFS('09_执行记录'!$H$6:$H$2022,'09_执行记录'!$B$6:$B$2022,A30,'09_执行记录'!$A$6:$A$2022,"<>")) | L30: =IF(COUNTIFS('09_执行记录'!$B$6:$B$2022,A30,'09_执行记录'!$A$6:$A$2022,"<>",'09_执行记录'!$M$6:$M$2022,"<>")=0,"",SUMIFS('09_执行记录'!$M$6:$M$2022,'09_执行记录'!$B$6:$B$2022,A30,'09_执行记录'!$A$6:$A$2022,"<>")) | M30: 未核实 | N30: 原任务未开始，本次未重跑代码。 审阅B012/B015标已修，但关联任务仍未开始；先核实复用改动。 | O30: T067、T068、T069 | P30: =MAX(P8,P22)+1 | Q30: 继承待核实 | R30: 待核实 | S30: 先做一篇图文与一篇视频内容的跨浏览器保存，再接列表/分组，不混入手机发布。
A31: P25 | B31: 双平台发布 | C31: 小红书发布命令与统一页面入口 | D31: 未开始 | E31: 待认领 | F31: P01；P06；P24 | G31: P03；P12；P26；P27 | H31: G1/G3/G4 | I31: 60 | J31: =COUNTIFS('09_执行记录'!$B$6:$B$2022,A31,'09_执行记录'!$A$6:$A$2022,"<>") | K31: =IF(COUNTIFS('09_执行记录'!$B$6:$B$2022,A31,'09_执行记录'!$A$6:$A$2022,"<>",'09_执行记录'!$H$6:$H$2022,"<>")=0,"",SUMIFS('09_执行记录'!$H$6:$H$2022,'09_执行记录'!$B$6:$B$2022,A31,'09_执行记录'!$A$6:$A$2022,"<>")) | L31: =IF(COUNTIFS('09_执行记录'!$B$6:$B$2022,A31,'09_执行记录'!$A$6:$A$2022,"<>",'09_执行记录'!$M$6:$M$2022,"<>")=0,"",SUMIFS('09_执行记录'!$M$6:$M$2022,'09_执行记录'!$B$6:$B$2022,A31,'09_执行记录'!$A$6:$A$2022,"<>")) | M31: 未核实 | N31: 原任务未开始；状态继承原上传快照；当前仓库与运行结果待核实。 | O31: T071、T076 | P31: =MAX(P7,P12,P30)+1 | Q31: 继承待核实 | R31: 待核实 | S31: 先修小红书生产允许列表并从网页生成真实命令；Recipe可先用同契约fixture开发，但不能据此记发布成功。
A32: P26 | B32: 双平台发布 | C32: 小红书图文发布与草稿完整流程 | D32: 未开始 | E32: 待认领 | F32: P07；P13；P17 | G32: P03；P09；P14；P18；P25；P27 | H32: G2/G3/G4 | I32: 60 | J32: =COUNTIFS('09_执行记录'!$B$6:$B$2022,A32,'09_执行记录'!$A$6:$A$2022,"<>") | K32: =IF(COUNTIFS('09_执行记录'!$B$6:$B$2022,A32,'09_执行记录'!$A$6:$A$2022,"<>",'09_执行记录'!$H$6:$H$2022,"<>")=0,"",SUMIFS('09_执行记录'!$H$6:$H$2022,'09_执行记录'!$B$6:$B$2022,A32,'09_执行记录'!$A$6:$A$2022,"<>")) | L32: =IF(COUNTIFS('09_执行记录'!$B$6:$B$2022,A32,'09_执行记录'!$A$6:$A$2022,"<>",'09_执行记录'!$M$6:$M$2022,"<>")=0,"",SUMIFS('09_执行记录'!$M$6:$M$2022,'09_执行记录'!$B$6:$B$2022,A32,'09_执行记录'!$A$6:$A$2022,"<>")) | M32: 未核实 | N32: 原任务未开始；状态继承原上传快照；当前仓库与运行结果待核实。 | O32: T072、T073、T075 | P32: =MAX(P13,P19,P23)+1 | Q32: 继承待核实 | R32: 待核实 | S32: 先做已发布Recipe的图文主路径，再同批验证草稿与一次提交后断网；不等待视频全完才调图文。
A33: P27 | B33: 双平台发布 | C33: 小红书视频笔记、封面与处理等待 | D33: 未开始 | E33: 待认领 | F33: P26；P17 | G33: P09；P14；P25 | H33: G2/G3/G4 | I33: 60 | J33: =COUNTIFS('09_执行记录'!$B$6:$B$2022,A33,'09_执行记录'!$A$6:$A$2022,"<>") | K33: =IF(COUNTIFS('09_执行记录'!$B$6:$B$2022,A33,'09_执行记录'!$A$6:$A$2022,"<>",'09_执行记录'!$H$6:$H$2022,"<>")=0,"",SUMIFS('09_执行记录'!$H$6:$H$2022,'09_执行记录'!$B$6:$B$2022,A33,'09_执行记录'!$A$6:$A$2022,"<>")) | L33: =IF(COUNTIFS('09_执行记录'!$B$6:$B$2022,A33,'09_执行记录'!$A$6:$A$2022,"<>",'09_执行记录'!$M$6:$M$2022,"<>")=0,"",SUMIFS('09_执行记录'!$M$6:$M$2022,'09_执行记录'!$B$6:$B$2022,A33,'09_执行记录'!$A$6:$A$2022,"<>")) | M33: 未核实 | N33: 原任务未开始；状态继承原上传快照；当前仓库与运行结果待核实。 | O33: T074 | P33: =MAX(P32,P23)+1 | Q33: 继承待核实 | R33: 待核实 | S33: 直接在P26共用Recipe能力上增加VIDEO分支；不要重复建设任务工厂、账号校验或结果上报。
A34: P28 | B34: 双平台发布 | C34: 闲鱼商品发布完整闭环 | D34: 验收通过 | E34: 待认领 | F34: P21；P07；P17 | G34: P01；P03；P06；P09；P12；P13；P14；P18；P19；P20 | H34: G2/G3/G4 | I34: 60 | J34: =COUNTIFS('09_执行记录'!$B$6:$B$2022,A34,'09_执行记录'!$A$6:$A$2022,"<>") | K34: =IF(COUNTIFS('09_执行记录'!$B$6:$B$2022,A34,'09_执行记录'!$A$6:$A$2022,"<>",'09_执行记录'!$H$6:$H$2022,"<>")=0,"",SUMIFS('09_执行记录'!$H$6:$H$2022,'09_执行记录'!$B$6:$B$2022,A34,'09_执行记录'!$A$6:$A$2022,"<>")) | L34: =IF(COUNTIFS('09_执行记录'!$B$6:$B$2022,A34,'09_执行记录'!$A$6:$A$2022,"<>",'09_执行记录'!$M$6:$M$2022,"<>")=0,"",SUMIFS('09_执行记录'!$M$6:$M$2022,'09_执行记录'!$B$6:$B$2022,A34,'09_执行记录'!$A$6:$A$2022,"<>")) | M34: 未核实 | N34: Q03真机验收通过2026-09-16：任务24c923bb(v1.1.1图全12态绿→WAITING_USER确认点)→人工填价9.90+发布→在卖187(+1)「云控平台验收测试服务¥9.9」；证据 artifacts/parallel/W5/Q03/run7-24c923bb/；遗留：PAUSED任务卡队列(问题清单) | O34: T078、T079、T080、T081 | P34: =MAX(P27,P13,P23)+1 | Q34: 模块通过 | R34: 无 | S34: 补齐完整字段+水印+资源池后整包验收；批量发布随维护定位方案解。
A35: P29 | B35: 闲鱼与采集 | C35: 擦亮、上下架与快速下架 | D35: 进行中 | E35: 待认领 | F35: P01；P07；P13 | G35: P03；P08；P09；P14 | H35: G2/G3/G4 | I35: 60 | J35: =COUNTIFS('09_执行记录'!$B$6:$B$2022,A35,'09_执行记录'!$A$6:$A$2022,"<>") | K35: =IF(COUNTIFS('09_执行记录'!$B$6:$B$2022,A35,'09_执行记录'!$A$6:$A$2022,"<>",'09_执行记录'!$H$6:$H$2022,"<>")=0,"",SUMIFS('09_执行记录'!$H$6:$H$2022,'09_执行记录'!$B$6:$B$2022,A35,'09_执行记录'!$A$6:$A$2022,"<>")) | L35: =IF(COUNTIFS('09_执行记录'!$B$6:$B$2022,A35,'09_执行记录'!$A$6:$A$2022,"<>",'09_执行记录'!$M$6:$M$2022,"<>")=0,"",SUMIFS('09_执行记录'!$M$6:$M$2022,'09_执行记录'!$B$6:$B$2022,A35,'09_执行记录'!$A$6:$A$2022,"<>")) | M35: 未核实 | N35: v2标题定位新路径已实现并装机；无意图干跑：导航→标题卡片→详情→管理菜单全通，确认弹窗GATED拦截止零副作用(在卖187不变)；真实下架复验待用户授权 | O35: T082、T083、T084、T101 | P35: =MAX(P7,P13,P19)+1 | Q35: 模块通过 | R35: 批量动作待定位方案 | S35: 批量下架随删除稳健定位方案解；titleContains待做；一轮设备会话覆盖多动作复用待验。
A36: P30 | B36: 闲鱼与采集 | C36: 商品、动态与留言安全删除 | D36: 进行中 | E36: 待认领 | F36: P01；P07；P13 | G36: P03；P08；P09；P14 | H36: G2/G3/G4 | I36: 60 | J36: =COUNTIFS('09_执行记录'!$B$6:$B$2022,A36,'09_执行记录'!$A$6:$A$2022,"<>") | K36: =IF(COUNTIFS('09_执行记录'!$B$6:$B$2022,A36,'09_执行记录'!$A$6:$A$2022,"<>",'09_执行记录'!$H$6:$H$2022,"<>")=0,"",SUMIFS('09_执行记录'!$H$6:$H$2022,'09_执行记录'!$B$6:$B$2022,A36,'09_执行记录'!$A$6:$A$2022,"<>")) | L36: =IF(COUNTIFS('09_执行记录'!$B$6:$B$2022,A36,'09_执行记录'!$A$6:$A$2022,"<>",'09_执行记录'!$M$6:$M$2022,"<>")=0,"",SUMIFS('09_执行记录'!$M$6:$M$2022,'09_执行记录'!$B$6:$B$2022,A36,'09_执行记录'!$A$6:$A$2022,"<>")) | M36: 未核实 | N36: v2删除路径同批就绪(已下架tab标题定位)；BADGE_UNREADABLE集成缝已修复(v2降级UNKNOWN→操作员核验)；真实删除复验待用户逐件授权 | O36: T085、T094、T096 | P36: =MAX(P7,P13,P19)+1 | Q36: 模块通过 | R36: 稳健定位未选型 | S36: 长期稳健定位三选一（详情页管理入口936,2245已勘察/tabs相对偏移/platformItemId映射）后再放开批量；留言/动态删除未开始。
A37: P31 | B37: 闲鱼与采集 | C37: 签到与鱼币抵扣设置 | D37: 未开始 | E37: 待认领 | F37: P01；P07；P13 | G37: P03；P09；P14 | H37: G2/G3/G4 | I37: 60 | J37: =COUNTIFS('09_执行记录'!$B$6:$B$2022,A37,'09_执行记录'!$A$6:$A$2022,"<>") | K37: =IF(COUNTIFS('09_执行记录'!$B$6:$B$2022,A37,'09_执行记录'!$A$6:$A$2022,"<>",'09_执行记录'!$H$6:$H$2022,"<>")=0,"",SUMIFS('09_执行记录'!$H$6:$H$2022,'09_执行记录'!$B$6:$B$2022,A37,'09_执行记录'!$A$6:$A$2022,"<>")) | L37: =IF(COUNTIFS('09_执行记录'!$B$6:$B$2022,A37,'09_执行记录'!$A$6:$A$2022,"<>",'09_执行记录'!$M$6:$M$2022,"<>")=0,"",SUMIFS('09_执行记录'!$M$6:$M$2022,'09_执行记录'!$B$6:$B$2022,A37,'09_执行记录'!$A$6:$A$2022,"<>")) | M37: 未核实 | N37: 原任务未开始；状态继承原上传快照；当前仓库与运行结果待核实。 | O37: T087、T088 | P37: =MAX(P7,P13,P19)+1 | Q37: 继承待核实 | R37: 待核实 | S37: 先验证当日签到读回，再验证抵扣设置及只打开模式；不把不同操作合成同一成功计数。
A38: P32 | B38: 闲鱼与采集 | C38: 鱼币推广与预算防重 | D38: 未开始 | E38: 待认领 | F38: P01；P07；P13 | G38: P03；P09；P14 | H38: G3必须先过 | I38: 60 | J38: =COUNTIFS('09_执行记录'!$B$6:$B$2022,A38,'09_执行记录'!$A$6:$A$2022,"<>") | K38: =IF(COUNTIFS('09_执行记录'!$B$6:$B$2022,A38,'09_执行记录'!$A$6:$A$2022,"<>",'09_执行记录'!$H$6:$H$2022,"<>")=0,"",SUMIFS('09_执行记录'!$H$6:$H$2022,'09_执行记录'!$B$6:$B$2022,A38,'09_执行记录'!$A$6:$A$2022,"<>")) | L38: =IF(COUNTIFS('09_执行记录'!$B$6:$B$2022,A38,'09_执行记录'!$A$6:$A$2022,"<>",'09_执行记录'!$M$6:$M$2022,"<>")=0,"",SUMIFS('09_执行记录'!$M$6:$M$2022,'09_执行记录'!$B$6:$B$2022,A38,'09_执行记录'!$A$6:$A$2022,"<>")) | M38: 未核实 | N38: 原任务未开始；状态继承原上传快照；当前仓库与运行结果待核实。 | O38: T089 | P38: =MAX(P7,P13,P19)+1 | Q38: 继承待核实 | R38: 待核实 | S38: 先验证无提交的预算/套餐检查与变更拒绝，再对明确授权的最小目标执行一次真实推广。
A39: P33 | B39: 闲鱼与采集 | C39: 小刀设置与价格下调 | D39: 未开始 | E39: 待认领 | F39: P01；P07；P13 | G39: P03；P09；P14；P21 | H39: G2/G3/G4 | I39: 60 | J39: =COUNTIFS('09_执行记录'!$B$6:$B$2022,A39,'09_执行记录'!$A$6:$A$2022,"<>") | K39: =IF(COUNTIFS('09_执行记录'!$B$6:$B$2022,A39,'09_执行记录'!$A$6:$A$2022,"<>",'09_执行记录'!$H$6:$H$2022,"<>")=0,"",SUMIFS('09_执行记录'!$H$6:$H$2022,'09_执行记录'!$B$6:$B$2022,A39,'09_执行记录'!$A$6:$A$2022,"<>")) | L39: =IF(COUNTIFS('09_执行记录'!$B$6:$B$2022,A39,'09_执行记录'!$A$6:$A$2022,"<>",'09_执行记录'!$M$6:$M$2022,"<>")=0,"",SUMIFS('09_执行记录'!$M$6:$M$2022,'09_执行记录'!$B$6:$B$2022,A39,'09_执行记录'!$A$6:$A$2022,"<>")) | M39: 未核实 | N39: 原任务未开始；状态继承原上传快照；当前仓库与运行结果待核实。 | O39: T090、T091 | P39: =MAX(P7,P13,P19)+1 | Q39: 继承待核实 | R39: 待核实 | S39: 先按原field-map核对枚举，分别做一个设置与一个明确降价目标；不把小刀当百分比降价。
A40: P34 | B40: 闲鱼与采集 | C40: 真实订单好评任务 | D40: 未开始 | E40: 待认领 | F40: P01；P07；P13 | G40: P03；P09；P14 | H40: G2/G3/G4 | I40: 60 | J40: =COUNTIFS('09_执行记录'!$B$6:$B$2022,A40,'09_执行记录'!$A$6:$A$2022,"<>") | K40: =IF(COUNTIFS('09_执行记录'!$B$6:$B$2022,A40,'09_执行记录'!$A$6:$A$2022,"<>",'09_执行记录'!$H$6:$H$2022,"<>")=0,"",SUMIFS('09_执行记录'!$H$6:$H$2022,'09_执行记录'!$B$6:$B$2022,A40,'09_执行记录'!$A$6:$A$2022,"<>")) | L40: =IF(COUNTIFS('09_执行记录'!$B$6:$B$2022,A40,'09_执行记录'!$A$6:$A$2022,"<>",'09_执行记录'!$M$6:$M$2022,"<>")=0,"",SUMIFS('09_执行记录'!$M$6:$M$2022,'09_执行记录'!$B$6:$B$2022,A40,'09_执行记录'!$A$6:$A$2022,"<>")) | M40: 未核实 | N40: 原任务未开始；状态继承原上传快照；当前仓库与运行结果待核实。 | O40: T092 | P40: =MAX(P7,P13,P19)+1 | Q40: 继承待核实 | R40: 待核实 | S40: 准备明确授权且可评价的真实订单；先核验目标范围，再单次评价取证。
A41: P35 | B41: 闲鱼与采集 | C41: 标准权限内重启闲鱼 | D41: 未开始 | E41: 待认领 | F41: P04；P07 | G41: P01；P03 | H41: G2 | I41: 60 | J41: =COUNTIFS('09_执行记录'!$B$6:$B$2022,A41,'09_执行记录'!$A$6:$A$2022,"<>") | K41: =IF(COUNTIFS('09_执行记录'!$B$6:$B$2022,A41,'09_执行记录'!$A$6:$A$2022,"<>",'09_执行记录'!$H$6:$H$2022,"<>")=0,"",SUMIFS('09_执行记录'!$H$6:$H$2022,'09_执行记录'!$B$6:$B$2022,A41,'09_执行记录'!$A$6:$A$2022,"<>")) | L41: =IF(COUNTIFS('09_执行记录'!$B$6:$B$2022,A41,'09_执行记录'!$A$6:$A$2022,"<>",'09_执行记录'!$M$6:$M$2022,"<>")=0,"",SUMIFS('09_执行记录'!$M$6:$M$2022,'09_执行记录'!$B$6:$B$2022,A41,'09_执行记录'!$A$6:$A$2022,"<>")) | M41: 未核实 | N41: 原任务未开始；状态继承原上传快照；当前仓库与运行结果待核实。 | O41: T093 | P41: =MAX(P10,P13)+1 | Q41: 继承待核实 | R41: 待核实 | S41: 复用已有launchTargetApp兜底，只补任务kind和结果语义；不要重写启动服务。
A42: P36 | B42: 闲鱼与采集 | C42: 消息删除与小红点处理 | D42: 未开始 | E42: 待认领 | F42: P01；P07；P13 | G42: P03；P09；P14 | H42: 删除分支须G3 | I42: 60 | J42: =COUNTIFS('09_执行记录'!$B$6:$B$2022,A42,'09_执行记录'!$A$6:$A$2022,"<>") | K42: =IF(COUNTIFS('09_执行记录'!$B$6:$B$2022,A42,'09_执行记录'!$A$6:$A$2022,"<>",'09_执行记录'!$H$6:$H$2022,"<>")=0,"",SUMIFS('09_执行记录'!$H$6:$H$2022,'09_执行记录'!$B$6:$B$2022,A42,'09_执行记录'!$A$6:$A$2022,"<>")) | L42: =IF(COUNTIFS('09_执行记录'!$B$6:$B$2022,A42,'09_执行记录'!$A$6:$A$2022,"<>",'09_执行记录'!$M$6:$M$2022,"<>")=0,"",SUMIFS('09_执行记录'!$M$6:$M$2022,'09_执行记录'!$B$6:$B$2022,A42,'09_执行记录'!$A$6:$A$2022,"<>")) | M42: 未核实 | N42: 原任务未开始；状态继承原上传快照；当前仓库与运行结果待核实。 | O42: T095 | P42: =MAX(P7,P13,P19)+1 | Q42: 继承待核实 | R42: 待核实 | S42: 先做只读/点红点分支，再用授权测试对话验证删除；不把两分支都映射为delete。
A43: P37 | B43: 闲鱼与采集 | C43: 草稿上架、编辑重发与快速重发 | D43: 未开始 | E43: 待认领 | F43: P28 | G43: P03；P08；P09；P14 | H43: G2/G3/G4 | I43: 60 | J43: =COUNTIFS('09_执行记录'!$B$6:$B$2022,A43,'09_执行记录'!$A$6:$A$2022,"<>") | K43: =IF(COUNTIFS('09_执行记录'!$B$6:$B$2022,A43,'09_执行记录'!$A$6:$A$2022,"<>",'09_执行记录'!$H$6:$H$2022,"<>")=0,"",SUMIFS('09_执行记录'!$H$6:$H$2022,'09_执行记录'!$B$6:$B$2022,A43,'09_执行记录'!$A$6:$A$2022,"<>")) | L43: =IF(COUNTIFS('09_执行记录'!$B$6:$B$2022,A43,'09_执行记录'!$A$6:$A$2022,"<>",'09_执行记录'!$M$6:$M$2022,"<>")=0,"",SUMIFS('09_执行记录'!$M$6:$M$2022,'09_执行记录'!$B$6:$B$2022,A43,'09_执行记录'!$A$6:$A$2022,"<>")) | M43: 未核实 | N43: 原任务未开始；状态继承原上传快照；当前仓库与运行结果待核实。 | O43: T097、T098、T100 | P43: =MAX(P34)+1 | Q43: 继承待核实 | R43: 待核实 | S43: 基于P28现成发布能力加三个薄适配器；先做单项目标，再用同一批次验证逐项恢复。
A44: P38 | B44: 闲鱼与采集 | C44: 托管无忧卖加入、退出与条款确认 | D44: 未开始 | E44: 待认领 | F44: P01；P07；P13 | G44: P03；P09；P14 | H44: G3；平台条件不足不可豁免 | I44: 60 | J44: =COUNTIFS('09_执行记录'!$B$6:$B$2022,A44,'09_执行记录'!$A$6:$A$2022,"<>") | K44: =IF(COUNTIFS('09_执行记录'!$B$6:$B$2022,A44,'09_执行记录'!$A$6:$A$2022,"<>",'09_执行记录'!$H$6:$H$2022,"<>")=0,"",SUMIFS('09_执行记录'!$H$6:$H$2022,'09_执行记录'!$B$6:$B$2022,A44,'09_执行记录'!$A$6:$A$2022,"<>")) | L44: =IF(COUNTIFS('09_执行记录'!$B$6:$B$2022,A44,'09_执行记录'!$A$6:$A$2022,"<>",'09_执行记录'!$M$6:$M$2022,"<>")=0,"",SUMIFS('09_执行记录'!$M$6:$M$2022,'09_执行记录'!$B$6:$B$2022,A44,'09_执行记录'!$A$6:$A$2022,"<>")) | M44: 未核实 | N44: 原任务未开始；状态继承原上传快照；当前仓库与运行结果待核实。 | O44: T099 | P44: =MAX(P7,P13,P19)+1 | Q44: 继承待核实 | R44: 待核实 | S44: 先核查真实账号资格和入口，不直接点同意；仅在明确条款确认后进入写操作验证。
A45: P39 | B45: 闲鱼与采集 | C45: 闲鱼发布、删除帖子可用性及实现 | D45: 未开始 | E45: 待认领 | F45: P04 | G45: P01；P07；P09；P13；P14 | H45: G3/G7；禁止静默删范围 | I45: 60 | J45: =COUNTIFS('09_执行记录'!$B$6:$B$2022,A45,'09_执行记录'!$A$6:$A$2022,"<>") | K45: =IF(COUNTIFS('09_执行记录'!$B$6:$B$2022,A45,'09_执行记录'!$A$6:$A$2022,"<>",'09_执行记录'!$H$6:$H$2022,"<>")=0,"",SUMIFS('09_执行记录'!$H$6:$H$2022,'09_执行记录'!$B$6:$B$2022,A45,'09_执行记录'!$A$6:$A$2022,"<>")) | L45: =IF(COUNTIFS('09_执行记录'!$B$6:$B$2022,A45,'09_执行记录'!$A$6:$A$2022,"<>",'09_执行记录'!$M$6:$M$2022,"<>")=0,"",SUMIFS('09_执行记录'!$M$6:$M$2022,'09_执行记录'!$B$6:$B$2022,A45,'09_执行记录'!$A$6:$A$2022,"<>")) | M45: 未核实 | N45: 原任务未开始，本次未重跑代码。 审阅B053标已修，但关联任务仍未开始；先核实复用改动。 | O45: T102 | P45: =MAX(P10)+1 | Q45: 继承待核实 | R45: 待核实 | S45: 在第一轮设备检查中提前做入口探测；后续实现才依赖命令/Recipe/定位器，避免到最后发现范围不可交付。
A46: P40 | B46: 设备与底座 | C46: 违禁词规则与发布前检查 | D46: 未开始 | E46: 待认领 | F46: P02 | G46: P21；P24；P25；P28 | H46: G1/G3 | I46: 60 | J46: =COUNTIFS('09_执行记录'!$B$6:$B$2022,A46,'09_执行记录'!$A$6:$A$2022,"<>") | K46: =IF(COUNTIFS('09_执行记录'!$B$6:$B$2022,A46,'09_执行记录'!$A$6:$A$2022,"<>",'09_执行记录'!$H$6:$H$2022,"<>")=0,"",SUMIFS('09_执行记录'!$H$6:$H$2022,'09_执行记录'!$B$6:$B$2022,A46,'09_执行记录'!$A$6:$A$2022,"<>")) | L46: =IF(COUNTIFS('09_执行记录'!$B$6:$B$2022,A46,'09_执行记录'!$A$6:$A$2022,"<>",'09_执行记录'!$M$6:$M$2022,"<>")=0,"",SUMIFS('09_执行记录'!$M$6:$M$2022,'09_执行记录'!$B$6:$B$2022,A46,'09_执行记录'!$A$6:$A$2022,"<>")) | M46: 未核实 | N46: 原任务未开始；状态继承原上传快照；当前仓库与运行结果待核实。 | O46: T103 | P46: =MAX(P8)+1 | Q46: 继承待核实 | R46: 待核实 | S46: 先提供检测DTO和服务，再接现有编辑入口；保留用户原始文案，不静默篡改。
A47: P41 | B47: 闲鱼与采集 | C47: 订单模型、同步命令与查询页面 | D47: 验收通过 | E47: W0总控+W1/W3子代理(GLM) | F47: P03；P01 | G47: P05；P06；P22；P42 | H47: G1/G6 | I47: 60 | J47: =COUNTIFS('09_执行记录'!$B$6:$B$2022,A47,'09_执行记录'!$A$6:$A$2022,"<>") | K47: =IF(COUNTIFS('09_执行记录'!$B$6:$B$2022,A47,'09_执行记录'!$A$6:$A$2022,"<>",'09_执行记录'!$H$6:$H$2022,"<>")=0,"",SUMIFS('09_执行记录'!$H$6:$H$2022,'09_执行记录'!$B$6:$B$2022,A47,'09_执行记录'!$A$6:$A$2022,"<>")) | L47: =IF(COUNTIFS('09_执行记录'!$B$6:$B$2022,A47,'09_执行记录'!$A$6:$A$2022,"<>",'09_执行记录'!$M$6:$M$2022,"<>")=0,"",SUMIFS('09_执行记录'!$M$6:$M$2022,'09_执行记录'!$B$6:$B$2022,A47,'09_执行记录'!$A$6:$A$2022,"<>")) | M47: 已核实（首尔生产orders-7adc827运行中） | N47: slice1真机验收：SOLD/BOUGHT双方向SUCCEEDED、6真实订单入库PG、幂等重放200、查询API 200；证据 artifacts/tasks/P41-P42-orders/orders-slice1-20260915/w0-acceptance/report.md | O47: T105、T106、T108 | P47: =MAX(P9,P7)+1 | Q47: 模块通过 | R47: 无（slice1范围） | S47: 订单slice2：详情页真实订单号升级order_key、occurred_at、分页断点续传
A48: P42 | B48: 闲鱼与采集 | C48: 订单真机采集与断点续传 | D48: 进行中 | E48: W0总控+W2子代理(GLM) | F48: P41；P07；P13 | G48: P03；P06；P08；P14 | H48: G2/G4/G6 | I48: 60 | J48: =COUNTIFS('09_执行记录'!$B$6:$B$2022,A48,'09_执行记录'!$A$6:$A$2022,"<>") | K48: =IF(COUNTIFS('09_执行记录'!$B$6:$B$2022,A48,'09_执行记录'!$A$6:$A$2022,"<>",'09_执行记录'!$H$6:$H$2022,"<>")=0,"",SUMIFS('09_执行记录'!$H$6:$H$2022,'09_执行记录'!$B$6:$B$2022,A48,'09_执行记录'!$A$6:$A$2022,"<>")) | L48: =IF(COUNTIFS('09_执行记录'!$B$6:$B$2022,A48,'09_执行记录'!$A$6:$A$2022,"<>",'09_执行记录'!$M$6:$M$2022,"<>")=0,"",SUMIFS('09_执行记录'!$M$6:$M$2022,'09_执行记录'!$B$6:$B$2022,A48,'09_执行记录'!$A$6:$A$2022,"<>")) | M48: 已核实（b0644fb5采集链路活跃） | N48: slice2 后端(screens/v2形状)+Web采集入口已合入并部署首尔；Android v2执行器(swipeUp步骤+跨屏去重)未做=下一切片；slice1采集已真机验收 | O48: T107 | P48: =MAX(P47,P13,P19)+1 | Q48: 模块通过（采集slice1） | R48: 断点续传/分页属slice2范围 | S48: 下一切片：Android v2执行器→多屏真机验收（采两页小样本贯通+断网续传）
A49: P43 | B49: 闲鱼与采集 | C49: 宝贝身份、历史快照与采集页面 | D49: 未开始 | E49: 待认领 | F49: P03；P01 | G49: P05；P06；P44 | H49: G1/G6 | I49: 60 | J49: =COUNTIFS('09_执行记录'!$B$6:$B$2022,A49,'09_执行记录'!$A$6:$A$2022,"<>") | K49: =IF(COUNTIFS('09_执行记录'!$B$6:$B$2022,A49,'09_执行记录'!$A$6:$A$2022,"<>",'09_执行记录'!$H$6:$H$2022,"<>")=0,"",SUMIFS('09_执行记录'!$H$6:$H$2022,'09_执行记录'!$B$6:$B$2022,A49,'09_执行记录'!$A$6:$A$2022,"<>")) | L49: =IF(COUNTIFS('09_执行记录'!$B$6:$B$2022,A49,'09_执行记录'!$A$6:$A$2022,"<>",'09_执行记录'!$M$6:$M$2022,"<>")=0,"",SUMIFS('09_执行记录'!$M$6:$M$2022,'09_执行记录'!$B$6:$B$2022,A49,'09_执行记录'!$A$6:$A$2022,"<>")) | M49: 未核实 | N49: 原任务未开始；状态继承原上传快照；当前仓库与运行结果待核实。 | O49: T109、T110、T112 | P49: =MAX(P9,P7)+1 | Q49: 继承待核实 | R49: 待核实 | S49: 先落MetricValue及批次契约，页面用结构化fixture开发；真实值由P44接入后才能验收。
A50: P44 | B50: 闲鱼与采集 | C50: 宝贝信息真实采集与恢复 | D50: 未开始 | E50: 待认领 | F50: P43；P07；P13 | G50: P03；P06；P08；P14 | H50: G2/G4/G6 | I50: 60 | J50: =COUNTIFS('09_执行记录'!$B$6:$B$2022,A50,'09_执行记录'!$A$6:$A$2022,"<>") | K50: =IF(COUNTIFS('09_执行记录'!$B$6:$B$2022,A50,'09_执行记录'!$A$6:$A$2022,"<>",'09_执行记录'!$H$6:$H$2022,"<>")=0,"",SUMIFS('09_执行记录'!$H$6:$H$2022,'09_执行记录'!$B$6:$B$2022,A50,'09_执行记录'!$A$6:$A$2022,"<>")) | L50: =IF(COUNTIFS('09_执行记录'!$B$6:$B$2022,A50,'09_执行记录'!$A$6:$A$2022,"<>",'09_执行记录'!$M$6:$M$2022,"<>")=0,"",SUMIFS('09_执行记录'!$M$6:$M$2022,'09_执行记录'!$B$6:$B$2022,A50,'09_执行记录'!$A$6:$A$2022,"<>")) | M50: 未核实 | N50: 原任务未开始；状态继承原上传快照；当前仓库与运行结果待核实。 | O50: T111 | P50: =MAX(P49,P13,P19)+1 | Q50: 继承待核实 | R50: 待核实 | S50: 先采一条完整详情与两页列表；与P42共享上传原语但不混用字段解析。
A51: P45 | B51: 交付收口 | C51: 长期保存与用户显式删除 | D51: 未开始 | E51: 待认领 | F51: P16；P03 | G51: P18；P21；P24；P41；P43 | H51: G6 | I51: 60 | J51: =COUNTIFS('09_执行记录'!$B$6:$B$2022,A51,'09_执行记录'!$A$6:$A$2022,"<>") | K51: =IF(COUNTIFS('09_执行记录'!$B$6:$B$2022,A51,'09_执行记录'!$A$6:$A$2022,"<>",'09_执行记录'!$H$6:$H$2022,"<>")=0,"",SUMIFS('09_执行记录'!$H$6:$H$2022,'09_执行记录'!$B$6:$B$2022,A51,'09_执行记录'!$A$6:$A$2022,"<>")) | L51: =IF(COUNTIFS('09_执行记录'!$B$6:$B$2022,A51,'09_执行记录'!$A$6:$A$2022,"<>",'09_执行记录'!$M$6:$M$2022,"<>")=0,"",SUMIFS('09_执行记录'!$M$6:$M$2022,'09_执行记录'!$B$6:$B$2022,A51,'09_执行记录'!$A$6:$A$2022,"<>")) | M51: 未核实 | N51: 原任务未开始；状态继承原上传快照；当前仓库与运行结果待核实。 | O51: T113 | P51: =MAX(P22,P9)+1 | Q51: 继承待核实 | R51: 待核实 | S51: 先检查已有保留/清理任务和引用计数，再把各数据域接入统一删除策略；不另造并行资产库。
A52: P46 | B52: 交付收口 | C52: 权限、并发与恢复故障回归 | D52: 未开始 | E52: 待认领 | F52: P02；P08；P09 | G52: P03；P06；P11；P14；P15；P17；P42；P44；P45 | H52: G1/G2/G3/G4/G6 | I52: 60 | J52: =COUNTIFS('09_执行记录'!$B$6:$B$2022,A52,'09_执行记录'!$A$6:$A$2022,"<>") | K52: =IF(COUNTIFS('09_执行记录'!$B$6:$B$2022,A52,'09_执行记录'!$A$6:$A$2022,"<>",'09_执行记录'!$H$6:$H$2022,"<>")=0,"",SUMIFS('09_执行记录'!$H$6:$H$2022,'09_执行记录'!$B$6:$B$2022,A52,'09_执行记录'!$A$6:$A$2022,"<>")) | L52: =IF(COUNTIFS('09_执行记录'!$B$6:$B$2022,A52,'09_执行记录'!$A$6:$A$2022,"<>",'09_执行记录'!$M$6:$M$2022,"<>")=0,"",SUMIFS('09_执行记录'!$M$6:$M$2022,'09_执行记录'!$B$6:$B$2022,A52,'09_执行记录'!$A$6:$A$2022,"<>")) | M52: 未核实 | N52: 原任务未开始；状态继承原上传快照；当前仓库与运行结果待核实。 | O52: T114、T115 | P52: =MAX(P8,P14,P15)+1 | Q52: 继承待核实 | R52: 待核实 | S52: 启动时建立最小故障矩阵；每包补相关测试，最后仅跑跨域故障组合。
A53: P47 | B53: 交付收口 | C53: 10台真机与100模拟容量验证 | D53: 未开始 | E53: 待认领 | F53: P05；P10；P17 | G53: P12；P42；P44；P48 | H53: G5/G7 | I53: 60 | J53: =COUNTIFS('09_执行记录'!$B$6:$B$2022,A53,'09_执行记录'!$A$6:$A$2022,"<>") | K53: =IF(COUNTIFS('09_执行记录'!$B$6:$B$2022,A53,'09_执行记录'!$A$6:$A$2022,"<>",'09_执行记录'!$H$6:$H$2022,"<>")=0,"",SUMIFS('09_执行记录'!$H$6:$H$2022,'09_执行记录'!$B$6:$B$2022,A53,'09_执行记录'!$A$6:$A$2022,"<>")) | L53: =IF(COUNTIFS('09_执行记录'!$B$6:$B$2022,A53,'09_执行记录'!$A$6:$A$2022,"<>",'09_执行记录'!$M$6:$M$2022,"<>")=0,"",SUMIFS('09_执行记录'!$M$6:$M$2022,'09_执行记录'!$B$6:$B$2022,A53,'09_执行记录'!$A$6:$A$2022,"<>")) | M53: 未核实 | N53: 10台真机与100模拟容量验证改为后期扩展，不作为当前单机验收阻塞，也不得标已通过或从原范围删除。当前不启动本包。 | O53: T116 | P53: =MAX(P11,P16,P23)+1 | Q53: 继承待核实 | R53: 待核实 | S53: 单机主链路通过后再启动；资源确认与容量批次推迟。推迟≠已通过。
A54: P48 | B54: 设备与底座 | C54: 诊断、公网部署与升级恢复 | D54: 未开始 | E54: 待认领 | F54: P02 | G54: P05；P10；P14；P45；P46 | H54: G1/G5/G6 | I54: 60 | J54: =COUNTIFS('09_执行记录'!$B$6:$B$2022,A54,'09_执行记录'!$A$6:$A$2022,"<>") | K54: =IF(COUNTIFS('09_执行记录'!$B$6:$B$2022,A54,'09_执行记录'!$A$6:$A$2022,"<>",'09_执行记录'!$H$6:$H$2022,"<>")=0,"",SUMIFS('09_执行记录'!$H$6:$H$2022,'09_执行记录'!$B$6:$B$2022,A54,'09_执行记录'!$A$6:$A$2022,"<>")) | L54: =IF(COUNTIFS('09_执行记录'!$B$6:$B$2022,A54,'09_执行记录'!$A$6:$A$2022,"<>",'09_执行记录'!$M$6:$M$2022,"<>")=0,"",SUMIFS('09_执行记录'!$M$6:$M$2022,'09_执行记录'!$B$6:$B$2022,A54,'09_执行记录'!$A$6:$A$2022,"<>")) | M54: 未核实 | N54: 原任务未开始；状态继承原上传快照；当前仓库与运行结果待核实。 | O54: T118、T119 | P54: =MAX(P8)+1 | Q54: 继承待核实 | R54: 待核实 | S54: 与首轮主链路同时确认现有环境；先交公网/TURN最小环境，不等权限全矩阵与全部业务验收完成。
A55: P49 | B55: 交付收口 | C55: Note9认证、31目录与一期交接 | D55: 未开始 | E55: 待认领 | F55: 无新增包前置 | G55: 全部一期包最终证据 | H55: G7/G8（最终交付） | I55: 60 | J55: =COUNTIFS('09_执行记录'!$B$6:$B$2022,A55,'09_执行记录'!$A$6:$A$2022,"<>") | K55: =IF(COUNTIFS('09_执行记录'!$B$6:$B$2022,A55,'09_执行记录'!$A$6:$A$2022,"<>",'09_执行记录'!$H$6:$H$2022,"<>")=0,"",SUMIFS('09_执行记录'!$H$6:$H$2022,'09_执行记录'!$B$6:$B$2022,A55,'09_执行记录'!$A$6:$A$2022,"<>")) | L55: =IF(COUNTIFS('09_执行记录'!$B$6:$B$2022,A55,'09_执行记录'!$A$6:$A$2022,"<>",'09_执行记录'!$M$6:$M$2022,"<>")=0,"",SUMIFS('09_执行记录'!$M$6:$M$2022,'09_执行记录'!$B$6:$B$2022,A55,'09_执行记录'!$A$6:$A$2022,"<>")) | M55: 未核实 | N55: Note9认证与10台真机改为后期扩展；当前只做 OnePlus 9R 单机分阶段证据，不得冒充 Note9/多机验收。31目录与一期交接仍保留，平台缺口保持阻塞。 | O55: T104、T117、T120 | P55: =1 | Q55: 继承待核实 | R55: 待核实 | S55: 当前维护单机证据索引；Note9/10台推迟到单机主链路通过之后。不在此重新跑120套手册。推迟≠已通过。

Sheet 02_验收卡
A1: 02 / 单包验收卡
A2: 每次只读取当前一个P包。模块自测达到固定契约可记01表Q列模块通过；整包真实场景通过才更新D列验收。代码路径是旧计划线索，施工前定向核实。按包内检查点执行，不按天等待或重复开启完整流程。
A5: 新编号 | B5: 功能包 | C5: 接手后的第一步 | D5: 核心通过标准 | E5: 整包验收 / 停止条件 | F5: 验证批次 | G5: 原代码定位线索 | H5: 旧任务 / 原表行
A6: P00 | B6: 继承基线、审阅和架构成果 | C6: 仅登记当前分支与已有产物位置；没有代码变化不重做T001–T003。 | D6: 继承原表已完成状态，不重跑全仓审阅，不再生成一轮8步骤任务。 | E6: 保留原SHA与现有ADR；N列缺失的提交/日志链接在交接时补齐。沿用完成不代表本次复核通过。 | F6: 无需重复真机 | G6: README.md；AGENTS.md；package.json；pyproject.toml；mobile/companion；apps/{web,studio}；services/*；edge/gateway；mobile/{companion,dpc}；packages/*；infra；tests；docs/adr（新增一期ADR）；services/control-api；services/temporal-worker；packages/automation-sdk | H6: T001；T002；T003｜原02表行6,7,8
A7: P01 | B7: 字段映射与双平台命令工厂 | C7: T077工厂已接。下一步与P03/P05联调operationId，不重做field-map。 | D7: 31项目录与所有启用字段有唯一归属；Python/TS/Kotlin使用同一CommandV1 fixture；工厂能生成分型参数，不依赖具体Recipe已实现。 | E7: 实际claim使用同版CommandV1；小红书允许列表贯通；未知字段/错设备拒绝；OPEN_ONLY不记执行成功。目录最终逐项验收归P49。 | F7: 契约测试为主 | G7: apps/web/src/data/operations-catalog.ts；views/OperationView.vue或实际动态页面分发入口（全库定位）；contracts/phase1（新增）；packages/api-contracts；services/control-api/src/cloudctl_api/mobile_schemas.py；APK parser；apps/web/src/views/XianyuSimpleTaskView.vue；XianyuExtraTaskView.vue；后端XianyuCommandFactory | H7: T004；T012；T077｜原02表行9,17,82
A8: P02 | B8: 真实登录态、API与统一权限 | C8: 按原表已记录的/session实际实现核对路由，联调现有测试；不另造/me第二套身份。 | D8: 复用已有session/API模式与权限集合；生产404/501失败即停止，不回退localStorage。 | E8: 真实登录读写通过；跨tenant/设备拒绝；低权限不能远控/发版；401/409/500不触发后续副作用。 | F8: API/浏览器，无强制真机 | G8: apps/web/src/api/product-catalog.ts；api/post-catalog.ts；stores/session.ts；env.d.ts；services/control-api/src/cloudctl_api/auth.py；services.py；mobile_routes.py；packages/domain权限定义 | H8: T005；T006｜原02表行10,11
A9: P03 | B9: 设备及双平台账号绑定、换绑隔离 | C9: 复用002/003迁移与现有绑定接口，先在可回滚环境应用并验证；核对T011把暂停计划记为CANCELED的语义。 | D9: 同设备每平台仅一个BOUND；闲鱼与小红书可并存；注册/重绑撤销旧凭据并递增版本。 | E9: SIM注册心跳；旧token拒绝；换绑旧任务ACCOUNT_CHANGED且历史归原账号；周期计划按约定暂停；绑定入口不保存平台密码。 | F9: 同批验证注册、双平台、换绑 | G9: services/control-api/src/cloudctl_api/mobile_service.py、db.py；mobile/companion/app/src/main/java/com/company/cloudctl/companion/security/与network/；services/control-api/src/cloudctl_api/services.py bind_account_device；mobile_service.py account_status；db.py；发布/订单/统计模型；账号页面；任务创建服务；apps/web/src/views/XianyuSimpleTaskView.vue或XianyuExtraTaskView.vue（按operation映射）；新增版本化Recipe xianyu.bind_account | H9: T007；T010；T011；T086｜原02表行12,15,16,91
A10: P04 | B10: 设备、平台能力探测与兼容底稿 | C10: 复用现有 OnePlus 9R 报告做当前机探测。Note9/10台改为后期扩展，不作为当前阻塞，也不得填通过。 | D10: 自动上报SDK/ROM、两平台包版本及权限能力，不要求用户填版本；缺能力明确reason。 | E10: 权限撤销及WiFi/SIM切换在当前机可见；卸载/未知包拒绝。Note9实际报告推迟；OnePlus 证据不能替代 Note9 认证。 | F10: 当前机开发与单机验收；Note9/多机认证为后期扩展，另见P49 | G10: mobile/companion/app/src/main/java/com/company/cloudctl/companion/device/LocalHealthCollector；service/CompanionSyncService.kt；services/control-api/src/cloudctl_api/mobile_schemas.py；mobile/companion/app/src/main/java/com/company/cloudctl/companion/automation/TargetLocatorRegistry.kt；services/control-api/src/cloudctl_api/mobile_service.py、db.py | H10: T008；T009｜原02表行13,14
A11: P05 | B11: 统一任务事实、事件与任务工作台 | C11: 应用并验证004迁移；沿用现有API和事件schema，先让一个真实taskId在网页完整可见。 | D11: 唯一PlatformTask/MobileTask事实、游标历史、幂等创建和结构化事件；队列/详情读取真实API。 | E11: 双击仅一任务；同设备FIFO、跨设备并行；暂停/失败/取消区分；刷新保留历史；恢复入口最终连接P08而非假按钮。 | F11: 与P07/P08共用一批任务证据 | G11: services/control-api/src/cloudctl_api/db.py、services.py、mobile_service.py；新增platform_tasks.py/routes；contracts/phase1/events/results；services/control-api/src/cloudctl_api/mobile_schemas.py、mobile_service.py；apps/web/src/views/TaskQueue/TaskDetail（按现有路由复用）；新增共用任务组件 | H11: T013；T014；T028｜原02表行18,19,33
A12: P06 | B12: 快照冻结与立即、预约、周期调度 | C12: 先补T017的Temporal接线与006迁移，再验证一次定时触发；资源解析按P19/P20接口联调。 | D12: 复用现有快照及ScheduleEditor；接通真实Temporal触发，不把API手动触发视为预约已完成。 | E12: 预约自动触发、周期幂等、停用不再触发；多设备独立taskId；时区/补发策略明确；资源选值/文案/素材在快照冻结，重试不漂移。 | F12: 预约与发布共用证据，调度边界自动化 | G12: 复用PublishSnapshotRow；新增通用TaskSnapshot或等价结构；services/control-api/src/cloudctl_api/services.py；services/temporal-worker；services/outbox-dispatcher；新增schedule模型/API；apps/web/src/components/ScheduleEditor.vue（新增）；所有一期任务表单 | H12: T015；T017；T018｜原02表行20,22,23
A13: P07 | B13: 本地Recipe生产接线与执行生命周期 | C13: CommandV1生产领取已接。下一步P14：人工签名发布候选Recipe到测试机。 | D13: 现有RecipeEngine接上真实领取链路；云端下发高层命令，手机本地执行，旧steps只保留兼容入口。 | E13: 真机下载并执行获准发布的指定Recipe；续租/事件上传不被主循环阻塞；未知页暂停；取消、下载失败和权限缺失不假成功。 | F13: 同包最多两批：真实领取/异常 | G13: contracts/phase1/recipe-manifest.schema.json（新增）；packages/automation-sdk；mobile/companion/app/src/main/java/com/company/cloudctl/companion/automation/（新增RecipeEngine/RecipeRegistry/RecipeContext）；mobile/companion/app/src/main/java/com/company/cloudctl/companion/service/CompanionSyncService.kt；automation/CloudCtlAccessibilityService.kt；mobile/companion/app/src/main/java/com/company/cloudctl/companion/data/AutomationStore.kt；service/CompanionSyncService.kt；network/ | H13: T019；T020；T021；T022｜原02表行24,25,26,27
A14: P08 | B14: 单写锁与暂停→人工→同task恢复 | C14: 暂停/取消/恢复门禁已接。下一步用探针补CommandV1同task续跑；不含最终提交。 | D14: 直接从T026现有成功现场接T027：暂停确认→人工处理→RESUME_CHECK→同taskId续跑，队头阻塞保持。 | E14: 继续原检查点而非第1步；旧epoch/未核对页面不得执行；失租立停；取消不可恢复；已有提交不重放；账号/版本不一致维持暂停。 | F14: 复用T026证据；补1批恢复与主要拒绝分支 | G14: services/control-api/src/cloudctl_api/mobile_service.py claim；services.py acquire_lease；db.py DeviceLeaseRow；APK执行门禁；mobile/companion/app/src/main/java/com/company/cloudctl/companion/data/AutomationStore.kt；automation/RecipeContext；PlatformTask状态机；APK RecipeContext cancel/pause token；控制API；POST task:resume；APK ResumeValidator；任务详情按钮 | H14: T016；T023；T026；T027｜原02表行21,28,31,32
A15: P09 | B15: 共享提交门禁与不确定结果核对 | C15: 双端RECONCILING加固已部署，89后端/78Android/3设备计数测试通过。真实提交接线与G3仍待验，见 cloudctl-source/artifacts/tasks/P09-unknown/hardening-20260910.md | D15: 复用ActionJournal：INTENT/APPLIED/UNKNOWN；同actionKey已成功不再执行；无可靠核对结果则保持暂停/RECONCILING。 | E15: 发布/扣费/删除前确认且参数冻结；点击后断网、丢ACK不盲重试；核对有证据才收敛；预算变化重新确认；不承诺第三方UI严格exactly-once。 | F15: 共享故障场景集中一批；各动作保留独立结果 | G15: 复用发布commit ledger；APK新增ActionJournal；服务端操作结果账；新增ReconciliationService；平台Recipe核对分支；Web任务详情 | H15: T024；T025｜原02表行29,30
A16: P10 | B16: WebRTC会话、采集与实时播放器 | C16: 包内依次交付：会话/授权→首帧→SIM relay；每段实际通过即可推进，不为每段另建任务单或重复审阅。 | D16: 打通手机授权采集→WebRTC信令/TURN→网页真实视频；只读观看不占设备写锁。 | E16: SIM公网强制relay可用；拒绝投屏授权明确显示；切换设备不串屏；断网不假实时；无观看者不持续高码率上传。720p/约20fps仅原稿建议起点。 | F16: 首帧与公网两批；记录实际耗时，30分钟稳定性观察要求另按G5保留。 | G16: control-api新增RealtimeSessionService；复用edge-hub连接职责；部署TURN；mobile/companion/app/src/main/java/com/company/cloudctl/companion/新增screen/ScreenCaptureService.kt；AndroidManifest.xml；授权Activity；mobile/companion/app/src/main/java/com/company/cloudctl/companion/新增realtime/PeerSessionManager.kt；apps/web/src/views/DeviceDetailView.vue；新增components/DeviceLiveScreen.vue | H16: T029；T030；T031；T032｜原02表行34,35,36,37
... A55: P49 | B55: Note9认证、31目录与一期交接 | C55: 当前只维护 OnePlus 9R 单机分阶段证据；Note9/10台推迟。最后跨模块交接不重跑120套手册。 | D55: 从启动起维护需求/目录证据；仅复用相关代码、契约和环境未变化的已通过用例。 | E55: 单机阶段不要求 Note9/10台通过。原 R01–R20、31目录、原120任务归属仍保留；平台不可用项保持阻塞。Note9/10台不得标已通过或永久删除，须在后期扩展中验收。 | F55: 当前 OnePlus 不得冒充 Note9；后期扩展验收不默认豁免 | G55: apps/web/src/data/operations-catalog.ts；导航/状态标签；帮助内容；docs/phase1/device-certification.md；版本包fixtures和真机证据索引；docs/phase1/acceptance.md；本Excel进度/证据列；release manifest | H55: T104；T117；T120｜原02表行109,122,125

Sheet 03_启动与门禁
A1: 03 / 从今天开始怎么推进
A2: S1–S5是启动阶段，不是天数或智能体轮数。以检查点证据推进；受阻操作停止并保留原卡，独立工作可继续。无进展检查与同错升级见08，不虚构总工期。
A5: 类型 | B5: 时段 / 编号 | C5: 目标 / 规则 | D5: 具体动作 / 准入 | E5: 不能做 / 停止条件 | F5: 交付证据 | G5: 责任 / 资源 | H5: 口径
A6: 启动阶段 | B6: S1 | C6: 先补恢复，不重新拆暂停 | D6: P08：复用T026现场完成不含最终提交的暂停→人工→同task续跑；P09：检查UNKNOWN停止与已有账本。 | E6: 不重复做T001–T003；不在门禁未过时点击真实发布/扣费/删除。 | F6: 同taskId、检查点、pauseAck、队头不越过、拒绝旧epoch的记录。 | G6: 主执行者；现有开发机 | H6: 先交无最终提交的恢复证据，不要求本阶段整包通过
A7: 启动阶段 | B7: S2 | C7: 真实身份与绑定迁移 | D7: P02 + P03前半：核实已有session/权限；在可回滚环境验证002/003等当前缺失迁移和旧token撤销。 | E7: 不直接未经备份上生产；不把单测通过当已迁移。 | F7: 真实API响应、迁移版本、旧凭据拒绝记录。 | G7: 主执行者；可回滚数据库 | H7: 实际通过即推进；缺接口/环境明确记录
A8: 启动阶段 | B8: S3 | C8: 收口契约与可用资源 | D8: P03剩余 + P01核心 + P04探测：修允许列表/工厂映射；核对当前 OnePlus 9R、目标账号可用性。Note9/10台推迟为后期扩展。 | E8: 不等定位器全集才写任务工厂；不把 OnePlus 当 Note9；推迟≠已通过。 | F8: 三端同fixture；资源缺口清单；真实版本报告。 | G8: 主执行者；用户/设备管理者配合 | H8: 资源探测启动即可做，不另增开发任务
A9: 启动阶段 | B9: S4 | C9: 让真实任务能被观察 | D9: P04剩余 + P05核心：核实004迁移，贯通创建、查询、事件、暂停/取消状态。 | E9: 不新增第二套队列/状态源；不靠前端缓存伪造成功。 | F9: 网页与服务端同一个taskId、结构化结果、刷新历史。 | G9: 主执行者 | H9: 先交真实任务可见证据，完整UI随后接通
A10: 启动阶段 | B10: S5 | C10: 打通生产领取入口，不绕发布门禁 | D10: P07接线与主链路联调；P06记录Temporal最小触发接线点。若缺合法已发布Recipe，先插入P14最小人工发布交付。 | E10: 不关闭签名、不伪造发布或真机成功；阶段不是交付时限。 | F10: CommandV1真实领取/拒绝记录；缺少发布包时明确阻塞及下一步。 | G10: 主执行者 | H10: 按实际缺口继续，不追加一轮8步骤
A11: 门禁 | B11: G0 | C11: 存量继承 | D11: T001–T003沿用，T026已有证据复用；核实分支和缺失证据即可。 | E11: 沿用完成≠本次重新验收；合包不得把部分完成自动变全完成。 | F11: 原T/新P映射；commit/证据路径补齐。 | G11: 功能包负责人+验收人 | H11: 原计划约束保留；本版集中管理
A12: 门禁 | B12: G1 | C12: 真实API与权限 | D12: 真实身份、tenant/设备隔离、401/409/500失败停止；API缺失明确失败。 | E12: 禁止生产静默localStorage/mock回退；不能用UI权限代替后端鉴权。 | F12: 真实API及负向测试；旧凭据/越权均拒绝。 | G12: 功能包负责人+验收人 | H12: 原计划约束保留；本版集中管理
A13: 门禁 | B13: G2 | C13: 设备单writer与安全恢复 | D13: 任何真实自动化/远控先验证单写锁、失租停止、暂停握手、检查点与绑定/版本核对。 | E13: 禁止AUTO与REMOTE并发写；禁止未核对页面就续跑；取消不可恢复。 | F13: Postgres并发、旧epoch拒绝、同task恢复与队头阻塞。 | G13: 功能包负责人+验收人 | H13: 原计划约束保留；本版集中管理
A14: 门禁 | B14: G3 | C14: 不可逆副作用准入 | D14: 发布/扣费/删除先确认目标与参数、写journal；UNKNOWN保持暂停/核对；成功项不重做。 | E14: 不可作为日后补测试的可选项；不得无证据重发或超预算。 | F14: 每类动作主路径+提交后断网/丢ACK；预算/目标变化拒绝。 | G14: 功能包负责人+验收人 | H14: 原计划约束保留；本版集中管理
A15: 门禁 | B15: G4 | C15: 版本发布与固定 | D15: Recipe需合法签名、验证并由用户手动发布；空闲激活，运行/暂停任务固定原版本。 | E15: 不自动发版；不为联调关签名；APK升级遵守系统确认。 | F15: 手动发布、篡改拒绝、暂停中升级/回退证据。 | G15: 功能包负责人+验收人 | H15: 原计划约束保留；本版集中管理
A16: 门禁 | B16: G5 | C16: SIM公网实时视频 | D16: 真实视频、强制TURN relay、长时观看与重连；记录网络条件、授权和设备切换。 | E16: 截图轮询不能充当实时投屏；百台在线不等于百路视频。 | F16: 30分钟观看记录；实际fps/延迟及条件，不把设计默认当硬SLA。 | G16: 功能包负责人+验收人 | H16: 原计划约束保留；本版集中管理
... A44: 多智能体 | B44: MA-06 | C44: 等待时空槽回填 | D44: P14 任一路 WAIT_LOCK/WAIT_AUTH/WAIT_HARDWARE 时，从 P08 软件证据、P16/P40、P48 只读环境等 READY 池补位。 | E44: P08/P14 真机共用设备锁；P15 仍等待 P14；不得因补位扩展二期范围。 | F44: 被阻塞项、解除条件、补位 work item。 | G44: Root Worker | H44: 避免全局等待

Sheet 04_旧任务对照
A1: 04 / 120项原任务 → 新闭环包
A2: 只读迁移账本：完整保留原任务状态、进度证据、验收与契约。原表头“所有任务未实施”与D/N列不一致，本版采用D/N逐行记录；审阅表差异另行提示。每个旧T只有一个主归属，协同验收见新卡片。
A5: 原T | B5: 原任务名称 | C5: 原状态 | D5: 原负责人 | E5: 新包 | F5: 新包状态 | G5: 原进度 / 证据（原文） | H5: 迁移提醒 | I5: 原验收（原文） | J5: 原契约（原文） | K5: 原前置（只留痕） | L5: 原表位置 / 来源
A6: T001 | B6: P0｜锁定代码并跑真实基线 | C6: 已完成 | D6: AI Agent | E6: P00 | F6: ='01_闭环计划'!D6 | G6: 未提供证据记录 | H6: 沿用完成；仅补缺失证据，不重做。 | I6: 验收1：干净环境能复跑同一SHA 验收2：失败项逐条入01代码审阅 验收3：不把mock或编译成功写成真机发布成功 | J6: 基线失败与后续回归分开记录；本次没有实际运行上述工程命令。 | K6: 无 | L6: 原工作簿/02_实施任务!A6:O6；S31、S01
A7: T002 | B7: P0｜全仓覆盖和问题补录 | C7: 已完成 | D7: AI Agent | E7: P00 | F7: ='01_闭环计划'!D6 | G7: 未提供证据记录 | H7: 沿用完成；仅补缺失证据，不重做。 | I7: 验收1：每个一级目录都有审阅状态 验收2：新旧Bug可追溯 验收3：一期外代码变更有明确原因 | J7: 覆盖率指已审阅文件/已执行测试，不能用“全仓无报错”替代业务验收。 | K7: T001 | L7: 原工作簿/02_实施任务!A7:O7；S31、S01
A8: T003 | B8: P0｜写分层ADR并确定复用边界 | C8: 已完成 | D8: AI Agent | E8: P00 | F8: ='01_闭环计划'!D6 | G8: 未提供证据记录 | H8: 沿用完成；仅补缺失证据，不重做。 | I8: 验收1：同一设备不存在两套独立写锁 验收2：有新旧功能开关及回滚路线 验收3：所有任务能定位唯一状态来源 | J8: 旧PublishPlan/Target/提交账本不得另造并行发布事实；Edge仅开发诊断。 | K8: T001 | L8: 原工作簿/02_实施任务!A8:O8；S31、S02、S03
A9: T004 | B9: P1｜逐字段盘点及31项闲鱼目录覆盖 | C9: 待联调 | D9: ZCode | E9: P01 | F9: ='01_闭环计划'!D7 | G9: 2026-09-06 field-map.json 已生成；31项闲鱼目录保留原ID；发布/删除帖子 AVAILABILITY_PENDING。Web 101 tests passed。 | H9: 复用已有代码/测试；按新包验收，未提供的证据不推定通过。 | I9: 验收1：31项均有处理归属 验收2：没有开启但未消费的字段 验收3：旧blocked不作为永不实现的依据 | J9: 字段仅存库不算发布实现；平台不支持的字段须保留数据并给出明确不支持原因。 | K9: T001 | L9: 原工作簿/02_实施任务!A9:O9；S20、S18、S17
A10: T005 | B10: P1｜生产API真相与真实登录态 | C10: 待联调 | D10: ZCode | E10: P02 | F10: ='01_闭环计划'!D8 | G10: 2026-09-06 生产 404/501 不再写 localStorage；session 从 /api/v1/session 加载。product-catalog-fail-closed.spec.ts 通过。 | H10: 复用已有代码/测试；按新包验收，未提供的证据不推定通过。 | I10: 验收1：断API保存失败且无业务本地新增 验收2：低权限不能远控/发版 验收3：清空localStorage不丢真实业务数据 | J10: UI权限只改善体验，后端必须独立鉴权；生产API缺失不能自动写本地。 | K10: T001、T003 | L10: 原工作簿/02_实施任务!A10:O10；S08、S09、S24
A11: T006 | B11: P1｜统一设备/文件/版本发布权限 | C11: 待联调 | D11: ZCode | E11: P02 | F11: ='01_闭环计划'!D8 | G11: 2026-09-06 新增 device.control/task.create/recipe.publish/data.delete；test_phase1_permissions.py 通过。 | H11: 复用已有代码/测试；按新包验收，未提供的证据不推定通过。 | I11: 验收1：跨tenant请求404/403 验收2：设备A不能读B任务/素材 验收3：发版必须操作者身份及权限 | J11: 一期单租户运行也必须过跨租户测试；后续二期不需重建所有主键。 | K11: T003 | L11: 原工作簿/02_实施任务!A11:O11；S02、S04、S05
A12: T007 | B12: P1｜设备注册、重绑与凭据撤销 | C12: 待联调 | D12: ZCode | E12: P03 | F12: ='01_闭环计划'!D9 | G12: 2026-09-06 重绑撤销旧 Companion token 并递增 controlEpoch；test_reenroll_revokes_previous_companion_instance 通过。迁移 002_device_control_epoch.sql 待生产执行。 | H12: 复用已有代码/测试；按新包验收，未提供的证据不推定通过。 | I12: 验收1：重绑后旧token401 验收2：并发注册只有一个活跃实例 验收3：手机通过SIM能注册和心跳 | J12: POST /api/v1/mobile/enrollments与/companion/v2/enroll沿用；新字段须向后兼容。 | K12: T006 | L12: 原工作簿/02_实施任务!A12:O12；S04、S03、S05
A13: T008 | B13: P1｜自动探测真实设备系统与能力 | C13: 进行中 | D13: ZCode | E13: P04 | F13: ='01_闭环计划'!D10 | G13: 2026-09-06 heartbeat 增加 sdkInt/model/network/mediaProjection。2026-09-06 ADB 真机 OnePlus LE2100 / Android 14 / SDK 34。 Companion com.company.cloudctl.companion 0.1.0 versionCode=1 minSdk=29 targetSdk=35。 闲鱼 com.taobao.idlefish 7.27.90 versionCode=516。 小红书 com.xingin.xhs 8.50.1 versionCode=8501132。 基线机型是红米 Note9，当前连接的是 OnePlus 9R，不能冒充 Note9 验收。 | H13: 复用已有代码/测试；按新包验收，未提供的证据不推定通过。 | I13: 验收1：实际Note9有设备报告 验收2：断开权限后任务前置校验失败 验收3：WiFi/蜂窝切换真实反映 | J13: heartbeat增加可选字段兼容旧APK；capability不可用需reasonCode。 | K13: T007 | L13: 原工作簿/02_实施任务!A13:O13；S30、S25、S06
A14: T009 | B14: P1｜平台包/版本/账号能力自动探测 | C14: 待联调 | D14: ZCode | E14: P04 | F14: ='01_闭环计划'!D10 | G14: 2026-09-06 真机已安装闲鱼7.27.90、小红书8.50.1、Companion 0.1.0。 CommandV1 允许 com.xingin.xhs；mobile_service._insert_task 仍只允许 Companion/闲鱼，小红书任务下发未接通。2026-09-06 ADB 真机 OnePlus LE2100 / Android 14 / SDK 34。 Companion com.company.cloudctl.companion 0.1.0 versionCode=1 minSdk=29 targetSdk=35。 闲鱼 com.taobao.idlefish 7.27.90 versionCode=516。 小红书 com.xingin.xhs 8.50.1 versionCode=8501132。 基线机型是红米 Note9，当前连接的是 OnePlus 9R，不能冒充 Note9 验收。 | H14: 复用已有代码/测试；按新包验收，未提供的证据不推定通过。 | I14: 验收1：卸载/升级后正确上报 验收2：官方单开小红书可注册 验收3：未知包本地和后端都拒绝 | J14: 版本只是适配选择与证据，不作为用户必须知道的产品输入。 | K14: T008 | L14: 原工作簿/02_实施任务!A14:O14；S04、S29、S28
A15: T010 | B15: P1｜每平台唯一账号与换绑事务 | C15: 待联调 | D15: ZCode | E15: P03 | F15: ='01_闭环计划'!D9 | G15: 2026-09-06 同设备同平台仅一条 BOUND；闲鱼+小红书可并存。 换绑递增 bindingVersion，旧排队任务 ACCOUNT_CHANGED。 tests: test_one_bound_account_per_device_platform_and_history_preserved 与 test_rebind_fails_queued_task_with_account_changed 通过。 迁移 003_account_binding_ownership.sql 未应用到生产库。 | H15: 复用已有代码/测试；按新包验收，未提供的证据不推定通过。 | I15: 验收1：1闲鱼+1小红书通过 验收2：两个闲鱼账号不能同时BOUND 验收3：换绑后旧排队任务ACCOUNT_CHANGED | J15: 不保存平台登录密码；secretRef如旧模型必填，调整为适用授权方式的可选字段。 | K15: T009、T006 | L15: 原工作簿/02_实施任务!A15:O15；S02、S04、S03
A16: T011 | B16: P1｜账号换绑后的数据归属与旧任务阻断 | C16: 待联调 | D16: ZCode | E16: P03 | F16: ='01_闭环计划'!D9 | G16: 2026-09-06 Product/Post 仍是租户资产。任务/发布目标冻结 accountId、bindingVersion、deviceIdAtExecution。 GET /api/v1/accounts/{id}/ownership 可查已解绑账号历史。换绑不改写历史 accountId。 周期计划完整模型仍待 T017；当前对 DRAFT/SCHEDULED/QUEUED 发布计划暂停为 CANCELED。 | H16: 复用已有代码/测试；按新包验收，未提供的证据不推定通过。 | I16: 验收1：甲订单依然属于甲 验收2：乙无法误执行甲任务 验收3：历史设备与当前绑定都可解释 | J16: 账号历史保留不等于永不允许删除；用户删除有独立权限与引用策略。 | K16: T010 | L16: 原工作簿/02_实施任务!A16:O16；S02、S03
A17: T012 | B17: P0｜高层指令与强类型参数契约 | C17: 待联调 | D17: ZCode | E17: P01 | F17: ='01_闭环计划'!D7 | G17: 2026-09-06 CommandV1 schema contracts/phase1/command-v1.schema.json；Python/TS/Kotlin 同 fixture。 拒绝 shell/DEX/JS/未知字段。test_command_v1.py 通过。 Companion claim 路径仍发 cloudctl.mobile/v1 steps，尚未用 CommandV1 替换生产下发。 2026-09-08 生产claim已改为cloudctl.command/v1；Companion解析command并执行builtin Recipe。 | H17: 复用已有代码/测试；按新包验收，未提供的证据不推定通过。 | I17: 验收1：三端解析同fixture一致 验收2：错设备/错账号/错schema拒绝 验收3：云端命令不含未授权执行代码 | J17: 手机只消费冻结参数和已发布本地Recipe；动态任意shell/DEX/JS执行均不在协议中。 | K17: T003、T009、T004 | L17: 原工作簿/02_实施任务!A17:O17；S06、S29、S27
A18: T013 | B18: P0｜统一业务任务API与唯一状态源 | C18: 进行中 | D18: ZCode | E18: P05 | F18: ='01_闭环计划'!D11 | G18: 2026-09-06 新增 /api/v1/platform-tasks，映射 MobileTask，不另建队列。幂等双击返回原任务；deviceIds 生成独立 taskId 共享 batchId；游标分页。取消 QUEUED→CANCELLED；ACCOUNT_CHANGED 不可 retry。test_platform_tasks.py 通过。迁移 004 未上生产库。 | H18: 复用已有代码/测试；按新包验收，未提供的证据不推定通过。 | I18: 验收1：双击只建1任务 验收2：201条历史可分页查全 验收3：跨设备并行、同设备仅顺序执行 | J18: 新增/api/v1/platform-tasks；原/api/v1/mobile/tasks为底层兼容，不另建业务队列。 终态限定SUCCEEDED/FAILED/CANCELLED/EXPIRED；REMOTE不是业务任务终态。 | K18: T012、T010 | L18: 原工作簿/02_实施任务!A18:O18；S04、S03、S02
A19: T014 | B19: P1｜步骤事件、错误和结构化结果 | C19: 进行中 | D19: ZCode | E19: P05 | F19: ='01_闭环计划'!D11 | G19: 2026-09-06 事件增加 attemptId/stepId/receivedAt；PAUSE_* 不记 FAILED；错误 resultType 422。契约 contracts/phase1/events/task-event.schema.json。现有事件重放/缺口 409 仍有效。 | H19: 复用已有代码/测试；按新包验收，未提供的证据不推定通过。 | I19: 验收1：不同失败code保持原义 验收2：事件重放不乱序 验收3：错误resultType被422拒绝 | J19: UTC保存时间；业务时区仅调度解释；不信任设备时钟作为授权有效期唯一依据。 | K19: T013 | L19: 原工作簿/02_实施任务!A19:O19；S04、S06、S26
A20: T015 | B20: P1｜不可变业务快照和资源解析规则 | C20: 待联调 | D20: ZCode | E20: P06 | F20: ='01_闭环计划'!D12 | G20: 2026-09-06 PlatformTask 创建时冻结 commandPayload 并计算 snapshotSha256；retry 复用原 parameters，不读后续编辑。完整 PublishSnapshot 池/水印解析仍待发布链路接通。 | H20: 复用已有代码/测试；按新包验收，未提供的证据不推定通过。 | I20: 验收1：旧任务文案和媒体hash不漂移 验收2：相同任务重试不重新随机 验收3：快照可以独立复现要执行的内容 | J20: 默认地址选择：设备池优先、通用池回退；用户可配置。默认规则是设计值，不伪称用户已指定。 | K20: T013 | L20: 原工作簿/02_实施任务!A20:O20；S02、S03
A21: T016 | B21: P0｜所有设备写操作共用fencing租约 | C21: 待联调 | D21: ZCode | E21: P08 | F21: ='01_闭环计划'!D14 | G21: 2026-09-06 Companion claim 复用 DeviceLeaseRow，ownerType=AUTO；PAUSE_WAITING_USER 队头阻塞后项；maintenance 禁止 AUTO claim；心跳续租。test_paused_head_blocks_later_task_and_maintenance_blocks_auto_claim 通过。迁移 005 未上生产库。APK 本地单调时钟门禁仍待 Companion 执行器。 | H21: 复用已有代码/测试；按新包验收，未提供的证据不推定通过。 | I21: 验收1：同设备并发100次claim仅1writer 验收2：旧epoch命令拒绝 验收3：maintenance禁止AUTO 验收4：下载期间不丢租 | J21: 设计初值lease60秒/续租15秒，需配置与压测；暂停只读不需要自动化writer，但设备逻辑队列仍阻塞到恢复/取消。 | K21: T013、T007 | L21: 原工作簿/02_实施任务!A21:O21；S04、S02、S03
A22: T017 | B22: P1｜预约和周期产生独立任务 | C22: 待联调 | D22: ZCode | E22: P06 | F22: ='01_闭环计划'!D12 | G22: 2026-09-07 新增 /api/v1/task-schedules。ONCE/RECURRING 触发按 scheduleId+scheduledFor+deviceId 幂等生成独立 PlatformTask；关闭计划 409；10 设备 10 taskId；换绑暂停计划。test_task_schedules.py 通过。迁移 006 未上生产库。Temporal 工作流未接线，当前为 API 触发。 | H22: 复用已有代码/测试；按新包验收，未提供的证据不推定通过。 | I22: 验收1：重复消息不重复建任务 验收2：时区/DST测试 验收3：关闭计划不再触发 验收4：10设备生成10独立任务 | J22: 设计默认：发布startDeadline到点后30分钟；订单/采集可更宽。参数可调，不当用户已确认SLA。 | K22: T013、T015 | L22: 原工作簿/02_实施任务!A22:O22；S31、S02
A23: T018 | B23: P1｜统一立即/预约/周期表单 | C23: 待联调 | D23: ZCode | E23: P06 | F23: ='01_闭环计划'!D12 | G23: 2026-09-07 ScheduleEditor 统一 IMMEDIATE/ONCE/RECURRING；闲鱼简单任务/额外任务/采集页去掉仅立即执行的旧 select。schedule-editor.spec.ts 通过。刷新后预约仍在需 Control API 联调。 | H23: 复用已有代码/测试；按新包验收，未提供的证据不推定通过。 | I23: 验收1：刷新后预约仍在 验收2：10台创建结果显示10 taskId 验收3：每页使用同一调度DTO | J23: 不新增优先级UI；批量入口只是便捷创建独立任务。 | K23: T017、T005 | L23: 原工作簿/02_实施任务!A23:O23；S15、S16、S13
A24: T019 | B24: P0｜定义可签名的手机本地状态图包 | C24: 待联调 | D24: ZCode | E24: P07 | F24: ='01_闭环计划'!D13 | G24: 2026-09-07 Recipe 签名包 schema + validate_recipe_package。test_recipe_package.py 通过。 | H24: 复用已有代码/测试；按新包验收，未提供的证据不推定通过。 | I24: 验收1：伪造/篡改/不兼容包拒绝 验收2：状态图有界 验收3：全部动作在APK白名单中 | J24: 原生新能力需要APK升级；页面和流程变化可更新数据Recipe；不开放任意远程代码执行。 | K24: T012、T003 | L24: 原工作簿/02_实施任务!A24:O24；S02、S27、S29
A25: T020 | B25: P0｜本地Recipe解释器与平台注册 | C25: 进行中 | D25: ZCode | E25: P07 | F25: ='01_闭环计划'!D13 | G25: 2026-09-07 Companion RecipeEngine 本地解释；gradle testDebugUnitTest 通过。生产 claim 仍兼容旧 steps。 2026-09-08 生产领取主入口不再发旧steps（legacyStepsEnabled默认false）。 | H25: 复用已有代码/测试；按新包验收，未提供的证据不推定通过。 | I25: 验收1：同命令独立本地完成流程 验收2：循环不会无限跑 验收3：未知页面进WAITING_USER 验收4：错recipe hash拒绝 | J25: 旧low-level steps用兼容adapter，不继续扩成第二套主引擎。 | K25: T019、T009 | L25: 原工作簿/02_实施任务!A25:O25；S27、S28、S29
A26: T021 | B26: P1｜执行生命周期、启动和下载错误修复 | C26: 待联调 | D26: ZCode | E26: P07 | F26: ='01_闭环计划'!D13 | G26: 2026-09-07 claim 后先心跳续租再下素材；launchTargetApp；锁屏/存储/无障碍 preflight；CancellationException 记 CANCELLED；ExecutorFailure.code 保留。gradle testDebugUnitTest 通过。 | H26: 复用已有代码/测试；按新包验收，未提供的证据不推定通过。 | I26: 验收1：手机桌面能启动平台 验收2：下载异常不卡RUNNING 验收3：取消不伪装失败 验收4：缺权限不会盲跑 | J26: 常亮执行是用户环境，不等于永不崩溃；不承诺自动解锁PIN或绕过系统权限。 | K26: T020、T016、T014 | L26: 原工作簿/02_实施任务!A26:O26；S25、S28、S26
A27: T022 | B27: P1｜独立事件和结果上传协程 | C27: 待联调 | D27: ZCode | E27: P07 | F27: ='01_闭环计划'!D13 | G27: 2026-09-07 独立 outboxLoop；dueEventsByTask 按任务交错上传；成功结果含 outcome/resultType；401 永久停发。 | H27: 复用已有代码/测试；按新包验收，未提供的证据不推定通过。 | I27: 验收1：长任务运行时Web及时收到steps 验收2：重连顺序正确 验收3：成功结果不是{} | J27: 仅日志可最终一致；设备控制租约和不可逆动作门禁不能等日志慢慢补。 | K27: T014、T021 | L27: 原工作簿/02_实施任务!A27:O27；S25、S26
A28: T023 | B28: P0｜持久化可恢复检查点 | C28: 待联调 | D28: ZCode | E28: P08 | F28: ='01_闭环计划'!D14 | G28: 2026-09-07 task_checkpoint 表；重启 RUNNING→RESUME_CHECK 不再 FAILED_RESTART。AutomationStoreTest checkpoint 用例通过。 | H28: 复用已有代码/测试；按新包验收，未提供的证据不推定通过。 | I28: 验收1：同taskId从检查点继续 验收2：第N项恢复不重做前N-1项 验收3：版本不匹配停下 | J28: 检查点不是屏幕截图；必须包含能判定恢复安全性的业务状态。 | K28: T020、T022、T015 | L28: 原工作簿/02_实施任务!A28:O28；S26、S27
A29: T024 | B29: P0｜发布/消耗/删除提交门禁 | C29: 待联调 | D29: ZCode | E29: P09 | F29: ='01_闭环计划'!D15 | G29: 2026-09-07 action_journal INTENT/APPLIED/UNKNOWN；同 actionKey APPLIED 不再二次点击。单元测试覆盖。真机断网二次提交仍待联调。 | H29: 复用已有代码/测试；按新包验收，未提供的证据不推定通过。 | I29: 验收1：点击发布后断网不自动再发 验收2：预算/参数变化必须重新确认 验收3：已有成功item不重复处理 | J29: 不宣称第三方UI严格exactly-once；采用可判定防重+不确定结果核对。 | K29: T023、T016 | L29: 原工作簿/02_实施任务!A29:O29；S31、S04、S26
A30: T025 | B30: P1｜不确定外部结果核对 | C30: 待联调 | E30: P09 | F30: ='01_闭环计划'!D15 | G30: 未提供证据记录 2026-09-08 服务端UNKNOWN/RECONCILING/终态ack门禁单测已补；真机断网二次提交仍无。 | H30: 复用已有代码/测试；按新包验收，未提供的证据不推定通过。 | I30: 验收1：未知状态不会自动变成功 验收2：有结果可收敛 验收3：所有人工核对可审计 | J30: 确认未成功不是无证据强制重试；平台没有可靠身份时保留不确定状态。 | K30: T024 | L30: 原工作簿/02_实施任务!A30:O30；S31、S26
A31: T026 | B31: P0｜暂停请求与安全停止握手 | C31: 已完成 | D31: ZCode | E31: P08 | F31: ='01_闭环计划'!D14 | G31: 真机联调通过 2026-09-07 任务: 54548b87-1963-40ad-a188-3f991e78f04b 状态: PAUSED_WAITING_USER, pauseAckAt=2026-09-07T15:20:52.082937Z, controlMode=REMOTE 后续任务被挡: 850060b6-649a-4573-aa6a-9cd3b9d82647 停在QUEUED 代码: CompanionSyncService心跳前移到预检; AndroidManifest补queries; launchTargetApp兜底 APK: 已编译签名安装 /tmp/cloudctl-app-debug-signed.apk 设备: OnePlus9R b0644fb5, 闲鱼未点发布 | H31: 沿用完成；仅补缺失证据，不重做。 | I31: 验收1：自动任务运行时看屏不暂停 验收2：接管前自动化确已停 验收3：暂停后后续队列不越过 | J31: 控制消息可独立于长任务主循环接收；只读观看不触发pause。 | K31: T023、T016 | L31: 原工作簿/02_实施任务!A31:O31；S04、S27、S26
A32: T027 | B32: P0｜交还控制权并继续原任务 | C32: 进行中 | D32: ZCode | E32: P08 | F32: ='01_闭环计划'!D14 | G32: 2026-09-07 接 T026：同 taskId 从检查点继续；心跳下发 RESUME；新 AUTO epoch；pageVerified=false 拒绝；不从步骤1重跑。真机恢复尚未验收。 2026-09-08 API：resume须ack；取消不可恢复。真机恢复在CommandV1路径上待补一轮。 | H32: 复用已有代码/测试；按新包验收，未提供的证据不推定通过。 | I32: 验收1：处理后继续同taskId 验收2：旧远控命令不落地 验收3：无法判定不盲目恢复 | J32: 可以自动回到安全锚点，但不能为恢复随意丢弃人工内容或重复提交。 | K32: T026、T025、T011 | L32: 原工作簿/02_实施任务!A32:O32；S26、S27
A33: T028 | B33: P1｜统一任务队列、详情与恢复入口 | C33: 进行中 | E33: P05 | F33: ='01_闭环计划'!D11 | G33: 未提供证据记录 | H33: 复用已有代码/测试；按新包验收，未提供的证据不推定通过。 | I33: 验收1：所有任务页复用同状态组件 验收2：暂停与失败视觉区分 验收3：刷新不丢历史 | J33: 长期任务历史可查；无父任务状态；batchId仅过滤。 | K33: T013、T014、T026、T027、T018 | L33: 原工作簿/02_实施任务!A33:O33；S04、S20
A34: T029 | B34: P0｜设备主动联网的WebRTC会话服务 | C34: 未开始 | E34: P10 | F34: ='01_闭环计划'!D16 | G34: 未提供证据记录 | H34: 复用已有代码/测试；按新包验收，未提供的证据不推定通过。 | I34: 验收1：SIM网络可建立relay视频 验收2：跨租户信令403 验收3：TURN凭据过期不可继续新建会话 | J34: POST /devices/{id}/rtc-sessions；WSS signaling；TURN REST短期凭据。接口名称为建议，优先复用现有路由规范。 | K34: T006、T007 | L34: 原工作簿/02_实施任务!A34:O34；S35、S36、S31
A35: T030 | B35: P0｜MediaProjection实时采集与前台服务 | C35: 未开始 | E35: P10 | F35: ='01_闭环计划'!D16 | G35: 未提供证据记录 | H35: 复用已有代码/测试；按新包验收，未提供的证据不推定通过。 | I35: 验收1：有授权可连续视频 验收2：拒绝授权不崩溃不假在线 验收3：进程死亡后重新授权路径明确 | J35: CaptureState=IDLE/NEEDS_CONSENT/ACTIVE/STOPPED/ERROR；真实能力上报。 | K35: T008、T029 | L35: 原工作簿/02_实施任务!A35:O35；S32、S37、S30
A36: T031 | B36: P1｜WebRTC连接、编码和弱网自适应 | C36: 未开始 | E36: P10 | F36: ='01_闭环计划'!D16 | G36: 未提供证据记录 | H36: 复用已有代码/测试；按新包验收，未提供的证据不推定通过。 | I36: 验收1：强制relay可用 验收2：网络恢复不重启自动任务 验收3：无viewer时无持续高码率上传 | J36: RealtimeStatsV1；视频媒体走WebRTC，任务与素材仍走既有HTTPS通道。 | K36: T030、T029 | L36: 原工作簿/02_实施任务!A36:O36；S36、S35、S32
A37: T032 | B37: P0｜可复用实时播放器与设备切换隔离 | C37: 未开始 | E37: P10 | F37: ='01_闭环计划'!D16 | G37: 未提供证据记录 | H37: 复用已有代码/测试；按新包验收，未提供的证据不推定通过。 | I37: 验收1：连续切A/B不串屏 验收2：断网显示卡顿而不是假实时 验收3：主界面真实视频 | J37: DeviceLiveScreen提供只读默认模式；控制通过独立租约能力传入。 | K37: T031 | L37: 原工作簿/02_实施任务!A37:O37；S21、S36
A38: T033 | B38: P1｜长时间观看、重连和授权状态闭环 | C38: 未开始 | E38: P12 | F38: ='01_闭环计划'!D18 | G38: 未提供证据记录 | H38: 复用已有代码/测试；按新包验收，未提供的证据不推定通过。 | I38: 验收1：30分钟观看不因120秒预览过期中断 验收2：重连不多建capture 验收3：授权丢失明确可见 | J38: 会话TTL/grace为配置；长期云端素材保留不代表永久维持录屏服务。 | K38: T032、T030 | L38: 原工作簿/02_实施任务!A38:O38；S32、S21
A39: T034 | B39: P0｜独立写控制权和时效命令协议 | C39: 未开始 | E39: P11 | F39: ='01_闭环计划'!D17 | G39: 未提供证据记录 | H39: 复用已有代码/测试；按新包验收，未提供的证据不推定通过。 | I39: 验收1：看屏不占writer 验收2：旧epoch命令无法落地 验收3：点击后断网不在重连时补点击 | J39: RemoteCommand{sessionId,controlEpoch,seq,ttlMs,viewportVersion,action,args}；RemoteAck{seq,status,executedAt}。 | K39: T026、T029、T016 | L39: 原工作簿/02_实施任务!A39:O39；S36、S04
A40: T035 | B40: P0｜手势和系统键能力 | C40: 未开始 | E40: P11 | F40: ='01_闭环计划'!D17 | G40: 未提供证据记录 | H40: 复用已有代码/测试；按新包验收，未提供的证据不推定通过。 | I40: 验收1：可Home并操作其它App 验收2：竖横屏映射正确 验收3：AUTO未暂停无法远控 | J40: 通用远控原语受REMOTE许可；自动化原语受command/platform许可。 | K40: T034、T020 | L40: 原工作簿/02_实施任务!A40:O40；S28、S36
A41: T036 | B41: P0｜屏幕操作面板与交还自动化 | C41: 未开始 | E41: P11 | F41: ='01_闭环计划'!D17 | G41: 未提供证据记录 | H41: 复用已有代码/测试；按新包验收，未提供的证据不推定通过。 | I41: 验收1：浏览器缩放不误点 验收2：接管后原taskId可恢复 验收3：关页不偷偷续跑 | J41: 独立按钮：仅观看／暂停并接管／交还并继续原任务／取消任务。 | K41: T035、T032、T027 | L41: 原工作簿/02_实施任务!A41:O41；S21
A42: T037 | B42: P1｜明确能力边界的输入与复制粘贴 | C42: 未开始 | E42: P11 | F42: ='01_闭环计划'!D17 | G42: 未提供证据记录 | H42: 复用已有代码/测试；按新包验收，未提供的证据不推定通过。 | I42: 验收1：中文文本可写 验收2：受限复制清楚提示 验收3：日志不泄露剪贴板内容 | J42: ClipboardBridge是显式用户动作；不承诺所有App的双向实时剪贴板。 | K42: T035、T036 | L42: 原工作簿/02_实施任务!A42:O42；S33、S28
A43: T038 | B43: P1｜设备卡片、能力和任务观察接入 | C43: 未开始 | E43: P12 | F43: ='01_闭环计划'!D18 | G43: 未提供证据记录 | H43: 复用已有代码/测试；按新包验收，未提供的证据不推定通过。 | I43: 验收1：任务中能实时看屏 验收2：SIM网络显示真实类型 验收3：缺权限可定位 | J43: GET device detail返回capabilities、accounts、activeTask、networkTelemetry和captureState。 | K43: T028、T032、T036、T008 | L43: 原工作簿/02_实施任务!A43:O43；S21、S24
A44: T039 | B44: P1｜自动探测版本的定位器采样与回归 | C44: 未开始 | E44: P13 | F44: ='01_闭环计划'!D19 | G44: 未提供证据记录 | H44: 复用已有代码/测试；按新包验收，未提供的证据不推定通过。 | I44: 验收1：多匹配拒绝盲点 验收2：App升级后安全暂停 验收3：真机采样可重复运行 | J44: LocatorSet{platform,appVersionRange,pageStates,selectors,postconditions}；脚本新版本须回归fixture。 | K44: T009、T020、T023 | L44: 原工作簿/02_实施任务!A44:O44；S29、S28
A45: T040 | B45: P0｜复用现有签名/晋级的人工发布流程 | C45: 未开始 | E45: P14 | F45: ='01_闭环计划'!D20 | G45: 未提供证据记录 | H45: 进度口径差异：审阅B052已修；任务仍未开始。只核对相关变更，不自动改状态。 | I45: 验收1：未点击发布设备不获生效指令 验收2：篡改包拒绝 验收3：每次发布可审计 | J45: PublishRequest{versionId,targetDeviceIds,idempotencyKey}；已发布包不可原地修改。 | K45: T019、T006、T039 | L45: 原工作簿/02_实施任务!A45:O45；S31、S03
A46: T041 | B46: P1｜版本查看、验证结果和手动发布按钮 | C46: 未开始 | E46: P14 | F46: ='01_闭环计划'!D20 | G46: 未提供证据记录 | H46: 进度口径差异：审阅B052已修；任务仍未开始。只核对相关变更，不自动改状态。 | I46: 验收1：后台点发布才推送 验收2：离线设备可补领 验收3：能追踪每机版本 | J46: 不提供自动发布开关作为一期默认；用户要求B流程。 | K46: T040 | L46: 原工作簿/02_实施任务!A46:O46；S31
A47: T042 | B47: P1｜签名校验、空闲激活与版本回退 | C47: 未开始 | E47: P14 | F47: ='01_闭环计划'!D20 | G47: 未提供证据记录 | H47: 进度口径差异：审阅B052已修；任务仍未开始。只核对相关变更，不自动改状态。 | I47: 验收1：下载中断旧版可用 验收2：暂停任务升级后仍可恢复旧版 验收3：无签名包不执行 | J47: 版本激活是原子指针切换；历史包保留到所有引用任务结束及保留规则允许删除。 | K47: T040、T023 | L47: 原工作簿/02_实施任务!A47:O47；S31、S26
A48: T043 | B48: P1｜整包更新与系统安装确认 | C48: 未开始 | E48: P15 | F48: ='01_闭环计划'!D21 | G48: 未提供证据记录 | H48: 复用已有代码/测试；按新包验收，未提供的证据不推定通过。 | I48: 验收1：新APK可升级且保留数据 验收2：用户拒绝有状态 验收3：升级不重复执行已提交动作 | J48: APK安装受Android系统政策；Recipe回退不等于Android APK可任意降级。 | K48: T042、T008 | L48: 原工作簿/02_实施任务!A48:O48；S34、S30
A49: T044 | B49: P0｜统一上传组件替代data/blob业务字段 | C49: 未开始 | E49: P16 | F49: ='01_闭环计划'!D22 | G49: 未提供证据记录 | H49: 进度口径差异：审阅B007,B015已修；任务仍未开始。只核对相关变更，不自动改状态。 | I49: 验收1：DB中无data/blob素材 验收2：跨浏览器媒体可用 验收3：上传失败不能伪保存成功 | J49: MediaRef{assetId,kind,mime,size,sha256,order,cover}；临时previewUrl不持久化。 | K49: T005 | L49: 原工作簿/02_实施任务!A49:O49；S10、S12、S02
A50: T045 | B50: P1｜复用MediaAsset并完善引用和访问校验 | C50: 未开始 | E50: P16 | F50: ='01_闭环计划'!D22 | G50: 未提供证据记录 | H50: 复用已有代码/测试；按新包验收，未提供的证据不推定通过。 | I50: 验收1：未完成媒体不能发布 验收2：共享引用不误删 验收3：越权下载403 | J50: 主素材长期保留可手删；临时上传清理与业务原件保留区分。 | K50: T044、T006 | L50: 原工作簿/02_实施任务!A50:O50；S03、S02、S31
A51: T046 | B51: P0｜按任务和设备绑定素材下发 | C51: 未开始 | E51: P17 | F51: ='01_闭环计划'!D23 | G51: 未提供证据记录 | H51: 复用已有代码/测试；按新包验收，未提供的证据不推定通过。 | I51: 验收1：同租户越设备素材访问被拒 验收2：合法断点重试成功 验收3：过期被拒 | J51: MediaDeliveryManifest含assetId/path或URL/mime/size/sha256；URL不能作为额外授权来源。 | K51: T045、T015、T007 | L51: 原工作簿/02_实施任务!A51:O51；S04、S05
A52: T047 | B52: P0｜续租期间流式下载与任务媒体清单 | C52: 未开始 | E52: P17 | F52: ='01_闭环计划'!D23 | G52: 未提供证据记录 | H52: 进度口径差异：审阅B025已修；任务仍未开始。只核对相关变更，不自动改状态。 | I52: 验收1：大视频下载不断租 验收2：中断重试不选半文件 验收3：内存不随视频大小线性增长 | J52: LocalMediaManifest{taskId,snapshotHash,assetId,localPath,hash,ready}。 | K52: T046、T016、T021 | L52: 原工作簿/02_实施任务!A52:O52；S25、S04
A53: T048 | B53: P0｜确定性选取本任务图片与视频 | C53: 未开始 | E53: P17 | F53: ='01_闭环计划'!D23 | G53: 未提供证据记录 | H53: 复用已有代码/测试；按新包验收，未提供的证据不推定通过。 | I53: 验收1：有旧图库仍只选任务素材 验收2：顺序正确 验收3：不会误删用户照片 | J53: PickerAdapter属于版本化recipe；无法稳定定位则待适配，不能盲目点击图库索引。 | K53: T047、T039 | L53: 原工作簿/02_实施任务!A53:O53；S29、S28
A54: T049 | B54: P1｜电脑上传并推送手机文件箱 | C54: 未开始 | E54: P18 | F54: ='01_闭环计划'!D24 | G54: 未提供证据记录 | H54: 复用已有代码/测试；按新包验收，未提供的证据不推定通过。 | I54: 验收1：电脑图片视频可到指定手机 验收2：跨设备隔离 验收3：删除本机不误删云端 | J54: FilePush{assetIds,deviceId,destination=APP_BOX|MEDIA_ALBUM}；非任意文件系统远程访问。 | K54: T046、T047、T036 | L54: 原工作簿/02_实施任务!A54:O54；S04
A55: T050 | B55: P1｜截图与失败现场上传查看 | C55: 未开始 | E55: P18 | F55: ='01_闭环计划'!D24 | G55: 未提供证据记录 | H55: 进度口径差异：审阅B028已修；任务仍未开始。只核对相关变更，不自动改状态。 | I55: 验收1：网页可看具体step截图 验收2：失败无截图仍可诊断 验收3：跨租户403 | J55: 直播不是录制；任务证据/用户保存截图是明确持久化对象。 | K55: T045、T014、T022 | L55: 原工作簿/02_实施任务!A55:O55；S27、S26、S02
A56: T051 | B56: P1｜持久化现有水印全部有效字段 | C56: 未开始 | E56: P19 | F56: ='01_闭环计划'!D25 | G56: 未提供证据记录 | H56: 复用已有代码/测试；按新包验收，未提供的证据不推定通过。 | I56: 验收1：换浏览器配置一致 验收2：改水印不改旧任务 验收3：未知变量拒绝 | J56: WatermarkProfileRevision{text/image/variables,position,scale,opacity,margin,...}。 | K56: T045、T010 | L56: 原工作簿/02_实施任务!A56:O56；S23、S03
A57: T052 | B57: P1｜复用派生媒体工作流生成确定素材 | C57: 未开始 | E57: P19 | F57: ='01_闭环计划'!D25 | G57: 未提供证据记录 | H57: 复用已有代码/测试；按新包验收，未提供的证据不推定通过。 | I57: 验收1：同输入输出可复用 验收2：原图不变 验收3：处理失败任务不错误开跑 | J57: 最终TaskSnapshot冻结outputAssetIds；水印不是APK发布时随机处理。 | K57: T051、T015 | L57: 原工作簿/02_实施任务!A57:O57；S31、S23、S03
A58: T053 | B58: P1｜水印页面接配置与真实预览 | C58: 未开始 | E58: P19 | F58: ='01_闭环计划'!D25 | G58: 未提供证据记录 | H58: 复用已有代码/测试；按新包验收，未提供的证据不推定通过。 | I58: 验收1：配置和预览真实可恢复 验收2：发布使用预览所对应规则 验收3：生产不写水印localStorage | J58: 所有当前启用水印控件须映射后端字段；不支持项不可假保存。 | K58: T052 | L58: 原工作簿/02_实施任务!A58:O58；S23
A59: T054 | B59: P1｜资源池和设备绑定后端模型 | C59: 未开始 | E59: P20 | F59: ='01_闭环计划'!D26 | G59: 未提供证据记录 | H59: 复用已有代码/测试；按新包验收，未提供的证据不推定通过。 | I59: 验收1：旧任务池内容不漂移 验收2：跨设备绑定正确 验收3：空池不能随机生成假地址 | J59: PoolSelectionSnapshot{poolId,poolRevision,itemId,itemRevision,resolvedValue,selectionSeed}。 | K59: T006、T010 | L59: 原工作簿/02_实施任务!A59:O59；S20、S02
A60: T055 | B60: P1｜地址池编辑、绑定与任务选用 | C60: 未开始 | E60: P20 | F60: ='01_闭环计划'!D26 | G60: 未提供证据记录 | H60: 复用已有代码/测试；按新包验收，未提供的证据不推定通过。 | I60: 验收1：跨浏览器一致 验收2：设备池优先可配置 验收3：实际选择可追溯 | J60: 地址是业务数据；手机执行按可见平台入口设置，不改GPS/不伪造定位系统。 | K60: T054 | L60: 原工作簿/02_实施任务!A60:O60；S20
A61: T056 | B61: P1｜描述模板后端化与变量渲染 | C61: 未开始 | E61: P20 | F61: ='01_闭环计划'!D26 | G61: 未提供证据记录 | H61: 复用已有代码/测试；按新包验收，未提供的证据不推定通过。 | I61: 验收1：同任务重试描述不变 验收2：未知变量拒绝 验收3：模板跨浏览器一致 | J61: 最终文本进入snapshot；不让APK联网查询“最新描述”。 | K61: T054 | L61: 原工作簿/02_实施任务!A61:O61；S20
A62: T057 | B62: P1｜标签CRUD与确定性抽取 | C62: 未开始 | E62: P20 | F62: ='01_闭环计划'!D26 | G62: 未提供证据记录 | H62: 复用已有代码/测试；按新包验收，未提供的证据不推定通过。 | I62: 验收1：任务标签稳定 验收2：重复标签不误增 验收3：无可用标签给明确错误 | J62: SelectedTagsSnapshot保留原文本与平台渲染文本。 | K62: T054 | L62: 原工作簿/02_实施任务!A62:O62；S20
A63: T058 | B63: P0｜修复价格类型和商品分组外键 | C63: 未开始 | E63: P21 | F63: ='01_闭环计划'!D27 | G63: 未提供证据记录 | H63: 进度口径差异：审阅B001已修；任务仍未开始。只核对相关变更，不自动改状态。 | I63: 验收1：价格20至100区间正确 验收2：商品分组不再引用帖子ID 验收3：脏值报告可追踪 | J63: price_cents为数值事实；兼容旧price输出时由Decimal格式化；商品分组和内容分组分表。 | K63: T001、T003 | L63: 原工作簿/02_实施任务!A63:O63；S03、S02
A64: T059 | B64: P0｜CRUD、分页和批量事务一致性 | C64: 未开始 | E64: P21 | F64: ='01_闭环计划'!D27 | G64: 未提供证据记录 | H64: 复用已有代码/测试；按新包验收，未提供的证据不推定通过。 | I64: 验收1：100商品页SQL常数级 验收2：单删批删保护一致 验收3：非法金额库存拒绝 | J64: 分页pageSize上限100为设计默认；batch API同一事务或显式逐项状态，不隐式部分成功。 | K64: T058、T045、T006 | L64: 原工作簿/02_实施任务!A64:O64；S02、S03、S08
A65: T060 | B65: P1｜分组CRUD与批量membership接通 | C65: 未开始 | E65: P21 | F65: ='01_闭环计划'!D27 | G65: 未提供证据记录 | H65: 进度口径差异：审阅B001已修；任务仍未开始。只核对相关变更，不自动改状态。 | I65: 验收1：FK开启批量分组成功 验收2：更名不改类别 验收3：跨浏览器分组一致 | J65: ProductGroupMembership(group_id,product_id)唯一；前端显示名不作主键。 | K65: T058、T059 | L65: 原工作簿/02_实施任务!A65:O65；S19、S02、S03
A66: T061 | B66: P0｜编辑页完整字段持久化 | C66: 未开始 | E66: P21 | F66: ='01_闭环计划'!D27 | G66: 未提供证据记录 | H66: 进度口径差异：审阅B007已修；任务仍未开始。只核对相关变更，不自动改状态。 | I66: 验收1：编辑转新建不覆盖旧记录 验收2：媒体可被手机使用 验收3：所有一期启用字段有roundtrip测试 | J66: ProductEditorV2 field-map需附源码实际字段名，不能仅完成title/price就宣布整页完成。 | K66: T059、T060、T044、T054、T051 | L66: 原工作簿/02_实施任务!A66:O66；S10、S08
A67: T062 | B67: P1｜真实列表、筛选、复制和批量操作 | C67: 未开始 | E67: P21 | F67: ='01_闭环计划'!D27 | G67: 未提供证据记录 | H67: 进度口径差异：审阅B005,B006已修；任务仍未开始。只核对相关变更，不自动改状态。 | I67: 验收1：409后不继续删除 验收2：复制有媒体 验收3：价格筛选正确 | J67: 前端缓存仅优化读取，不是商品事实库。 | K67: T059、T060 | L67: 原工作簿/02_实施任务!A67:O67；S08、S02
A68: T063 | B68: P1｜导入预检与行级结果格式 | C68: 未开始 | E68: P22 | F68: ='01_闭环计划'!D28 | G68: 未提供证据记录 | H68: 复用已有代码/测试；按新包验收，未提供的证据不推定通过。 | I68: 验收1：第50行错误可定位 验收2：同名不同目录不覆盖 验收3：无媒体不假称成功 | J68: ImportPreview{batchId,validRows,rowErrors,assetPlan}；ImportCommit引用已验证版本。 | K68: T059、T045 | L68: 原工作簿/02_实施任务!A68:O68；S11、S02
A69: T064 | B69: P1｜批次幂等、媒体导入与事务提交 | C69: 未开始 | E69: P22 | F69: ='01_闭环计划'!D28 | G69: 未提供证据记录 | H69: 复用已有代码/测试；按新包验收，未提供的证据不推定通过。 | I69: 验收1：重复导入不重复商品 验收2：无错误外键 验收3：内网URL被拒 | J69: 大文件可分批，但UI必须显示各批已提交事实；不能承诺跨无限行全局事务。 | K69: T063、T060、T046 | L69: 原工作簿/02_实施任务!A69:O69；S02、S11
A70: T065 | B70: P1｜预览、提交和错误清单 | C70: 未开始 | E70: P22 | F70: ='01_闭环计划'!D28 | G70: 未提供证据记录 | H70: 复用已有代码/测试；按新包验收，未提供的证据不推定通过。 | I70: 验收1：刷新可恢复进度 验收2：错误能定位行 验收3：所有媒体形成asset引用 | J70: 操作成功来自ImportBatch终态，不是本地for循环结束。 | K70: T064 | L70: 原工作簿/02_实施任务!A70:O70；S11
A71: T066 | B71: P1｜一次性迁移旧浏览器数据 | C71: 未开始 | E71: P23 | F71: ='01_闭环计划'!D29 | G71: 未提供证据记录 | H71: 复用已有代码/测试；按新包验收，未提供的证据不推定通过。 | I71: 验收1：重复迁移不重复 验收2：模拟任务不被执行 验收3：缺失视频明确报告 | J71: 不可恢复blob不能伪造素材；数据导入不是任务补发。 | K71: T060、T054、T051 | L71: 原工作簿/02_实施任务!A71:O71；S08、S09、S19
A72: T067 | B72: P0｜内容修订、标题和真实归档 | C72: 未开始 | E72: P24 | F72: ='01_闭环计划'!D30 | G72: 未提供证据记录 | H72: 进度口径差异：审阅B012已修；任务仍未开始。只核对相关变更，不自动改状态。 | I72: 验收1：列表详情revision标题一致 验收2：删除不复活 验收3：分页只需常数请求 | J72: PostRevisionV2为发布输入；列表title不是另一套可不同步真相。 | K72: T003、T045、T006 | L72: 原工作簿/02_实施任务!A72:O72；S09、S02、S03
A73: T068 | B73: P1｜完整编辑器与媒体资产接入 | C73: 未开始 | E73: P24 | F73: ='01_闭环计划'!D30 | G73: 未提供证据记录 | H73: 进度口径差异：审阅B015已修；任务仍未开始。只核对相关变更，不自动改状态。 | I73: 验收1：刷新媒体可用 验收2：标题不回退 验收3：编辑后发布引用正确revision | J73: 只编辑不等于发布；发布动作单独有明确任务创建。 | K73: T067、T044 | L73: 原工作簿/02_实施任务!A73:O73；S12、S09
A74: T069 | B74: P1｜列表、分组和删除真实接通 | C74: 未开始 | E74: P24 | F74: ='01_闭环计划'!D30 | G74: 未提供证据记录 | H74: 进度口径差异：审阅B012已修；任务仍未开始。只核对相关变更，不自动改状态。 | I74: 验收1：删除后服务端归档 验收2：分组一致 验收3：无N+1详情请求 | J74: 后端contents/groups为唯一真相；前端store仅缓存。 | K74: T067 | L74: 原工作簿/02_实施任务!A74:O74；S09、S02
A75: T070 | B75: P1｜CSV/Excel文本转义与导入边界 | C75: 未开始 | E75: P22 | F75: ='01_闭环计划'!D28 | G75: 未提供证据记录 | H75: 复用已有代码/测试；按新包验收，未提供的证据不推定通过。 | I75: 验收1：Excel打开无外部公式执行 验收2：金额仍可计算 验收3：越权字段不导出 | J75: 导出安全处理作用于序列化层，不修改原始商品文案。 | K75: T063、T067 | L75: 原工作簿/02_实施任务!A75:O75；S11、S02
A76: T071 | B76: P0｜单一发布笔记命令与所有入口复用 | C76: 未开始 | E76: P25 | F76: ='01_闭环计划'!D31 | G76: 未提供证据记录 | H76: 复用已有代码/测试；按新包验收，未提供的证据不推定通过。 | I76: 验收1：两入口生成同类真实任务 验收2：双击幂等 验收3：改帖不改变旧快照 | J76: xhs.publish_note.v1；result含mode、平台可得noteId/url、时间与证据；不可得字段null+reason。 | K76: T067、T012、T015、T046、T010 | L76: 原工作簿/02_实施任务!A76:O76；S13、S06、S04
A77: T072 | B77: P1｜启动、账号核验与发布页归一化 | C77: 未开始 | E77: P26 | F77: ='01_闭环计划'!D32 | G77: 未提供证据记录 | H77: 复用已有代码/测试；按新包验收，未提供的证据不推定通过。 | I77: 验收1：桌面起点可启动 验收2：账号错时不发布 验收3：未知弹窗可接管 | J77: 账号识别只采最小必要字段；未知状态返回PAUSED_WAITING_USER而非乱点。 | K77: T071、T039、T021 | L77: 原工作簿/02_实施任务!A77:O77；S29、S28
A78: T073 | B78: P0｜多图选择与标题正文标签填入 | C78: 未开始 | E78: P26 | F78: ='01_闭环计划'!D32 | G78: 未提供证据记录 | H78: 复用已有代码/测试；按新包验收，未提供的证据不推定通过。 | I78: 验收1：有旧图库仍选对 验收2：文案标签读回一致 验收3：中断后不重新选重复图片 | J78: 图文Recipe不包含未经commit_guard保护的最终发布点击。 | K78: T072、T048、T023 | L78: 原工作簿/02_实施任务!A78:O78；S13、S29
A79: T074 | B79: P1｜视频选择、处理等待和封面 | C79: 未开始 | E79: P27 | F79: ='01_闭环计划'!D33 | G79: 未提供证据记录 | H79: 复用已有代码/测试；按新包验收，未提供的证据不推定通过。 | I79: 验收1：真实视频笔记可发布 验收2：转码慢不假成功 验收3：恢复不重复导入 | J79: VIDEO模式为一期素材能力；平台不支持的格式明确错误，不能静默丢弃视频。 | K79: T072、T048、T023 | L79: 原工作簿/02_实施任务!A79:O79；S12、S13
A80: T075 | B80: P0｜发布/草稿成功判断和恢复 | C80: 未开始 | E80: P26 | F80: ='01_闭环计划'!D32 | G80: 未提供证据记录 | H80: 复用已有代码/测试；按新包验收，未提供的证据不推定通过。 | I80: 验收1：DIRECT真实发布 验收2：DRAFT不误发布 验收3：丢complete不重复发 | J80: draft保存和实际发布两种结果不能混用；未知提交结果不是FAILED可随意重试。 | K80: T073、T074、T024、T025、T050 | L80: 原工作簿/02_实施任务!A80:O80；S13、S26
A81: T076 | B81: P0｜选择帖子设备、下发和看执行 | C81: 未开始 | E81: P25 | F81: ='01_闭环计划'!D31 | G81: 未提供证据记录 | H81: 复用已有代码/测试；按新包验收，未提供的证据不推定通过。 | I81: 验收1：电脑创作→手机发布→网页结果闭环 验收2：定时可用 验收3：观看不影响执行 | J81: 发布页不自行生成点击步骤；云端不逐步控制小红书UI。 | K81: T071、T075、T028、T038 | L81: 原工作簿/02_实施任务!A81:O81；S13
A82: T077 | B82: P0｜所有闲鱼任务工厂和页面字段映射 | C82: 未开始 | E82: P01 | F82: ='01_闭环计划'!D7 | G82: 未提供证据记录 2026-09-08 T077：command_factory映射31项；operationId mint；未接线命令422。device-probe真机ca985a89 SUCCEEDED。 | H82: 复用已有代码/测试；按新包验收，未提供的证据不推定通过。 | I82: 验收1：所有kind有schema和路由映射 验收2：旧blocked功能纳入开发 验收3：不启用无实现字段 | J82: xianyu.*.v1参数按动作分型；选择“只打开页面”必须返回OPEN_ONLY而非执行成功。 | K82: T012、T013、T039、T020、T010 | L82: 原工作簿/02_实施任务!A82:O82；S15、S16、S17、S20
A83: T078 | B83: P0｜完整商品发布快照与接口 | C83: 未开始 | E83: P28 | F83: ='01_闭环计划'!D34 | G83: 未提供证据记录 | H83: 复用已有代码/测试；按新包验收，未提供的证据不推定通过。 | I83: 验收1：快照可独立解释发什么 验收2：UI字段不丢 验收3：响应与真实发布行为一致 | J83: XianyuPublishSnapshotV1记录productRevision、resolved文案/地址/标签、outputAssets、mode、bindingVersion。 | K83: T077、T061、T052、T055、T056、T057、T046 | L83: 原工作簿/02_实施任务!A83:O83；S14、S18、S07、S02
A84: T079 | B84: P0｜启动闲鱼、媒体选择和字段填写 | C84: 未开始 | E84: P28 | F84: ='01_闭环计划'!D34 | G84: 未提供证据记录 | H84: 复用已有代码/测试；按新包验收，未提供的证据不推定通过。 | I84: 验收1：从桌面自动拉起 验收2：选图无错 验收3：输入字段与快照一致 | J84: 发布填写与最终提交明确分离；所有定位引用已发布版本包。 | K84: T078、T021、T048、T023 | L84: 原工作簿/02_实施任务!A84:O84；S07、S29、S18
A85: T080 | B85: P0｜直发/草稿、提交判定与结果 | C85: 未开始 | E85: P28 | F85: ='01_闭环计划'!D34 | G85: 未提供证据记录 | H85: 复用已有代码/测试；按新包验收，未提供的证据不推定通过。 | I85: 验收1：实际直发与草稿行为匹配 验收2：不重复发布 验收3：旧API也遵守单writer | J85: XianyuPublishResult{mode,status,listingId?,publishedAt?,snapshotHash,evidenceRefs}。 | K85: T079、T024、T025、T050 | L85: 原工作簿/02_实施任务!A85:O85；S07、S02、S26
A86: T081 | B86: P1｜真实下发、排队和执行观察 | C86: 未开始 | E86: P28 | F86: ='01_闭环计划'!D34 | G86: 未提供证据记录 | H86: 复用已有代码/测试；按新包验收，未提供的证据不推定通过。 | I86: 验收1：从该页面能真正发布 验收2：刷新有历史 验收3：设置均被消费 | J86: UI保存发布配置可以有后端模板；配置模板不是已创建执行任务。 | K86: T080、T028、T038 | L86: 原工作簿/02_实施任务!A86:O86；S14、S18
A87: T082 | B87: P1｜擦亮商品真实执行 | C87: 未开始 | E87: P29 | F87: ='01_闭环计划'!D35 | G87: 未提供证据记录 | H87: 复用已有代码/测试；按新包验收，未提供的证据不推定通过。 | I87: 验收1：符合条件商品真实擦亮 验收2：已完成不重复 验收3：结果计数与清单一致 | J87: xianyu.polish.v1；字段：目标范围、商品过滤条件、数量/轮次/间隔（严格映射原字段）；结果必须含每item的done/skipped/failed/uncertain与证据，OPEN_ONLY单独状态。 | K87: T077、T023、T024 | L87: 原工作簿/02_实施任务!A87:O87；S20、S15、S16、S17、S29
A88: T083 | B88: P1｜上架商品 | C88: 未开始 | E88: P29 | F88: ='01_闭环计划'!D35 | G88: 未提供证据记录 | H88: 复用已有代码/测试；按新包验收，未提供的证据不推定通过。 | I88: 验收1：目标商品状态真实变在售 验收2：非目标不受影响 验收3：部分失败可追踪 | J88: xianyu.shelf_up.v1；字段：待上架范围、数量、过滤条件、间隔；结果必须含每item的done/skipped/failed/uncertain与证据，OPEN_ONLY单独状态。 | K88: T077、T023、T024 | L88: 原工作簿/02_实施任务!A88:O88；S20、S15、S16、S17、S29
A89: T084 | B89: P1｜下架商品 | C89: 未开始 | E89: P29 | F89: ='01_闭环计划'!D35 | G89: 未提供证据记录 | H89: 复用已有代码/测试；按新包验收，未提供的证据不推定通过。 | I89: 验收1：只下架指定项 验收2：不误删 验收3：丢ACK不盲目二次操作 | J89: xianyu.shelf_down.v1；字段：在售范围、过滤条件、数量、间隔；结果必须含每item的done/skipped/failed/uncertain与证据，OPEN_ONLY单独状态。 | K89: T077、T023、T024 | L89: 原工作簿/02_实施任务!A89:O89；S20、S15、S16、S17、S29
A90: T085 | B90: P1｜删除商品 | C90: 未开始 | E90: P30 | F90: ='01_闭环计划'!D36 | G90: 未提供证据记录 | H90: 复用已有代码/测试；按新包验收，未提供的证据不推定通过。 | I90: 验收1：仅删确认目标 验收2：列表重排不误删 验收3：不可逆动作有证据 | J90: xianyu.delete_goods.v1；字段：目标范围、数量、确认标志、过滤条件；结果必须含每item的done/skipped/failed/uncertain与证据，OPEN_ONLY单独状态。 | K90: T077、T023、T024 | L90: 原工作簿/02_实施任务!A90:O90；S20、S15、S16、S17、S29
A91: T086 | B91: P1｜绑定闲鱼账号 | C91: 未开始 | E91: P03 | F91: ='01_闭环计划'!D9 | G91: 未提供证据记录 | H91: 复用已有代码/测试；按新包验收，未提供的证据不推定通过。 | I91: 验收1：一个闲鱼当前绑定 验收2：旧历史不迁移 验收3：不会泄露密码 | J91: xianyu.bind_account.v1；字段：deviceId、当前平台账号探测、换绑确认、expectedBindingVersion；结果必须含每item的done/skipped/failed/uncertain与证据，OPEN_ONLY单独状态。 | K91: T077、T010、T011、T023 | L91: 原工作簿/02_实施任务!A91:O91；S20、S15、S16、S17、S29
A92: T087 | B92: P1｜签到鱼币 | C92: 未开始 | E92: P31 | F92: ='01_闭环计划'!D37 | G92: 未提供证据记录 | H92: 复用已有代码/测试；按新包验收，未提供的证据不推定通过。 | I92: 验收1：已签到不重复 验收2：签到可得结果真实 验收3：平台入口缺失可见 | J92: xianyu.coin_checkin.v1；字段：执行账号、日期/周期、原页面其它有效选项；结果必须含每item的done/skipped/failed/uncertain与证据，OPEN_ONLY单独状态。 | K92: T077、T023、T024 | L92: 原工作簿/02_实施任务!A92:O92；S20、S15、S16、S17、S29
A93: T088 | B93: P1｜鱼币抵扣 | C93: 未开始 | E93: P31 | F93: ='01_闭环计划'!D37 | G93: 未提供证据记录 | H93: 复用已有代码/测试；按新包验收，未提供的证据不推定通过。 | I93: 验收1：每种模式语义正确 验收2：OPEN_ONLY无设置改变 验收3：不误改价格 | J93: xianyu.coin_discount.v1；字段：目标商品、抵扣模式不抵扣/10%/20%/30%/只打开页面（以现有枚举为准）；结果必须含每item的done/skipped/failed/uncertain与证据，OPEN_ONLY单独状态。 | K93: T077、T023、T024 | L93: 原工作簿/02_实施任务!A93:O93；S20、S15、S16、S17、S29
A94: T089 | B94: P1｜鱼币推广 | C94: 未开始 | E94: P32 | F94: ='01_闭环计划'!D38 | G94: 未提供证据记录 | H94: 复用已有代码/测试；按新包验收，未提供的证据不推定通过。 | I94: 验收1：不超明确预算 验收2：不确定扣费不重复提交 验收3：套餐变化暂停 | J94: xianyu.coin_promote.v1；字段：商品筛选/排序、推广包或时长、最大鱼币预算、逐项确认；结果必须含每item的done/skipped/failed/uncertain与证据，OPEN_ONLY单独状态。 | K94: T077、T023、T024 | L94: 原工作簿/02_实施任务!A94:O94；S20、S15、S16、S17、S29
A95: T090 | B95: P1｜一键小刀（非降价） | C95: 未开始 | E95: P33 | F95: ='01_闭环计划'!D39 | G95: 未提供证据记录 | H95: 复用已有代码/测试；按新包验收，未提供的证据不推定通过。 | I95: 验收1：小刀与降价逻辑分开 验收2：设置值读回正确 验收3：OPEN_ONLY不操作 | J95: xianyu.bargain_setting.v1；字段：打开/关闭/指定小刀参数/只打开页面及目标商品（以原枚举为准）；结果必须含每item的done/skipped/failed/uncertain与证据，OPEN_ONLY单独状态。 | K95: T077、T023、T024 | L95: 原工作簿/02_实施任务!A95:O95；S20、S15、S16、S17、S29
A96: T091 | B96: P1｜一键降价 | C96: 未开始 | E96: P33 | F96: ='01_闭环计划'!D39 | G96: 未提供证据记录 | H96: 复用已有代码/测试；按新包验收，未提供的证据不推定通过。 | I96: 验收1：重试不二次降价 验收2：底价有效 验收3：每项旧新价可查 | J96: xianyu.price_cut.v1；字段：商品范围、按金额或百分比、最低价、数量/间隔；结果必须含每item的done/skipped/failed/uncertain与证据，OPEN_ONLY单独状态。 | K96: T077、T023、T024 | L96: 原工作簿/02_实施任务!A96:O96；S20、S15、S16、S17、S29
A97: T092 | B97: P1｜一键好评 | C97: 未开始 | E97: P34 | F97: ='01_闭环计划'!D40 | G97: 未提供证据记录 | H97: 复用已有代码/测试；按新包验收，未提供的证据不推定通过。 | I97: 验收1：真实订单评价可追踪 验收2：不重复评价 验收3：不默认发送互评推广私信 | J97: xianyu.review_order.v1；字段：真实已完成订单范围、评价内容、数量、原页面评价选项；结果必须含每item的done/skipped/failed/uncertain与证据，OPEN_ONLY单独状态。 | K97: T077、T023、T024 | L97: 原工作簿/02_实施任务!A97:O97；S20、S15、S16、S17、S29
A98: T093 | B98: P1｜重启闲鱼的权限边界 | C98: 未开始 | E98: P35 | F98: ='01_闭环计划'!D41 | G98: 未提供证据记录 | H98: 复用已有代码/测试；按新包验收，未提供的证据不推定通过。 | I98: 验收1：有权限范围内确实重新拉起 验收2：不宣称无权force-stop 验收3：不丢账号数据 | J98: xianyu.relaunch_app.v1；字段：设备/账号、导航恢复模式、原有等待选项；结果必须含每item的done/skipped/failed/uncertain与证据，OPEN_ONLY单独状态。 | K98: T077、T023、T024 | L98: 原工作簿/02_实施任务!A98:O98；S20、S15、S16、S17、S29
A99: T094 | B99: P1｜删除动态 | C99: 未开始 | E99: P30 | F99: ='01_闭环计划'!D36 | G99: 未提供证据记录 | H99: 复用已有代码/测试；按新包验收，未提供的证据不推定通过。 | I99: 验收1：不误删商品/消息 验收2：分页有界 验收3：每项结果可追踪 | J99: xianyu.delete_feed.v1；字段：动态范围、数量/轮次、筛选、明确删除确认；结果必须含每item的done/skipped/failed/uncertain与证据，OPEN_ONLY单独状态。 | K99: T077、T023、T024 | L99: 原工作簿/02_实施任务!A99:O99；S20、S15、S16、S17、S29
A100: T095 | B100: P1｜删除消息/处理小红点 | C100: 未开始 | E100: P36 | F100: ='01_闭环计划'!D42 | G100: 未提供证据记录 | H100: 复用已有代码/测试；按新包验收，未提供的证据不推定通过。 | I100: 验收1：点红点不删除 验收2：删除范围正确 验收3：不自动发送消息 | J100: xianyu.message_action.v1；字段：messageAction=删除对话框或点开小红点、数量/轮次、筛选；结果必须含每item的done/skipped/failed/uncertain与证据，OPEN_ONLY单独状态。 | K100: T077、T023、T024 | L100: 原工作簿/02_实施任务!A100:O100；S20、S15、S16、S17、S29
A101: T096 | B101: P1｜删除留言 | C101: 未开始 | E101: P30 | F101: ='01_闭环计划'!D36 | G101: 未提供证据记录 | H101: 复用已有代码/测试；按新包验收，未提供的证据不推定通过。 | I101: 验收1：不误删会话 验收2：无权不乱点 验收3：恢复不跳错项 | J101: xianyu.delete_comment.v1；字段：留言目标范围、数量、轮次、确认标志；结果必须含每item的done/skipped/failed/uncertain与证据，OPEN_ONLY单独状态。 | K101: T077、T023、T024 | L101: 原工作簿/02_实施任务!A101:O101；S20、S15、S16、S17、S29
A102: T097 | B102: P1｜草稿上架 | C102: 未开始 | E102: P37 | F102: ='01_闭环计划'!D43 | G102: 未提供证据记录 | H102: 复用已有代码/测试；按新包验收，未提供的证据不推定通过。 | I102: 验收1：指定草稿真实上架 验收2：不误发相邻草稿 验收3：重试不重复 | J102: xianyu.publish_draft.v1；字段：草稿选择、数量、发布选项、账号和确认；结果必须含每item的done/skipped/failed/uncertain与证据，OPEN_ONLY单独状态。 | K102: T077、T023、T024 | L102: 原工作簿/02_实施任务!A102:O102；S20、S15、S16、S17、S29
...

Sheet 05_范围追溯
A1: 05 / 原范围不删减 · 逐项验收
A2: 20项R需求 + 12项原始范围 + 31项闲鱼目录。需求原文与“用户已确认 / 原稿设计默认”分开保留；所有平台缺口保留状态，只有用户明确变更范围后才能豁免。2026-09-08：当前验收改为 OnePlus 9R 单机分阶段；R01（10台/百台）与 R06（Note9）保留为后期扩展，不得标已通过、不得删除。
A5: 类别 | B5: 原编号 | C5: 需求 / 目录名称 | D5: 原要求 / 处理说明 | E5: 新包归属 | F5: 验收状态（维护） | G5: 约束 / 需求属性 | H5: 原表位置
A6: 已确认需求 | B6: R01 | C6: 规模｜一期至少10台，面向百台扩展 | D6: 区分在线数、运行任务数和同时观看数；百台在线不等于百路高码率视频。 | E6: P47、P48 | F6: 后期扩展（当前不阻塞） | G6: 用户已确认 | H6: 原00_需求与架构!A30:H30
A7: 已确认需求 | B7: R02 | C7: 连接｜SIM移动网络连接 | D7: APK主动连接公网云端；手机和电脑不需同局域网。生产执行不依赖USB、ADB常驻或Edge Gateway。 | E7: P03、P10、P48 | F7: 待验收 | G7: 用户已确认 | H7: 原00_需求与架构!A31:H31
A8: 已确认需求 | B8: R03 | C8: 视频｜流畅实时视频是一期必做 | D8: 画面流畅优先，不追求最高分辨率；截图轮询仅作诊断/降级，不能作为实时投屏验收。 | E8: P10、P12、P47 | F8: 待验收 | G8: 用户已确认 | H8: 原00_需求与架构!A32:H32
A9: 已确认需求 | B9: R04 | C9: 远控｜观看不中断，写操作先接管 | D9: 点击、滑动、长按、文字输入、返回/Home/多任务；观看任务不占写锁，接管先暂停自动化。 | E9: P08、P11、P12 | F9: 待验收 | G9: 用户已确认 | H9: 原00_需求与架构!A33:H33
A10: 已确认需求 | B10: R05 | C10: 恢复｜人工处理后继续原任务 | D10: 未知页面保留现场并暂停；交回控制权后校验页面与检查点，再继续原taskId。取消和暂停必须分开。 | E10: P08、P09、P11 | F10: 待验收 | G10: 用户已确认 | H10: 原00_需求与架构!A34:H34
A11: 已确认需求 | B11: R06 | C11: 兼容｜红米Note9作为真实设备基线 | D11: 不猜Android版本。APK自动上报SDK/ROM/目标App版本；用户不用手填。手机常亮，允许无障碍、投屏授权和前台服务。 | E11: P04、P13、P49 | F11: 后期扩展（当前不阻塞） | G11: 用户已确认 | H11: 原00_需求与架构!A35:H35
A12: 已确认需求 | B12: R07 | C12: 解耦｜云端负责做什么，APK负责怎么做 | D12: 云端负责内容、素材、业务快照、队列、定时、指令、状态；手机本地负责识别、动作、分支、采集和恢复。 | E12: P01、P05、P06、P07 | F12: 待验收 | G12: 用户已确认 | H12: 原00_需求与架构!A36:H36
A13: 已确认需求 | B13: R08 | C13: 更新｜APK整体升级+Recipe独立更新 | D13: 新版本生成并测试后，由用户在后台点击发布；未发布不可生效。运行中任务固定原版本。 | E13: P14、P15 | F13: 待验收 | G13: 用户已确认 | H13: 原00_需求与架构!A37:H37
A14: 已确认需求 | B14: R09 | C14: 队列｜立即/预约/周期；每设备串行FIFO | D14: 闲鱼与小红书共享同台设备写队列；不做优先级。多设备操作生成独立任务，不新增父任务状态。 | E14: P05、P06、P08 | F14: 待验收 | G14: 用户已确认 | H14: 原00_需求与架构!A38:H38
A15: 已确认需求 | B15: R10 | C15: 账号｜每设备1闲鱼+1小红书，可解绑换绑 | D15: 两平台各自绑定。历史订单、发布实例、任务和统计归原账号；换绑不迁移历史。云端待发布内容库可复用。 | E15: P03、P41、P43 | F15: 待验收 | G15: 用户已确认 | H15: 原00_需求与架构!A39:H39
A16: 已确认需求 | B16: R11 | C16: 异常｜已知弹窗处理，未知暂停等人工 | D16: 登录失效、人机验证、风控及未知页面暂停并提供接管入口；不自动绕过平台或系统的验证/授权。 | E16: P07、P08、P09、P13 | F16: 待验收 | G16: 用户已确认 | H16: 原00_需求与架构!A40:H40
... A68: 闲鱼31目录 | B68: xy-tasks-31 | C68: 视频操作教程 | D68: 静态帮助内容/版本对应 | E68: P49 | F68: 待验收 | G68: 共享页面/帮助，不新增mobile task | H68: 原00_需求与架构!A127:H127；T104

Sheet 06_执行实测
A1: 06 / 智能体执行实测与成本
A2: 无执行日志时保持待采样；不能把人日换成AI小时。费用仅记录可核对的人民币账单/分摊值，未知留空；日志最多预置2000轮，超出须扩展公式范围。
A5: 指标 | B5: 值 | C5: 解释
A6: 记录轮数 | B6: =COUNTIF('09_执行记录'!A6:A2022,"<>") | C6: 一轮＝一次当前检查点的实际执行/规划/审阅会话。每轮唯一ID，不等于工具调用次数。
A7: 主动耗时已填轮数 | B7: =COUNTIFS('09_执行记录'!A6:A2022,"<>",'09_执行记录'!H6:H2022,"<>") | C7: 未知留空，0只用于实际没有主动耗时的轮次。
A8: 累计主动分钟 | B8: =IF(B7=0,"待采样",SUM('09_执行记录'!H6:H2022)) | C8: 多个智能体主动时间相加；并行时不等于从开始到结束的自然时长。
A9: 成本已填轮数 | B9: =COUNTIFS('09_执行记录'!A6:A2022,"<>",'09_执行记录'!M6:M2022,"<>") | C9: 包括确认零增量费用的0；网页订阅不自动摊为0成本。
A10: 已知人民币成本 | B10: =IF(B9=0,"待采样",SUM('09_执行记录'!M6:M2022)) | C10: 仅已填账单或明确分摊值，缺项时不是完整总成本；不得重复计入缓存Token。
A11: 成本数据完整度 | B11: =IF(B6=0,"待采样",B9/B6) | C11: 实测只覆盖新增日志，不包含此前历史运行。
A12: 资源等待已填轮数 | B12: =COUNTIFS('09_执行记录'!A6:A2022,"<>",'09_执行记录'!I6:I2022,"<>") | C12: 等待与主动时间分开；并行或同一阻塞重复计时须避免。
A13: 累计已记录等待分钟 | B13: =IF(B12=0,"待采样",SUM('09_执行记录'!I6:I2022)) | C13: 不直接把累计等待与累计主动耗时相加预测项目日历时间。
A14: 模块通过包数 | B14: =COUNTIF('01_闭环计划'!Q6:Q55,"模块通过") | C14: 模块契约与自测通过，不等于真机场景或一期全部验收。
A15: 功能验收通过包数 | B15: =COUNTIF('01_闭环计划'!D6:D55,"验收通过") | C15: D列「验收通过」才计入。2026-09-08 未把任何新包D改为验收通过；Q列「模块通过」见B14。
A16: 升级诊断轮数 | B16: =COUNTIFS('09_执行记录'!A6:A2022,"<>",'09_执行记录'!N6:N2022,"升级诊断") | C16: 升级是停止盲修，不是自动付费或自动批准新资源。
A17: 总工期预测 | B17: 不生成 | C17: 先采集P08/P09及其他不同复杂度任务；仅对相似任务给实测区间，不外推成全项目交付承诺。
A18: 模型选择比较 | B18: 按已通过交付比较 | C18: 同一标准下比较总成本、耗时、失败修复轮数；便宜单次价格不能代替总交付成本。
A19: 原估算处理 | B19: 已移除 | C19: 原38–76人日、人数效率与日历换算不再参与任何活动公式；原文件保留追溯。
A20: Token统计 | B20: 原始账单字段 | C20: 输入/输出Token未知留空；不同提供方缓存口径可能重叠，所以不另造缓存加总公式。

Sheet 07_原审阅索引
A1: 07 / 原审阅结论保留索引
A2: 63条原审阅记录不改写为63个已复现Bug。静态确认、需求差距、待复现风险、待验证约束、旧稿纠正保留原类别；26条原标代码已修/待联调也不是26项已验收。源码URL仅继承，未重新联网核验。
A5: 原B | B5: 级别 | C5: 原结论类型 | D5: 原状态 | E5: 模块 / 问题缺口 | F5: 原源码证据 | G5: 原核查方法 | H5: 原修复指导 | I5: 原验收 | J5: 旧T → 新包 | K5: 原负责人 / 提交证据 | L5: 原位置 / 来源URL
A6: B001 | B6: P0 | C6: 静态确认 | D6: 代码已修/待联调 | E6: 商品/数据库｜商品分组写错外键对象 | F6: services.py batch_update_product_group/import_products 写 content_id=product_id；db.py 的content_id外键指向content_item。 | G6: 在开启FK的数据库建1商品+1内容组；执行批量分组；检查FK异常或错误关联。 | H6: 新增ProductGroup/ProductGroupMembership，FK指向product；迁移旧groupName与可识别脏数据；禁止复用帖子membership。 | I6: Postgres/SQLite FK开启均成功；分组删改不影响帖子；无孤儿行。 | J6: T058→P21；T060→P21 | K6: 负责人：ZCode 证据：未提供 | L6: 原01_代码审阅!A6:N6 https://github.com/candywang98/lamda-yun/blob/b394475c56a07b0ea660531222d182646e1c7e66/services/control-api/src/cloudctl_api/services.py https://github.com/candywang98/lamda-yun/blob/b394475c56a07b0ea660531222d182646e1c7e66/services/control-api/src/cloudctl_api/db.py
A7: B002 | B7: P1 | C7: 静态确认 | D7: 未处理 | E7: 商品/价格｜字符串价格用于数值范围筛选 | F7: ProductRow.price=String；filter_products直接price >= min_price / <= max_price。 | G7: 录入9.9/20/100/1000；查询20至100区间；核对结果。 | H7: 迁移price_cents BIGINT；Decimal转换，保留API兼容输出；范围过滤使用数值且None判断。 | I7: 20至100只返回20和100；0/小数/非法数值边界覆盖。 | J7: T058→P21；T059→P21 | K7: 负责人：未填 证据：未提供 | L7: 原01_代码审阅!A7:N7 https://github.com/candywang98/lamda-yun/blob/b394475c56a07b0ea660531222d182646e1c7e66/services/control-api/src/cloudctl_api/db.py https://github.com/candywang98/lamda-yun/blob/b394475c56a07b0ea660531222d182646e1c7e66/services/control-api/src/cloudctl_api/services.py
A8: B003 | B8: P1 | C8: 静态确认 | D8: 未处理 | E8: 商品/删除｜批量删除绕过单项引用保护 | F8: archive_product检查活跃PublishPlan；batch_delete_products直接ARCHIVED。 | G8: 建引用商品的活动发布计划；分别单删和批删，比较行为。 | H8: 抽取统一归档保护并锁行；批量预检后同事务执行；返回blockedIds。 | I8: 单删批删同规则；任何被引用项导致整批不改；重复归档有明确幂等语义。 | J8: T059→P21 | K8: 负责人：未填 证据：未提供 | L8: 原01_代码审阅!A8:N8 https://github.com/candywang98/lamda-yun/blob/b394475c56a07b0ea660531222d182646e1c7e66/services/control-api/src/cloudctl_api/services.py
A9: B004 | B9: P1 | C9: 静态确认 | D9: 代码已修/待联调 | E9: Web数据｜404/501自动转localStorage造成真假数据分裂 | F9: product-catalog/post-catalog的isMissingApi触发usingLocal并保存本地。 | G9: API模式把保存接口改成404；保存后直接查询数据库。 | H9: 生产环境失败即报错；仅显式dev mock允许本地；删除会话内隐式降级。 | I9: 生产404不显示成功、不写业务localStorage；切换浏览器数据一致。 | J9: T005→P02 | K9: 负责人：ZCode 证据：未提供 | L9: 原01_代码审阅!A9:N9 https://github.com/candywang98/lamda-yun/blob/b394475c56a07b0ea660531222d182646e1c7e66/apps/web/src/api/product-catalog.ts https://github.com/candywang98/lamda-yun/blob/b394475c56a07b0ea660531222d182646e1c7e66/apps/web/src/api/post-catalog.ts
A10: B005 | B10: P1 | C10: 静态确认 | D10: 代码已修/待联调 | E10: 商品/批删｜批删失败回退条件反向且可能部分删除 | F10: product-catalog.archive 在非404/501错误时逐个archive；404/501却转本地。 | G10: 批删返回409或500；观察是否仍发N个单删请求。 | H10: 禁止在权限/冲突/500后继续副作用请求；只对显式协商的接口兼容版本选路径。 | I10: 409/500后0个单删；批量失败无部分成功假象。 | J10: T062→P21 | K10: 负责人：ZCode 证据：未提供 | L10: 原01_代码审阅!A10:N10 https://github.com/candywang98/lamda-yun/blob/b394475c56a07b0ea660531222d182646e1c7e66/apps/web/src/api/product-catalog.ts
A11: B006 | B11: P1 | C11: 静态确认 | D11: 代码已修/待联调 | E11: 商品/复制｜复制商品丢失媒体资产关联 | F11: product-catalog.duplicate固定mediaAssetIds:[]。 | G11: 复制有两图商品；比较新商品mediaAssetIds。 | H11: 复用已完成资产ID和顺序，不复制blob；明确封面与引用计数。 | I11: 复制后原件/副本都可预览发布，删除一方不误删共享媒体。 | J11: T062→P21 | K11: 负责人：ZCode 证据：未提供 | L11: 原01_代码审阅!A11:N11 https://github.com/candywang98/lamda-yun/blob/b394475c56a07b0ea660531222d182646e1c7e66/apps/web/src/api/product-catalog.ts
A12: B007 | B12: P1 | C12: 静态确认 | D12: 代码已修/待联调 | E12: 商品/媒体｜新媒体没有进入MediaAsset链路 | F12: ProductEditView 新图进attributes.images，视频为blob URL；save保留旧mediaAssetIds。 | G12: 上传新图片/视频保存后刷新，检查服务端媒体关联与手机manifest。 | H12: 统一上传create/upload/complete；存assetId；草稿预览URL与业务引用分离。 | I12: 刷新与换电脑可见，APK下载hash一致，payload无data/blob URL。 | J12: T044→P16；T061→P21 | K12: 负责人：ZCode 证据：未提供 | L12: 原01_代码审阅!A12:N12 https://github.com/candywang98/lamda-yun/blob/b394475c56a07b0ea660531222d182646e1c7e66/apps/web/src/views/ProductEditView.vue
A13: B008 | B13: P1 | C13: 静态确认 | D13: 未处理 | E13: 商品/字段｜分组名和商品类别混用 | F13: ProductEditView.applyProduct用category补groupName；save用groupName写category。 | G13: 改分组保存；检查category是否被覆盖。 | H13: 独立category与groupId；迁移需报告不确定记录，不能盲目改全部category。 | I13: 分组重命名不改变类别；筛选类别和分组相互独立。 | J13: T058→P21；T061→P21 | K13: 负责人：未填 证据：未提供 | L13: 原01_代码审阅!A13:N13 https://github.com/candywang98/lamda-yun/blob/b394475c56a07b0ea660531222d182646e1c7e66/apps/web/src/views/ProductEditView.vue https://github.com/candywang98/lamda-yun/blob/b394475c56a07b0ea660531222d182646e1c7e66/apps/web/src/data/product-groups.ts
A14: B009 | B14: P1 | C14: 待复现风险 | D14: 未处理 | E14: 商品/路由｜编辑页切到新建可能沿用旧current.id | F14: loadProduct无id时resetForm未清current；save优先current.value.id。 | G14: 同组件路由先?id=A，再去无id新建；保存，检查是否覆盖A。 | H14: 新建分支清current/id/SPU；异步加载加request epoch，旧响应不覆盖新路由。 | I14: 从编辑转新建创建B，A不变；快速切A/B不串数据。 | J14: T061→P21 | K14: 负责人：未填 证据：未提供 | L14: 原01_代码审阅!A14:N14 https://github.com/candywang98/lamda-yun/blob/b394475c56a07b0ea660531222d182646e1c7e66/apps/web/src/views/ProductEditView.vue
A15: B010 | B15: P1 | C15: 静态确认 | D15: 未处理 | E15: 商品/导入｜导入逐行保存，失败会部分写入 | F15: ProductImportView.importRows循环await catalog.save；无批次事务或结果账。 | G15: 100行第50行注入错误；重试并观察重复与已写入行。 | H15: 改预检+批次提交+幂等导入；每行错误带rowNo；已提交批次重复返回原结果。 | I15: 错误行可定位；重试不重复；UI准确展示已写入/失败数量。 | J15: T063→P22；T064→P22；T065→P22 | K15: 负责人：未填 证据：未提供 | L15: 原01_代码审阅!A15:N15 https://github.com/candywang98/lamda-yun/blob/b394475c56a07b0ea660531222d182646e1c7e66/apps/web/src/views/ProductImportView.vue
A16: B011 | B16: P1 | C16: 静态确认 | D16: 未处理 | E16: 商品/分组｜分组CRUD仍是浏览器本地事实 | F16: data/product-groups.ts 使用本地持久化；ProductImportView调用createProductGroup。 | G16: 浏览器A建组，浏览器B同账号查询。 | H16: ProductGroup API为唯一真相；一次性导入旧数据，不长期双写。 | I16: 跨浏览器一致；API失败不能本地伪成功。 | J16: T060→P21 | K16: 负责人：未填 证据：未提供 | L16: 原01_代码审阅!A16:N16 https://github.com/candywang98/lamda-yun/blob/b394475c56a07b0ea660531222d182646e1c7e66/apps/web/src/data/product-groups.ts https://github.com/candywang98/lamda-yun/blob/b394475c56a07b0ea660531222d182646e1c7e66/apps/web/src/views/ProductImportView.vue
... A68: B063 | B68: P2 | C68: 待验证约束 | D68: 未处理 | E68: 代码覆盖｜本轮不能证明全部构建/运行/安全缺陷已穷尽 | F68: 公开main源码静态核查；容器git clone DNS失败；无Android真机、无实际API/DB运行。 | G68: 在真实仓库执行基线命令与全目录扫描，记录未读/未跑项。 | H68: 不得将47或本表数量声称全部Bug；把新失败补入此Sheet，保留证据与严重度。 | I68: 有可重复构建日志、全库覆盖矩阵与真机证据才允许结案。 | J68: T001→P00；T002→P00；T120→P49 | K68: 负责人：未填 证据：未提供 | L68: 原01_代码审阅!A68:N68 https://github.com/candywang98/lamda-yun/blob/b394475c56a07b0ea660531222d182646e1c7e66/README.md https://github.com/candywang98/lamda-yun/commit/b394475c56a07b0ea660531222d182646e1c7e66

Sheet 08_模型分工与解锁
A1: 08 / 模型分工、接口解锁与结束条件
A2: 以下为执行建议，不是代码现状证明。初始检查阈值60分钟、同错两轮升级可用实测校准；保留真实验收和不可逆动作授权要求。
A5: 编号 | B5: 场景 | C5: 执行规则 | D5: 结束 / 升级条件 | E5: 证据与范围
A6: A01 | B6: 网页高级模型：总方案 | C6: 一次确定完整范围、架构和共享接口；详细施工单滚动展开当前包，依据当前代码证据。 | D6: 交付10模板要求的具体方案即可结束，不每包重复总架构审阅。 | E6: 代码未知标待核实；不凭旧路径编造当前符号。
A7: A02 | B7: 本地模型：执行 | C7: 一次领取当前卡的一个可验收检查点；定向核实代码，按接口实施并运行有关测试。 | D7: 有通过证据或可定位阻塞即回写；不自行扩大范围。 | E7: 01是唯一进度台；09仅为每轮实测日志。
A8: A03 | B8: 高级模型：异常诊断 | C8: 只接收失败签名、diff、错误日志和两轮尝试；输出合并的阻断清单。 | D8: 同一问题两轮不同修复仍失败或共享契约冲突时触发；可选优化不阻断。 | E8: 不是每个包必经审阅；涉及共享身份/租约/提交/版本机制的重大变更，接入真实副作用前做定向审阅。
A9: A04 | B9: 无进展检查 | C9: 连续主动排查无新增证据达到I列阈值，暂停猜测，检查代码/接口/资源原因。 | D9: 正常长编译或长时测试按声明的检查点继续；不能自动重开相同循环。 | E9: 不等同于60分钟完工；次数用尽不等同通过。
A10: A05 | B10: 独立完成 | C10: 冻结接口后，各模块契约测试通过即可记模块通过并结束开发。 | D10: 不等其他包整包完成；相关接口齐备后执行一条约定真实场景。 | E10: 失败定位到不符合契约的一侧；不用全部模块重新审阅。
A11: A06 | B11: 同错计数 | C11: 用复现条件、失败断言/错误栈和触及路径定义同一失败签名；实质修复才算一轮。 | D11: 两轮后集中诊断，给出新证据和明确新方案后才开始新的修复批次。 | E11: 不因换会话、换措辞或换模型自动清零。
A12: A07 | B12: 证据复用 | C12: 按受影响代码、契约、迁移、APK、Recipe及平台环境判断有效性。 | D12: 只复验受影响行为；相关实现变化时不能仅凭版本号不变沿用证据。 | E12: 无关改动不触发整套重跑；最终跨域验收仍保留。
A13: A08 | B13: 并行执行 | C13: 接口冻结，文件族、迁移和真机写操作无冲突时可并行；默认单执行通道，按实际资源增加。 | D13: 共享文件/契约冲突收敛到一个负责人；独立分支通过后再合并验证。 | E13: 不按Agent数量直接除工期；工作副本/分支与证据基准要明确。
A14: U01 | B14: P08 ↔ P09 | C14: P08先实现无最终提交任务的恢复：同taskId、检查点、旧epoch拒绝、FIFO。P09先验证通用账本/UNKNOWN保持停止。 | D14: P08当前检查点不等待P09全部动作验收；涉及真实提交时必须过对应G3。 | E14: 仍需核实T026旧现场可用性，不保证过去taskId当前仍可续用。
A15: U02 | B15: P09 ↔ 发布/删除/扣费包 | C15: 共享journal/幂等/不确定停止接口先经契约与故障测试可用；每个动作随后补独立核对证据。 | D15: 只有该动作的门禁与授权通过才允许真实副作用；不等所有动作全部完成才开发第一种。 | E15: 保留每类动作主路径及丢ACK场景，不伪造exactly-once。
A16: U03 | B16: P07 ↔ P14 | C16: 安装+claim 与焦点硬验收均已关闭；签名包已装到 OnePlus 9R。当前缺口是 P14 版本生命周期完整证据，不是重新部署、重开签名或重复焦点 probe。 | D16: 定向核实 T041、签名 Recipe 的任务固定/执行、暂停与运行版本固定、下载中断和回退审计；不关签名、不自动发版、不重复焦点 probe、不启动 P15。 | E16: 首个包的确切测试和发布命令须据当前代码填写10模板。
... A27: U07 | B27: P14 三泳道 | C27: WEB=T041 页面；CONTROL=claim版本固定/单active/回退审计；ANDROID=下载验签/空闲激活/旧版保留。 | D27: 三路独立测试后 Root 合并；真实发布和 OnePlus 验收只执行一次。 | E27: 机器清单：docs/phase1/multi-agent-work-items.json；协议：docs/phase1/multi-agent-execution.md。

Sheet 09_执行记录
A1: 09 / 每轮执行记录（填写实际值）
A2: 执行者每轮追加一行；不要求用户重复填多张表。每轮唯一ID；B填P00–P49，费用以人民币记账并在P列标明来源/分摊方法；未知留空。时间用Asia/Shanghai。预置2000行。自2026-09-08起写入真实运行记录。
A5: 轮次ID | B5: P包 | C5: 检查点 | D5: 模型/版本 | E5: 角色 | F5: 开始时间 | G5: 结束时间 | H5: 主动分钟 | I5: 资源等待分钟 | J5: 输入Token | K5: 输出Token | L5: 同错修复轮数 | M5: 人民币成本 | N5: 本轮结果 | O5: 失败签名 | P5: 证据/费用来源/下一步
A6: R20260908-01 | B6: P08 | C6: 暂停ack→同task恢复门禁；取消不可恢复；不含最终提交 | D6: ZCode / grok-4.6 | E6: 执行 | F6: 46273.021 | G6: 46273.083 | N6: 模块通过：resume须PAUSED_WAITING_USER；取消/SUCCEEDED/RECONCILING拒绝恢复。真机有暂停与取消证据。CommandV1领取后的同task续跑未再跑一轮。 | P6: cloudctl-source/artifacts/tasks/P08-resume/。未点发布。下一步：P14前可用探针补CommandV1同task续跑。
A7: R20260908-02 | B7: P09 | C7: UNKNOWN/终态门禁；commitIntent→RECONCILING不得盲续 | D7: ZCode / grok-4.6 | E7: 执行 | F7: 46273.083 | G7: 46273.125 | N7: 模块通过：mark-unknown/ack-paused拒绝SUCCEEDED；RECONCILING阻塞resume/retry。无真机断网二次提交。G3未过。 | P7: cloudctl-source/artifacts/tasks/P09-unknown/；tests/integration/test_platform_tasks.py。下一步：真实发布/扣费/删除前必须过G3。
A8: R20260908-03 | B8: P07 | C8: 生产claim改走CommandV1并接RecipeEngine | D8: ZCode / grok-4.6 | E8: 执行 | F8: 46273.417 | G8: 46273.521 | N8: 模块通过：claim protocolVersion=cloudctl.command/v1；无legacy steps。OnePlus探针67d95d4a SUCCEEDED controlEpoch=93。内置Recipe不是P14已发布包。OPEN_ONLY不记发布成功。 | P8: cloudctl-source/artifacts/tasks/P07-command-v1/summary.md；首尔cloudctl-mobile-api已重启；APK已装。下一步：P14签名人工发布。
A9: R20260908-04 | B9: P01 | C9: T077闲鱼目录工厂；operationId mint CommandV1 | D9: ZCode / grok-4.6 | E9: 执行 | F9: 46273.521 | G9: 46273.549 | N9: 模块通过：31项目录唯一归属；未接线/PENDING失败关闭。xy-tasks-03擦亮现场422；operationId=device-probe ca985a89 SUCCEEDED controlEpoch=94。 | P9: cloudctl-source/artifacts/tasks/P01-factory/summary.md；tests/unit/test_command_factory.py。下一步：P03/P05联调，不重做field-map。
A10: BATCH-001 | B10: P01-P09 | C10: 主链路代码与单测 | D10: 混合/ZCode历史会话 | E10: 执行+审阅 | F10: 2026-09-06 ~ 2026-09-08 | G10: 2026-09-08 12:44:25 | N10: 模块通过 | P10: T001-T027代码已写；001-007迁移SQL待执行；真机验收待补
A11: R20260908-05 | B11: P14 | C11: 人工签名发布候选Recipe到测试机；失败可回退；不得关签名 | D11: ZCode / grok-4.6 | E11: 执行 | F11: 46273.556 | G11: 46273.632 | N11: 开发中：已接签名登记/人工publish到指定设备/Companion校验canonical hash+Ed25519。拒绝hash-pinned-builtin与:promote百分比发版。集成测试通过。未部署首尔，未在OnePlus拉取签名包。G3未过。 | P11: cloudctl-source/artifacts/tasks/P14-recipe-publish/summary.md；tests/integration/test_backend_control_api.py::test_recipe_catalog_requires_signature_and_manual_device_publish
A12: R20260908-06 | B12: SCOPE/P14 | C12: 单机分阶段验收范围变更；同步 P01/P07/P14 已知进度 | D12: ZCode / grok-4.6 | E12: 计划修订 | N12: 用户确认当前验收=OnePlus 9R b0644fb5 单机分阶段；Note9/10台/100模拟改为后期扩展，非已通过、非永久删除。P01/P07模块通过且生产 CommandV1 claim 已有成功探针。P08同task续跑待验收。P09 G3未过。P14安装+claim关闭；ca211913 SUCCEEDED 19:10 Asia/Shanghai attempt=1；7f292679 FAILED/WRONG_ACTIVE；captain D 覆盖 worker CLOSED。未改代码/设备。本轮只改规划文档。 | P12: 权威活动计划 lamda_yun_一期计划_智能体执行版.xlsx。证据：artifacts/tasks/P01-factory、P07-command-v1、P08-resume、P09-unknown、P14-recipe-publish。下一步：P14更强验收（不新开探针）；不启动P15。
A13: R20260909-01 | B13: P14 | C13: 闲鱼前台焦点竞争硬验收；对照当前任务状态 | D13: 历史执行会话（证据回填） | E13: 验收回填 | N13: 当前检查点通过：单次授权任务 0d36fe3f… SUCCEEDED attempt=1；闲鱼前台起始，执行器日志显示 expected/actual 收敛到 Companion；进程未重启。7f292679 保持 FAILED/WRONG_ACTIVE_PACKAGE，签名校验未关闭。该结果只关闭焦点竞争检查点，不代表 P14 整包通过。 | P13: cloudctl-source/artifacts/tasks/P14-recipe-publish/knife-20260909-hard-accept-probe.md；hard-accept-probe-20260909/。本次复核：后端相关 6 项测试通过；Android Recipe 定向测试 BUILD SUCCESSFUL。下一步：T041 + 签名 Recipe claim 固定/执行 + 运行/暂停版本固定 + 下载中断保旧版 + 回退/设备版本审计；不重复焦点 probe，不启动 P15。
A14: R20260909-02 | B14: SCOPE/P14 | C14: 多智能体非串行执行方案；P14 三泳道与资源锁 | D14: Root + 3 分析子智能体 | E14: 计划修订 | N14: 已建立开发层多智能体协议：Root Worker + 最多3个写入子智能体；同轮批量创建后统一等待。P14 拆为 WEB、CONTROL、ANDROID 三路并行，Root 负责合同、合并、生成客户端和真机验收。生产 Temporal Worker 不承担 LLM 子智能体编排。当前仓库为单个脏 worktree，实际多写者启动前状态为 WAIT_BASELINE。 | P14: AGENTS.md；docs/phase1/multi-agent-execution.md；docs/phase1/multi-agent-work-items.json；11_多智能体并行。下一步：审核并固化共同基线，然后一次性启动 P14-WEB-T041、P14-CONTROL-VERSION、P14-ANDROID-LIFECYCLE；不在共享脏目录并发写。
A15: R20260910-P14-01 | B15: P14 | C15: 签名版本生命周期单机验收及等待/恢复修复 | D15: Codex Root + lamda-astra-worker×2 | E15: 执行 | G15: 46275.039 | N15: 功能验收通过 | P15: cloudctl-source/artifacts/tasks/P14-multi-agent/P14-INTEGRATION-ACCEPTANCE/summary.md；成本/Token未提供，留空。P09/G3与P15未验收。
A16: R20260910-P09-01 | B16: P09 | C16: 不确定状态保护与本地防重切片 | D16: Codex Root + lamda-astra-worker×2 | E16: 执行 | G16: 46275.063 | N16: 模块通过 | P16: cloudctl-source/artifacts/tasks/P09-unknown/hardening-20260910.md；G3未验收。调用成本未提供，留空。
A17: R20260913-P09-02 | B17: P09 | C17: 抖音提交前验证与门禁路径（不执行真实发布） | D17: Root总控+写入子智能体（回填） | E17: 执行 | F17: 2026-09-13 | G17: 2026-09-13 | N17: 模块通过：后端40过1跳；Android 190/0/0；真机任务91d7d91b 14步SUCCEEDED停在发布前；契约p09-steps-commit/20260913.1(+douyin)冻结 | P17: cloudctl-source/artifacts/tasks/P09-unknown/dy-precommit-20260913/；抖音真实发布待用户指示后执行
A18: R20260914-SCOPE-01 | B18: SCOPE/IM | C18: IM聚合端到端真机验收（原二期提前，用户2026-09-13批准） | D18: Root总控+用户真实账号配合（回填） | E18: 验收 | F18: 2026-09-14 | G18: 2026-09-14 | N18: 真机验收通过（单机）：真通知→云端会话✅；云端回复→手机6步自动发送✅（8a5ead36 SUCCEEDED）；slice2监听配置/多平台/值班模式已部署首尔（迁移0018） | P18: cloudctl-source/artifacts/tasks/P09-unknown/im-live-20260914/ 及 im-slice2-20260914/；值班内页导航与营销通道标定为slice 2遗留
A19: R20260914-P10-01 | B19: P10 | C19: 实时会话第一片：JPEG帧流投屏/远控（WebRTC后置） | D19: Root总控+2写入子智能体（回填） | E19: 执行 | F19: 2026-09-13 | G19: 2026-09-14 | N19: 模块通过（已集成02a10fd）：后端51过1跳；Android 197/0；web typecheck+build过；真机SIM观看/远控验收（Q04）待Root持锁 | P19: cloudctl-source/artifacts/tasks/P09-unknown/dual-slice-20260913/；contracts/phase1/p10-live-session-v1.md
A20: R20260915-P29-01 | B20: P29 | C20: 闲鱼维护动作：擦亮+下架真机闭环（GATED受控账本） | D20: Root总控+2写入子智能体+契约裁定（回填） | E20: 执行+真机验收 | F20: 2026-09-15 | G20: 2026-09-15 | N20: 真机验收通过（单件动作）：擦亮LAYOUT_GUARD_PASSED+5步SUCCEEDED；下架intent→恰好一次确认→在卖1→0→账本APPLIED→操作员CONFIRMED（63516d24）；后端606/1(+27)、Android 316/0(+24) | P20: cloudctl-source/artifacts/tasks/P09-unknown/xianyu-maintenance-20260915/report.md；contracts/phase1/xianyu-maintenance-anchors-20260915.md；批量下架待定位方案
A21: R20260915-P30-01 | B21: P30 | C21: 闲鱼商品删除真机闭环（GATED确认+零误删安全停） | D21: Root总控（回填） | E21: 执行+真机验收 | F21: 2026-09-15 | G21: 2026-09-15 | L21: 2 | N21: 真机验收通过（单件动作）：删除37a665b0首卡单击→确认弹窗→GATED单击→¥299卡真实删除→账本confirm-delete→操作员核验卡片消失→CONFIRMED；首击坐标漂移两轮UNKNOWN安全停，零误删 | P21: cloudctl-source/artifacts/tasks/P09-unknown/xianyu-maintenance-20260915/report.md；稳健定位方案三选一待选型；留言/动态删除未开始
A2006: R20260915-P41-01 | B2006: P41 | C2006: 订单表+迁移0021+companion批量上报+查询API+collect编排+Web订单页（slice1全链） | D2006: GLM-5.3内置子代理+W0总控 | E2006: W1/W3子代理开发,W0集成部署 | F2006: 2026-09-15 | G2006: 2026-09-15 | L2006: 1 | N2006: 模块通过+集成通过：后端626/1·Web178全绿；首尔orders-7adc827上线（PG迁移0021+备份，drop-in可回滚）；集成c113f0e已推送 | P2006: cloudctl-source/artifacts/tasks/P41-P42-orders/orders-slice1-20260915/
A2007: R20260915-P42-01 | B2007: P42 | C2007: readOrders真机采集：定位器翻转+Flutter渲染重试修复+双方向验收 | D2007: GLM-5.3内置子代理+W0总控 | E2007: W2子代理开发,W0持DEVICE锁真机验收 | F2007: 2026-09-15 | G2007: 2026-09-15 | L2007: 2 | N2007: 真机验收通过：SOLD run bdb3dc74与BOUGHT run 3f77b85f均SUCCEEDED，6真实订单入库（价格U+200B碎片拼接全对）；首轮4579e4d1时序缺陷LOCATOR_NOT_FOUND已修复并补2单测 | P2007: cloudctl-source/artifacts/tasks/P41-P42-orders/orders-slice1-20260915/w0-acceptance/report.md
A2008: R20260915-P09-07 | B2008: P09 | C2008: 维护稳健化勘察：管理按钮语义锚点+菜单结构+订单页/已下架/草稿+锚点契约冻结 | D2008: W0总控(GLM-5.3) | E2008: W0串行持DEVICE锁,只读勘察 | F2008: 2026-09-15 | G2008: 2026-09-15 | L2008: 0 | N2008: 勘察完成并冻结xianyu-anchors-20260915（95c99c4）：管理按钮语义可点；菜单文本锚点（编辑/下架/删除/取消,推广/超擦为G3禁区）；列表标题可读→platformItemId映射可行；草稿tab空态未标定；全程零副作用 | P2008: cloudctl-source/artifacts/tasks/P09-unknown/xianyu-maintenance-20260915/recon-20260915-2/
A2009: R20260915-P29-02 | B2009: P29 | C2009: 维护动作v2新路径(标题定位→详情→管理菜单)全栈+无意图安全干跑 | D2009: GLM-5.3内置子代理+W0总控 | E2009: W4子代理开发,W0集成部署+持DEVICE锁干跑 | F2009: 2026-09-15 | G2009: 2026-09-15 | L2009: 1 | N2009: 模块通过+集成通过+干跑验证：三端656/1·356·184全绿并部署首尔maint-v2-c13aad8；干跑task 68437f3f新路径步骤0-6全SUCCEEDED、确认弹窗出现、GATED确认单击未发生、在卖187不变零副作用；BADGE_UNREADABLE集成缝已修复(876e4a7) | O2009: BADGE_UNREADABLE(v2详情页上下文) | P2009: cloudctl-source/artifacts/tasks/P09-unknown/xianyu-maintenance-20260915/w4-newpath/
A2010: R20260915-P42-02 | B2010: P42 | C2010: 订单slice2后端+Web（screens入参/v2多屏形状/采集入口启用） | D2010: GLM-5.3内置子代理+W0总控 | E2010: S2API/S2WEB子代理开发,W0集成 | F2010: 2026-09-15 | G2010: 2026-09-15 | L2010: 0 | N2010: 模块通过+集成通过：后端656/1(8变异门禁+v1零改动)、Web 184全绿、首尔已上线；Android v2执行器下一切片 | P2010: cloudctl-source/artifacts/tasks/P41-P42-orders/orders-slice2-20260915/
A2011: R20260916-P09-08 | B2011: P09 | C2011: 事故修复：嵌套卡片结构定位+安全点击带 | D2011: W0总控 | E2011: 主线修复+真机只读核对 | F2011: 2026-09-16 | G2011: 2026-09-16 | L2011: 0 | N2011: 模块通过：定位器12项回归全绿；标题叶节点向上解析卡片，整列表包裹/退化矩形 fail-closed；点击点限制在卡片与屏幕安全带交集；设备目标卡片唯一且取消后仍存在 | P2011: cloudctl-source/artifacts/tasks/P09-unknown/xianyu-maintenance-20260916/delete-dialog-readonly/
A2012: R20260916-P09-09 | B2012: P09 | C2012: 无障碍 readiness：claim 前稳定门禁+三入口防御等待 | D2012: GLM子代理+W0总控 | E2012: 子代理实现,W0审阅集成 | F2012: 2026-09-16 | G2012: 2026-09-16 | L2012: 0 | N2012: 模块通过：7项定向测试+Android全量375项全绿；enabled与active分离，稳定实例才claim；normal/resume/CommandV1保留3秒防御等待；ACCESSIBILITY_NOT_ACTIVE不再误报未启用 | O2012: claim后网络窗口断连仍需后续lease/requeue协议 | P2012: cloudctl-source/mobile/companion/app/src/test/java/com/company/cloudctl/companion/service/AccessibilityRuntimeReadinessTest.kt
A2013: R20260916-P09-10 | B2013: P09 | C2013: v2删除语义门禁生产装配+真实包装层防误选+新APK构建 | D2013: W0总控+GLM审阅子代理 | E2013: W0修复集成+独立只读复审 | F2013: 2026-09-16 | G2013: 2026-09-16 | L2013: 0 | N2013: 模块通过：生产服务已为xianyu_delete_confirm构造受控门禁，普通Tap不进门禁且旧布局确认不变；全列表包装/退化矩形fail-closed；Android全量380项、后端662项通过（1跳过），最终定向16项通过；APK内嵌48005da-dirty，SHA256=c6353cdd…c15f7；本检查点未触发确认、未删除商品 | O2013: 真机验收未执行；claim后断连lease/requeue仍为后续协议缺口 | P2013: cloudctl-source/artifacts/tasks/P09-unknown/xianyu-maintenance-20260916/semantic-gate-build-evidence.md
A2014: R20260916-P09-11 | B2014: P09 | C2014: 首尔v2删除语义协议独立release部署 | D2014: W0总控 | E2014: 独立release+远端定向测试+systemd切换 | F2014: 2026-09-16 | G2014: 2026-09-16 | L2014: 0 | N2014: 模块通过+部署通过：新release p09-semantic-48005da-20260916；远端维护测试53项全绿；mobile_actions/xianyu_maintenance哈希与本地一致；cloudctl-mobile-api active，WorkingDirectory指向新release，OpenAPI 151 paths；旧maint-v2-c13aad8保留可回滚 | O2014: 无专用health路由，以/openapi.json及systemd active为部署健康证据 | P2014: cloudctl-source/artifacts/tasks/P09-unknown/xianyu-maintenance-20260916/semantic-gate-build-evidence.md
A2015: R20260916-P09-12 | B2015: P09 | C2015: OnePlus新APK安装与源码/构建/安装/运行身份核验 | D2015: W0总控 | E2015: DEVICE锁串行安装+只读身份核验 | F2015: 2026-09-16 | G2015: 2026-09-16 | L2015: 0 | N2015: 模块通过+安装通过：唯一设备b0644fb5；adb install -r成功且未force-stop；本地与installed APK SHA256均为c6353cdd…c15f7；无障碍enabled+bound；新PID5684日志ACCESSIBILITY_CONNECTED generation=1 revision=48005da-dirty；心跳恢复 | O2015: 尚未执行目标定位/确认/删除 | P2015: cloudctl-source/artifacts/tasks/P09-unknown/xianyu-maintenance-20260916/install-identity/README.md
A2016: R20260916-P09-13 | B2016: P09 | C2016: 删除前真机只读预检：唯一卡片+弹窗三元守卫+取消闭环 | D2016: W0总控 | E2016: DEVICE锁串行只读预检 | F2016: 2026-09-16 | G2016: 2026-09-16 | L2016: 0 | N2016: 模块通过+真机预检通过：b0644fb5已下架列表目标标题前后均唯一1次；目标卡片[0,345][1080,764]，整列表包装[0,345][1080,2337]被防误选规则排除；详情标题正确；弹窗标题/取消/确定结构唯一且位置合法；仅点击取消(310,1364)，目标仍存在；未建任务/未建intent/未删除 | O2016: 下一步为已授权单次GATED删除；签发前须确认无活跃/不确定任务 | P2016: cloudctl-source/artifacts/tasks/P09-unknown/xianyu-maintenance-20260916/readonly-preflight/README.md
A2017: R20260916-P09-14 | B2017: P09 | C2017: 已授权单商品GATED删除：一次确认后UNKNOWN/KEEP_WAITING | D2017: W0总控 | E2017: 单次任务+一次受控确认+人工延迟复核 | F2017: 2026-09-16 | G2017: 2026-09-16 | L2017: 0 | N2017: 未通过真实删除验收，但安全门禁符合：仅签发1个delete-v2 task a25549e5；唯一actionKey 061e9532…，ledger仅1行actionId=confirm-delete，状态UNKNOWN；任务RECONCILING；无重放/无重试/无fallback。人工返回已下架列表并刷新等待8秒，目标“如果历史是一群喵4”仍唯一存在，已裁决KEEP_WAITING | O2017: 确认手势已发生但平台删除未证实且目标仍在；严禁重试，须基于证据分析tapOnce实际落点/窗口变化后再由用户决定新授权 | P2017: cloudctl-source/artifacts/tasks/P09-unknown/xianyu-maintenance-20260916/final-delete/README.md
A2018: R20260916-P09-15 | B2018: P09 | C2018: 权威进度表最终审计与视觉验收 | D2018: W0总控 | E2018: openpyxl审计+Quick Look/Chrome本地视觉兜底 | F2018: 2026-09-16 | G2018: 2026-09-16 | L2018: 0 | N2018: 模块通过：09新增记录全部启用换行与150pt行高；372个公式零错误/零零值异常/零隐式数组；158个09引用公式均延长至最新行；00/01/09/10渲染无文本重叠，P09保持进行中/模块通过，UNKNOWN/KEEP_WAITING未虚标验收通过 | O2018: 视觉judge代理EPIPE不可用，按协议采用本地渲染兜底；结构validator仍仅报既有6个=1常量公式 | P2018: cloudctl-source/artifacts/tasks/P09-unknown/xianyu-maintenance-20260916/final-delete/README.md
A2019: R20260916-P09-16 | B2019: P09 | C2019: UNKNOWN只读根因审阅与提交屏障修复 | D2019: W0总控+2路Explore审阅 | E2019: 现场证据法证审阅+静态调用链审计+Android JVM回归 | F2019: 2026-09-16 | G2019: 2026-09-16 | L2019: 0 | N2019: 模块通过：确认生产证据不足以证明删除生效或最终确认落点；修复语义删除门禁UNKNOWN后仍继续后续步骤的误报，改为提交屏障。定向门禁测试及Android全量55套件/380测试通过，零失败/错误/跳过；未连接设备、未写API、未改旧任务/ledger | O2019: 现有任务继续KEEP_WAITING且严禁重试；窗口身份/边界从解析到dispatchGesture存在TOCTOU风险，但不是本事故已证实根因；下一步仅做代码级活动窗口绑定、即时重检和手势可观测性加固 | P2019: cloudctl-source/artifacts/tasks/P09-unknown/xianyu-maintenance-20260916/unknown-root-cause-review.md
A2020: R20260916-P09-17 | B2020: P09 | C2020: 单次确认活动窗口重检与手势可观测性加固 | D2020: W0总控+独立对抗审阅 | E2020: 纯Kotlin竞态决策器+主线程三快照校验+单投递边界+全量JVM回归 | F2020: 2026-09-16 | G2020: 2026-09-16 | L2020: 0 | N2020: 模块通过：语义删除UNKNOWN在STEP_SUCCEEDED前停止；活动窗口在刷新前/后/dispatch runnable内三次核对package/windowId/结构/边界；取消在最终校验前后双检；dispatchGesture最多一次且无fallback/retry；关联日志记录落点、接受与回调。Android 57套件/392测试全通过，独立复核无高/中危项 | O2020: 仅源码/单测完成，未构建/安装/部署/连设备/写API；Android无法原子冻结外部窗口，末次校验到屏幕坐标投递仍有不可消除的系统级极窄竞态；旧UNKNOWN继续KEEP_WAITING且严禁重试 | P2020: cloudctl-source/artifacts/tasks/P09-unknown/xianyu-maintenance-20260916/single-shot-hardening-evidence.md
A2021: R20260916-P09-18 | B2021: P09 | C2021: claim后无障碍断开安全释放协议冻结 | D2021: W0总控+2路Explore审计 | E2021: Android生命周期审计+后端lease/action journal契约审计 | F2021: 2026-09-16 | G2021: 2026-09-16 | L2021: 0 | N2021: 模块通过：冻结最小协议为仅服务端CLAIMED/PREFLIGHT且首次task heartbeat前允许按当前lease释放回QUEUED；heartbeat成功即RUNNING执行边界，之后禁止自动回队。错误/过期lease、RUNNING、RECONCILING、任意action row或legacy commitIntent全部拒绝；设备heartbeat仅为遥测不触发状态变化 | O2021: 下一步后端/Android分域实现并补并发与断开测试；release失败时客户端不得本地重排或继续执行；旧task a25549e5仅作禁止重试反例，不做任何状态操作 | P2021: cloudctl-source/artifacts/tasks/P09-unknown/xianyu-maintenance-20260916/single-shot-hardening-evidence.md
A2022: R20260916-P09-19 | B2022: P09 | C2022: claim后无障碍断开安全释放协议实现与对抗审阅闭环 | D2022: W0总控+后端子代理+独立对抗审阅 | E2022: 后端release端点+Android coordinator/store/边界实现+两轮对抗审阅修复 | F2022: 2026-09-16 | G2022: 2026-09-16 | L2022: 0 | N2022: 模块通过：仅CLAIMED/PREFLIGHT且首次heartbeat前允许按当前lease释放回QUEUED；RUNNING/RECONCILING/任意action row/legacy intent/错误过期lease全部409。首轮审阅发现B1阻断行永久卡死与B2无限churn两个阻断缺陷，已用5分钟退役+claim前就绪门修复并经二审确认闭环。Android 60套件409测试、后端44测试全通过 | O2022: 仅源码/单测完成，未构建/部署/连设备/写生产API；接受后果：断连超5分钟的阻断任务在重投递时终判FAILED、极端双超时心跳仍会fence后经重投递或退役恢复；旧UNKNOWN任务未触碰 | P2022: cloudctl-source/artifacts/tasks/P09-unknown/xianyu-maintenance-20260916/release-protocol-evidence.md
A2023: R20260916-P09-20 | B2023: P09 P41 P42 | C2023: W-A/W-B并行+首尔部署+slice2真机验收+第3次删除挂起 | D2023: 两线合并(错卡双防线+slice2多屏执行器,Android 427/0)；首尔升级81e24ec；slice2多屏采集真机验收PASSED(run 9135e84c)；第3次授权删除安全失败CARD_BOUNDS_UNVERIFIED(零副作用)用户挂起转问题清单(delete-automation-issue-handoff.md) | E2023: cloudctl-source @ce074df；artifacts/tasks/P41-P42-orders/orders-slice2-20260916/；P09-unknown/xianyu-maintenance-20260916/
A2024: R20260916-P09-21 | B2024: P14 P41 P42 | C2024: K02/K03/K05三契约冻结+A03/A04双线落地+首尔部署(迁移0022) | D2024: 三契约冻结(7+4项裁决全按建议)；W-C/W-D并行交付合并(后端681/1)；operation_id迁移上生产(备份先行)；首尔3ce33ba:152端点公网200 | E2024: cloudctl-source @3ce33ba；contracts/parallel/；artifacts/tasks/phase1/
A2025: R20260916-P09-22 | B2025: P14 | C2025: A05/B05发布链落地+首尔部署(子代理三次API故障,主会话接管) | D2025: A05稳定publishTargetId+校验矩阵+open-only身份(702/1);B05 publish-2 open-only图+valueRef绑定+有序选图(433/0);K05勘误媒体49;首尔publish-29f19dd公网200 | E2025: cloudctl-source @29f19dd；artifacts/tasks/phase1/
A2026: R20260916-P09-23 | B2026: P09 P14 | C2026: Q02套件(42绿+2真机桩)+A09目录(31动作)落地+首尔a09-b226105 | D2026: A09:31动作46定义result_type各异716/1;Q02:A类42全绿,B类发现cardIndex:0真实商品风险已暂停待裁决;首尔公网200 | E2026: cloudctl-source @b226105；tests/parallel_acceptance/q02/；artifacts/tasks/phase1/a09-operation-catalog/
A2027: R20260916-P09-24 | B2027: P14 | C2027: Q03真实发布验收(open-only v1.1.1)+4真bug修复 | D2027: Q03通过：任务24c923bb全图12态SUCCEEDED→PAUSED_WAITING_USER确认点→操作员填价9.90+点发布→在卖187(+1)「云控平台验收测试服务¥9.9」在线验证；修：图v1.1.1(补裁剪页完成步/去价格态/加菜单settled等待)、终态checkpoint可持久化(resume bug)、auto_publish默认翻False(双产线隐患)、wait轮询容忍无障碍瞬断；发现并绕过：SET_TEXT幻影→须CloudCtl Input为当前输入法、部署venv editable指向陷阱、PAUSED任务卡队列(遗留问题清单)、force-stop致无障碍禁用(重启用设置搜索路径) | E2027: cloudctl-source @d4206bb；artifacts/parallel/W5/Q03/run7-24c923bb/

Sheet 10_当前包交接模板
A1: 当前包：P14闲鱼发布链（Q03已验收通过）。下一棒：修companion暂停任务生命周期（服务器cancel不下发→本地PAUSED行永久占队列；重现：platform任务到WAITING_USER后cancel，companion claimNext被hasBlockingHead挡死）。方案提示：heartbeat携带任务终态或resume-terminated语义；注意force-stop会禁无障碍（重启用设置内搜索CloudCtl的路径）；描述输入依赖CloudCtl Input为当前输入法（SET_TEXT是幻影，重渲染即丢）。关键SHA：recipe-xianyu-publish-2 v1.1.1=becbe9d8…；APK 628f19c；首尔release a11-9c53cc7（venv为editable安装，换目录必须改_editable_impl_cloudctl.pth）。
A2: 只为当前包填写；这是交接信息模板，不新增任务流程。高级模型依据当前代码证据填方案，本地模型执行。未核实项明示，不能把表内路径当当前代码事实。
A5: 项目 | B5: 填写要求 | C5: P14 发布链收尾：修复 companion 暂停任务生命周期（Q02-B 真机场景前置）
A6: 范围与基准 | B6: P编号、当前检查点、分支/提交、相关代码证据；当前真实状态。 | C6: P14/Q02-B前置；基线 cloudctl-source @d4206bb（recipe v1.1.1 已上真机验收通过）；APK 628f19c 在 b0644fb5；首尔 release a11-9c53cc7。
A7: 复用证据 | B7: 只读取有关文件和直接调用方；记录已通过证据及仍有效的理由。 | C7: 复用 artifacts/parallel/W5/Q03/run7-24c923bb/README.md（七次任务全根因链）、CloudCtlAccessibilityService.kt claimNext/hasBlockingHead、CompanionSyncService 心跳 ResumeCommand 通道。
A8: 依赖接口就绪 | B8: 写接口/符号、版本、输入输出fixture、验证命令与预期结果；不能只写Pxx完成。 | C8: 方案提示：服务器在 heartbeat 响应中携带已终态(cancel/complete)任务列表，或 claim 204 响应体带终态通知；companion 收到后将本地 task_inbox 对应行置 TERMINAL_CONFIRMED 并记 journal（OPERATOR_RETIRE_SERVER_TERMINAL）。需要新增 pydantic schema 字段+Kotlin 解析，双侧测试。验证命令：pytest tests/integration/test_platform_tasks.py + gradlew testDebugUnitTest。
A9: 最小改动 | B9: 列已核实文件和函数、调用关系、最小修改步骤、共享契约不可擅改项。 | C9: 最小改动文件：mobile_service.py(claim/heartbeat 响应)、CompanionSyncService.kt(心跳处理)、AutomationStore.kt(退役方法)；不改共享契约 K02/K03/K05；不动 recipe 图字节。
A10: 独立完成标准 | B10: 列模块契约和相关测试通过条件；达标后模块开发结束。 | C10: 达标：真机复现「platform任务到WAITING_USER→服务端cancel→companion 60s内自动退役本地行→队列恢复可认领新任务」并有 journal 证据；软件测试全绿。
A11: 真实场景与门禁 | B11: 列需要的设备/账号/授权、操作步骤、预期结果及证据；区别mock测试。 | C11: 设备仅 b0644fb5（严禁 5934418a0821）；禁止 force-stop companion（ColorOS 会禁无障碍；误禁后用设置内搜索 CloudCtl 的路径重开，已跑通）；描述输入须 CloudCtl Input 为当前输入法。
A12: 执行边界 | B12: 一轮交付当前检查点或可定位阻塞；不得扩大成关联包全量开发。 | C12: 只修暂停生命周期，不扩多机型/不加新 CommandV1 类型（K05 5处同步另立任务）。
A13: 升级条件 | B13: 同错两轮未解决；共享契约冲突；连续无证据达到I列阈值。 | C13: 同错两轮→换思路；仍卡→按专家阶梯最多1次咨询；无障碍反复解绑(约30分钟1次)属已知现象，wait 轮询已容忍。
A14: 回报格式 | B14: 产出/修改与提交/验证证据/剩余与下一步；09只追加一行实测。 | C14: 产出/提交/验证证据/下一步；09 追加一行实测；D 在真机复现通过前保持进行中。
A15: 高级审阅输出 | B15: 仅给合并阻断项：位置、复现、证据、违反哪条验收、最小修复；可选项不阻断。 | C15: 位置=mobile_service.claim 或 AutomationStore.claimNext；复现=Q03 任务 24c923bb 取消后队列卡死实测；违反=单活跃runner不变量（AGENTS.md）。

Sheet 11_多智能体并行
A1: 11 / 多智能体并行控制台
A2: 开发层：Root + 最多3个隔离写入子智能体。P14三路及集成单机验收已完成；不再WAIT_BASELINE。生产Temporal Worker不是LLM调度器。
A4: 调度规则
A5: 编号 | B5: 规则 | C5: 触发条件 | D5: 执行动作 | E5: 停止/串行边界 | F5: 证据
A6: S01 | B6: 批量派发 | C6: 同轮≥2个READY且写集互斥 | D6: 先创建全部子智能体，再wait_all | E6: 禁止spawn一个就await一个 | F6: 子任务handle/启动时间
A7: S02 | B7: READY | C7: 合同可用+写集互斥+锁空闲+无契约争议+测试已声明 | D7: 选最大无冲突集合，最多3个写入项 | E7: INTEG只门禁最终联调 | F7: work item状态
A8: S03 | B8: 空槽回填 | C8: 任一路WAIT_LOCK/WAIT_AUTH/WAIT_HARDWARE | D8: 立即从P08/P16/P40/P48等READY池补位 | E8: P15依赖已解锁；按READY安排，不扩二期 | F8: 阻塞与补位ID
A9: S04 | B9: 工作区隔离 | C9: 写入子智能体启动前 | D9: 从同一冻结SHA建独立branch/worktree | E9: 当前脏共享目录禁止并发写 | F9: BaselineSHA/BranchSHA
A10: S05 | B10: 受控合并 | C10: 子任务独立测试通过 | D10: 合同/Control→Android→Web→统一生成客户端→跨端测试 | E10: 语义冲突退回owner | F10: integration SHA
A13: 独占资源锁
A14: 锁 | B14: 默认持有者 | C14: 保护动作 | D14: 等待时是否阻塞其他开发
A15: CONTRACT:recipe-version | B15: Root | C15: 共享schema/状态机裁决 | D15: 否
A16: DB_MIGRATION | B16: P14-CONTROL，经Root授权 | C16: 迁移编号、升降级 | D16: 否
A17: MERGE:integration | B17: Root | C17: 集成分支与生成合同 | D17: 否
A18: DEVICE:b0644fb5 | B18: Root/验收者 | C18: OnePlus安装、claim、暂停/恢复、激活、回退 | D18: 否；其他软件任务补位
A19: DEPLOY:seoul | B19: Root/验收者 | C19: 首尔部署与重启 | D19: 否
A20: RELEASE:P14 | B20: 用户+Root | C20: 人工发布/撤销/回退Recipe | D20: 否
A21: SIDE_EFFECT:G3 | B21: 用户+Root | C21: 真实发布、扣费、删除、评价、推广 | D21: 否；相关真实动作等待
A24: P14 当前工作队列
A25: WorkItem | B25: 泳道 | C25: 状态 | D25: Agent/分支 | E25: owned_paths | F25: 只读输入 | G25: 所需锁 | H25: 独立交付 | I25: 独立验证 | J25: 合并/真实验收 | K25: 证据目录
A26: P14-PREFLIGHT | B26: ROOT | C26: COMPLETE | D26: Root / integration/p14-20260909 | E26: 计划、合同裁决、集成基线 | F26: 当前git状态与P14证据 | G26: CONTRACT:recipe-version | H26: 审核当前改动；建立可恢复共同SHA；创建3个worktree | I26: 基线文件清单/分支可见性 | J26: 完成后同批派发三个子智能体 | K26: artifacts/tasks/P14-multi-agent/PREFLIGHT/
A27: P14-WEB-T041 | B27: WEB | C27: ACCEPTED | D27: 子智能体 / agent/p14-web-t041 | E27: apps/web/** | F27: 冻结API fixture | G27: 无 | H27: 人工发布/回退页面、权限与状态展示 | I27: Web unit/typecheck/build | J27: Root最终验证真实用户点击 | K27: artifacts/tasks/P14-multi-agent/P14-WEB-T041/
A28: P14-CONTROL-VERSION | B28: CONTROL | C28: ACCEPTED | D28: 子智能体 / agent/p14-api-version-pin | E28: services/control-api/**；相关后端测试；唯一迁移 | F28: contracts/phase1/** | G28: CONTRACT；DB_MIGRATION | H28: claim持久固定版本；单active；旧版授权；显式回退与审计 | I28: 迁移升降级/API/claim/并发测试 | J28: 合并第一位；输出冻结fixture | K28: artifacts/tasks/P14-multi-agent/P14-CONTROL-VERSION/
A29: P14-ANDROID-LIFECYCLE | B29: ANDROID | C29: ACCEPTED | D29: 子智能体 / agent/p14-android-lifecycle | E29: mobile/companion/** | F29: 冻结Recipe/Command fixture | G29: 无（真机锁由Root持有） | H29: 原子下载验签、空闲激活、版本固定、断点/离线旧版、回退 | I29: Android定向测试/assembleDebug | J29: 合并第二位；不得自行发真机任务 | K29: artifacts/tasks/P14-multi-agent/P14-ANDROID-LIFECYCLE/
A30: P14-INTEGRATION-ACCEPTANCE | B30: INTEGRATION | C30: ACCEPTED | D30: Root | E30: 集成分支、生成合同、最终evidence | F30: 三个子分支 | G30: MERGE；RELEASE；DEVICE | H30: 同一SHA跨端通过 | I30: 后端+Android+Web全套相关测试 | J30: 网页人工发布→签名版本执行→固定/断点/回退/审计 | K30: artifacts/tasks/P14-multi-agent/P14-INTEGRATION-ACCEPTANCE/
A33: 空槽补位池
A34: 优先级 | B34: 候选 | C34: 可并行内容 | D34: 冲突边界 | E34: 状态触发
A35: 1 | B35: P08 | C35: 同task恢复的软件测试/证据整理 | D35: 真机阶段与P14共用DEVICE锁 | E35: P14任一路WAIT_LOCK/WAIT_AUTH
A36: 2 | B36: P16 | C36: 媒体接口与上传UI按后端/Web拆分 | D36: 合同与services.py需单owner | E36: 存在互斥写集和冻结fixture
A37: 3 | B37: P40 | C37: 违禁词DTO/服务与Web入口 | D37: 不静默修改原文，不绕G3 | E37: P14等待构建或设备
A38: 4 | B38: P48 | C38: 公网/TURN/环境只读探测 | D38: 部署/重启需DEPLOY锁 | E38: 环境只读通道可用
